Workbook

Sheet Resumo 2026
A3: Processos em andamento | B3: Data: 06/04/2026
A4: Analista | B4: Senioridade/cargo | C4: Ag booking | D4: Ag embarque | E4: Embarcado | F4: Ag faturamento | G4: Total | H4: Meta
A5: Matheus Bourscheid | B5: Junior | C5: 7 | D5: 6 | E5: 38 | F5: 11 | G5: =SUM(C5:F5) -> 62 | H5: 70- 80 | I5: férias
A6: Tiago Schneider | B6: Senior | C6: 24 | D6: 25 | E6: 63 | F6: 20 | G6: =SUM(C6:F6) -> 132 | H6: 110-140
A7: Enila Kawely | B7: Senior | C7: 28 | D7: 14 | E7: 35 | F7: 27 | G7: =SUM(C7:F7) -> 104 | H7: 110-140 | I7: retorno de férias | M7: 640 | N7: 100
A8: Bruna Kelsch | B8: Senior | C8: 24 | D8: 14 | E8: 37 | F8: =56-37 -> 19 | G8: =SUM(C8:F8) -> 94 | H8: 110-140 | M8: 530 | N8: =M8*N7/M7 -> 82.8125
A9: Mariana Piccini | B9: Pleno | C9: 8 | D9: 8 | E9: 0 | F9: 1 | G9: =SUM(C9:F9) -> 17 | H9: 80-110 | I9: Inicio em 16/03
A10: Graziele Meytre | B10: Junior | C10: 0 | D10: 0 | E10: 0 | F10: 0 | G10: =SUM(C10:F10) -> 0 | H10: 70-80
A11: Kailane Claudino | B11: Assistente | C11: 0 | D11: 0 | E11: 0 | F11: 0 | G11: =SUM(C11:F11) -> 0 | H11: 010-20
A12: Manuela Silva | B12: Assistente | C12: 0 | D12: 0 | E12: 0 | F12: 0 | G12: =SUM(C12:F12) -> 0 | H12: 010-20
A13: Gabriel Hilgert | B13: Coordenador | C13: 0 | D13: 0 | E13: 0 | F13: 0 | G13: =SUM(C13:F13) -> 0 | H13: 0
A14: Matheus Ropelato | B14: Supervisor | C14: 18 | D14: 23 | E14: 38 | F14: 25 | G14: =SUM(C14:F14) -> 104 | H14: 0
G15: =SUM(G5:G14) -> 513
H16: minimo | I16: MÁXIMO
H17: =70+110+110+110+80+70+10+10 -> 570 | I17: =80+140+140+140+110+80+20+20 -> 730
A18: Chegadas confirmadas por mês: | B18: 1 | C18: 2 | D18: 3 | E18: 4 | F18: 5 | G18: 6 | H18: 7 | I18: 8 | J18: 9 | K18: 10 | L18: 11 | M18: 12 | N18: 12
A19: Analista | B19: Janeiro | C19: Fevereiro | D19: Março | E19: Abril | F19: Maio | G19: Junho | H19: Julho | I19: Agosto | J19: Setembro | K19: Outubro | L19: Novembro | M19: Dezembro | N19: Total
A20: Matheus Bourscheid | B20: =SUMIFS('Faturados 2026 HS'!$A:$A,'Faturados 2026 HS'!$AU:$AU,'Resumo 2026'!B$18,'Faturados 2026 HS'!$BA:$BA,'Resumo 2026'!$A20) -> 60 | C20: =SUMIFS('Faturados 2026 HS'!$A:$A,'Faturados 2026 HS'!$AU:$AU,'Resumo 2026'!C$18,'Faturados 2026 HS'!$BA:$BA,'Resumo 2026'!$A20) -> 66 | D20: =SUMIFS('Faturados 2026 HS'!$A:$A,'Faturados 2026 HS'!$AU:$AU,'Resumo 2026'!D$18,'Faturados 2026 HS'!$BA:$BA,'Resumo 2026'!$A20) -> 46 | N20: =SUM(B20:M20) -> 172
A21: Tiago Schneider | B21: =SUMIFS('Faturados 2026 HS'!$A:$A,'Faturados 2026 HS'!$AU:$AU,'Resumo 2026'!B$18,'Faturados 2026 HS'!$BA:$BA,'Resumo 2026'!$A21) -> 67 | C21: =SUMIFS('Faturados 2026 HS'!$A:$A,'Faturados 2026 HS'!$AU:$AU,'Resumo 2026'!C$18,'Faturados 2026 HS'!$BA:$BA,'Resumo 2026'!$A21) -> 47 | D21: =SUMIFS('Faturados 2026 HS'!$A:$A,'Faturados 2026 HS'!$AU:$AU,'Resumo 2026'!D$18,'Faturados 2026 HS'!$BA:$BA,'Resumo 2026'!$A21) -> 73 | N21: =SUM(B21:M21) -> 187
A22: Enila Kawely | B22: =SUMIFS('Faturados 2026 HS'!$A:$A,'Faturados 2026 HS'!$AU:$AU,'Resumo 2026'!B$18,'Faturados 2026 HS'!$BA:$BA,'Resumo 2026'!$A22) -> 45 | C22: =SUMIFS('Faturados 2026 HS'!$A:$A,'Faturados 2026 HS'!$AU:$AU,'Resumo 2026'!C$18,'Faturados 2026 HS'!$BA:$BA,'Resumo 2026'!$A22) -> 36 | D22: =SUMIFS('Faturados 2026 HS'!$A:$A,'Faturados 2026 HS'!$AU:$AU,'Resumo 2026'!D$18,'Faturados 2026 HS'!$BA:$BA,'Resumo 2026'!$A22) -> 29 | N22: =SUM(B22:M22) -> 110
A23: Bruna Kelsch | B23: =SUMIFS('Faturados 2026 HS'!$A:$A,'Faturados 2026 HS'!$AU:$AU,'Resumo 2026'!B$18,'Faturados 2026 HS'!$BA:$BA,'Resumo 2026'!$A23) -> 48 | C23: =SUMIFS('Faturados 2026 HS'!$A:$A,'Faturados 2026 HS'!$AU:$AU,'Resumo 2026'!C$18,'Faturados 2026 HS'!$BA:$BA,'Resumo 2026'!$A23) -> 57 | D23: =SUMIFS('Faturados 2026 HS'!$A:$A,'Faturados 2026 HS'!$AU:$AU,'Resumo 2026'!D$18,'Faturados 2026 HS'!$BA:$BA,'Resumo 2026'!$A23) -> 55 | N23: =SUM(B23:M23) -> 160
A24: Annie Audrien | B24: =SUMIFS('Faturados 2026 HS'!$A:$A,'Faturados 2026 HS'!$AU:$AU,'Resumo 2026'!B$18,'Faturados 2026 HS'!$BA:$BA,'Resumo 2026'!$A24) -> 29 | C24: =SUMIFS('Faturados 2026 HS'!$A:$A,'Faturados 2026 HS'!$AU:$AU,'Resumo 2026'!C$18,'Faturados 2026 HS'!$BA:$BA,'Resumo 2026'!$A24) -> 21 | D24: =SUMIFS('Faturados 2026 HS'!$A:$A,'Faturados 2026 HS'!$AU:$AU,'Resumo 2026'!D$18,'Faturados 2026 HS'!$BA:$BA,'Resumo 2026'!$A24) -> 4 | N24: =SUM(B24:M24) -> 54
A25: Graziele Meytre | B25: =SUMIFS('Faturados 2026 HS'!$A:$A,'Faturados 2026 HS'!$AU:$AU,'Resumo 2026'!B$18,'Faturados 2026 HS'!$BA:$BA,'Resumo 2026'!$A25) -> 0 | C25: =SUMIFS('Faturados 2026 HS'!$A:$A,'Faturados 2026 HS'!$AU:$AU,'Resumo 2026'!C$18,'Faturados 2026 HS'!$BA:$BA,'Resumo 2026'!$A25) -> 0 | D25: =SUMIFS('Faturados 2026 HS'!$A:$A,'Faturados 2026 HS'!$AU:$AU,'Resumo 2026'!D$18,'Faturados 2026 HS'!$BA:$BA,'Resumo 2026'!$A25) -> 0 | N25: =SUM(B25:M25) -> 0
A26: Kailane Claudino | B26: =SUMIFS('Faturados 2026 HS'!$A:$A,'Faturados 2026 HS'!$AU:$AU,'Resumo 2026'!B$18,'Faturados 2026 HS'!$BA:$BA,'Resumo 2026'!$A26) -> 0 | C26: =SUMIFS('Faturados 2026 HS'!$A:$A,'Faturados 2026 HS'!$AU:$AU,'Resumo 2026'!C$18,'Faturados 2026 HS'!$BA:$BA,'Resumo 2026'!$A26) -> 0 | D26: =SUMIFS('Faturados 2026 HS'!$A:$A,'Faturados 2026 HS'!$AU:$AU,'Resumo 2026'!D$18,'Faturados 2026 HS'!$BA:$BA,'Resumo 2026'!$A26) -> 0 | N26: =SUM(B26:M26) -> 0 | P26: =N29 -> 2
A27: Manuela Silva | B27: =SUMIFS('Faturados 2026 HS'!$A:$A,'Faturados 2026 HS'!$AU:$AU,'Resumo 2026'!B$18,'Faturados 2026 HS'!$BA:$BA,'Resumo 2026'!$A27) -> 0 | C27: =SUMIFS('Faturados 2026 HS'!$A:$A,'Faturados 2026 HS'!$AU:$AU,'Resumo 2026'!C$18,'Faturados 2026 HS'!$BA:$BA,'Resumo 2026'!$A27) -> 0 | D27: =SUMIFS('Faturados 2026 HS'!$A:$A,'Faturados 2026 HS'!$AU:$AU,'Resumo 2026'!D$18,'Faturados 2026 HS'!$BA:$BA,'Resumo 2026'!$A27) -> 0 | N27: =SUM(B27:M27) -> 0
A28: Mariana Piccini | B28: =SUMIFS('Faturados 2026 HS'!$A:$A,'Faturados 2026 HS'!$AU:$AU,'Resumo 2026'!B$18,'Faturados 2026 HS'!$BA:$BA,'Resumo 2026'!$A28) -> 0 | C28: =SUMIFS('Faturados 2026 HS'!$A:$A,'Faturados 2026 HS'!$AU:$AU,'Resumo 2026'!C$18,'Faturados 2026 HS'!$BA:$BA,'Resumo 2026'!$A28) -> 0 | D28: =SUMIFS('Faturados 2026 HS'!$A:$A,'Faturados 2026 HS'!$AU:$AU,'Resumo 2026'!D$18,'Faturados 2026 HS'!$BA:$BA,'Resumo 2026'!$A28) -> 0
A29: Gabriel Hilgert | B29: =SUMIFS('Faturados 2026 HS'!$A:$A,'Faturados 2026 HS'!$AU:$AU,'Resumo 2026'!B$18,'Faturados 2026 HS'!$BA:$BA,'Resumo 2026'!$A29) -> 0 | C29: =SUMIFS('Faturados 2026 HS'!$A:$A,'Faturados 2026 HS'!$AU:$AU,'Resumo 2026'!C$18,'Faturados 2026 HS'!$BA:$BA,'Resumo 2026'!$A29) -> 2 | D29: =SUMIFS('Faturados 2026 HS'!$A:$A,'Faturados 2026 HS'!$AU:$AU,'Resumo 2026'!D$18,'Faturados 2026 HS'!$BA:$BA,'Resumo 2026'!$A29) -> 0 | N29: =SUM(B29:M29) -> 2
A30: Matheus Ropelato | B30: =SUMIFS('Faturados 2026 HS'!$A:$A,'Faturados 2026 HS'!$AU:$AU,'Resumo 2026'!B$18,'Faturados 2026 HS'!$BA:$BA,'Resumo 2026'!$A30) -> 48 | C30: =SUMIFS('Faturados 2026 HS'!$A:$A,'Faturados 2026 HS'!$AU:$AU,'Resumo 2026'!C$18,'Faturados 2026 HS'!$BA:$BA,'Resumo 2026'!$A30) -> 57 | D30: =SUMIFS('Faturados 2026 HS'!$A:$A,'Faturados 2026 HS'!$AU:$AU,'Resumo 2026'!D$18,'Faturados 2026 HS'!$BA:$BA,'Resumo 2026'!$A30) -> 34 | N30: =SUM(B30:M30) -> 139
A31: Total Mês | B31: =SUM(B20:B30) -> 297 | C31: =SUM(C20:C30) -> 286 | D31: =SUM(D20:D30) -> 241 | E31: =SUM(E20:E30) -> 0 | F31: =SUM(F20:F30) -> 0 | G31: =SUM(G20:G30) -> 0 | H31: =SUM(H20:H30) -> 0 | I31: =SUM(I20:I30) -> 0 | ... N31: =SUM(N20:N30) -> 824
A33: Analista Senior: 110 - 140 (Bruna Kelsch, Enila Kawely, Tiago Schneider)
A34: Analista Pleno : 80-110 (não temos ninguém no momento)
A35: Analista Junior: 70-80 (Matheus Bourscheid, Graziele Meytre)
A36: Assistentes: 10 - 20 (Kailane Claudino e Manuela Silva)
F41: 94.16 | G41: 90.31 | H41: 98.09 | I41: 92.66 | J41: 100 | K41: 98.59

Sheet Faturados 2026 HS
D1: Nº processo house | E1: Cliente | F1: Notify | G1: Exportador | H1: ETD/ATD | I1: ETA/ATA | J1: Incoterm | K1: Nº conhecimento master | L1: Data processo | M1: Data abertura processo | N1: Situação embarque | O1: Companhia de transporte | P1: Conhecimentos | Q1: Origem | R1: Previsão início | S1: Navio | T1: Destino | U1: Navio transbordo | V1: Cliente - CNPJ | W1: Cliente Classificação | X1: Importador | Y1: Agente origem | Z1: Ref. cliente | AA1: Modalidade pgto. master | AB1: Ref. externa | AC1: Ref. interna | AD1: Tipo frete | AE1: Situação pagamento | AF1: Situação recebimento | AG1: Situação acerto agente | AH1: Situação CCT | AI1: Tipo do processo | AJ1: Metros cúbicos | AK1: Peso bruto | AL1: Peso cubado | AM1: Peso taxado | AN1: Tipo carga | AO1: Total container 20' | AP1: Total container 40' | AQ1: Equipamentos | AR1: Peso considerado | AS1: Data liberado faturamento | AT1: Data faturado | AU1: MÊS | AV1: Despachante | AW1: Data término | AX1: Números de embarque | AY1: Número oferta | AZ1: Containers | BA1: OPERACIONAL | BB1: FINANCEIRO OPERACIONAL | BC1: Número courrier | BD1: Lucro bruto momento processo | BE1: Lucro estimado corrente | BF1: Total pagamento processo | BG1: Total pago processo | BH1: Total recebimento processo | BI1: Total recebido processo | BJ1: Nível serviço | BK1: Data último acompanhamento | BL1: Tota pagamento corrente | BM1: Total pago corrente | BN1: Total recebimento corrente | BO1: Total recebido corrente | BP1: Previsão último desembarque | BQ1: Data último desembarque | BR1: Total TEUS | BS1: Tipo serviço aéreo | BT1: Situação tracking viagens | BU1: Seguro | BV1: Importância segurada | BW1: % seguro | BX1: Ativo | BY1: Ativo
A2: 1 | B2: Marítimo importação | C2: Back to back | D2: IM2307-25 | E2: VERALLIA BRASIL S.A. | F2: VERALLIA BRASIL S.A. | G2: CHINA BRIDGE HOLDINGS LIMITED | H2: 45998 | I2: 45665 | J2: FOB | K2: PSLSHASTS03736 | L2: 45978.66 | M2: 45978.66 | N2: Desembarcado | O2: KINGSHIP LINE LTDA | P2: SWS2511079 | Q2: SHANGHAI | S2: COSCO SHIPPING BRAZIL | T2: SANTOS | V2: 60.853.942/0013-88 | X2: VERALLIA BRASIL S.A. | Y2: (LCL) SHENZHEN SMOOTHWIN INTERNATIONAL | Z2: 5502170931 + 5502170928 | AA2: Collect | AB2: IM2307-25 | AE2: Parcialmente pago | AF2: Parcialmente recebido | AG2: Quitado | AH2: Não aplicável | AJ2: 1.585 | AK2: 3420 | AL2: 1585 | AN2: LCL | AO2: 0 | AP2: 0 | AR2: 3.42 | AS2: 46041 | AT2: 46041 | AU2: =MONTH(AT2) -> 1 | AY2: PF006185/25-01 | AZ2: SEGU9496518 | BA2: Tiago Schneider | BB2: Mariana Reis | BD2: 511.92 | BE2: 2839.95 | BF2: 30.66 | BG2: 28.94 | BH2: 542.58 | BI2: 275.04 | BK2: 46036.717 | BL2: 165.65 | BM2: 153.47 | BN2: 3005.6 | BO2: 1492.56 | BP2: 46030 | BQ2: 45665 | BR2: 0 | BT2: Sincronizado | BU2: Falso | BW2: 0 | BX2: Ativo | BY2: Ativo
A3: 1 | B3: Marítimo importação | C3: Back to back | D3: IM2308-25 | E3: VERALLIA BRASIL S.A. | F3: VERALLIA BRASIL S.A. | G3: CHINA BRIDGE HOLDINGS LIMITED | H3: 45998 | I3: 45665 | J3: FOB | K3: PSLSHASTS03735 | L3: 45978.664 | M3: 45978.664 | N3: Desembarcado | O3: KINGSHIP LINE LTDA | P3: SWS2511077 | Q3: SHANGHAI | S3: COSCO SHIPPING BRAZIL | T3: SANTOS | V3: 60.853.942/0007-30 | X3: VERALLIA BRASIL S.A. | Y3: (LCL) SHENZHEN SMOOTHWIN INTERNATIONAL | Z3: 5502173651 | AA3: Prepaid | AB3: IM2308-25 | AE3: Pago | AF3: Recebido | AG3: Quitado | AH3: Não aplicável | AJ3: 0.701 | AK3: 960 | AL3: 701 | AN3: LCL | AO3: 0 | AP3: 0 | AR3: 1 | AS3: 46045 | AT3: 46057 | AU3: =MONTH(AT3) -> 2 | AY3: PF006188/25-01 | AZ3: SEGU9496518 | BA3: Tiago Schneider | BB3: Mariana Reis | BD3: 169.35 | BE3: 955.27 | BF3: 590.35 | BG3: 590.35 | BH3: 759.7 | BI3: 759.7 | BK3: 46045.708 | BL3: 3259.2 | BM3: 3256.75 | BN3: 4214.47 | BO3: 4214.47 | BR3: 0 | BT3: Divergência viagens | BU3: Falso | BW3: 0 | BX3: Ativo | BY3: Ativo
A4: 1 | B4: Aéreo importação | C4: Back to back | D4: IA0455-25 | E4: SANDENNI INDUSTRIA & COMÉRCIO DE ARTIGOS OPTICOS LTDA | F4: SANDENNI INDUSTRIA & COMÉRCIO DE ARTIGOS OPTICOS LTDA | G4: WENZHOU GLASSES SHARE INDUSTRY DEVELOPMENT CO.,LTD | H4: 45911 | I4: 45917 | J4: EXW | K4: 016-77798140 | L4: 45905.401 | M4: 45905.401 | N4: Desembarcado | O4: UNITED AIRLINES | P4: BQDA2509005 | Q4: PEQUIM (BEIJING) | T4: GUARULHOS | V4: 19.090.436/0001-47 | X4: WINNING TRADING S.A. (SC) | Y4: BVL - BON VOYAGE LOGISTICS INC. | Z4: IMP.013/2025 - ILOG 3429/25 - ANTIGO IA0338-25 | AA4: Prepaid | AB4: 3429/25 | AE4: Pago | AF4: Recebido | AG4: Quitado | AH4: Desconsolidado | AJ4: 10.05 | AK4: 1700 | AL4: 1675 | AM4: 1700 | AN4: Aéreo | AR4: 1700 | AS4: 46043 | AT4: 46044 | AU4: =MONTH(AT4) -> 1 | AV4: LEADER LOGISTICS LTDA FILIAL ITJ | AY4: PF003135/25-10 | BA4: Annie Audrien | BD4: 343.01 | BE4: 2602.31 | BF4: 14196.48 | BG4: 14196.48 | BH4: 14539.49 | BI4: 14539.49 | BK4: 46043.735 | BL4: 78326.72 | BM4: 76945.08 | BN4: 80929.03 | BO4: 80929.03 | BP4: 45919.75 | BQ4: 45919.39 | BT4: Tracking inativo | BU4: Falso | BW4: 0 | BX4: Ativo | BY4: Ativo
A5: 1 | B5: Marítimo importação | C5: Back to back | D5: IM1496-25 | E5: OVERSEAS NETWORK SALES & MARKETING | F5: ENDURANCE COMERCIO ATACADISTA DE ARTIGOS PARA PRESENTES LTDA | G5: BAITAIXING SUPPLY CHAIN CO.,LIMITED | H5: 45896 | I5: 45931 | J5: CFR | K5: EGLV149505987694 | L5: 45889.604 | M5: 45889.604 | N5: Desembarcado | O5: EVERGREEN | P5: CSZ2508567 | Q5: YANTIAN | S5: EVER FAST | T5: NAVEGANTES | X5: ENDURANCE COMERCIO ATACADISTA DE ARTIGOS PARA PRESENTES LTDA | Y5: SHENZHEN SUPERSONIC CARGO, CO., LTD. | Z5: CSZ2508567 | AB5: IM1496-25 | AE5: Pago | AF5: Recebido | AG5: Sem acerto com agente | AH5: Não aplicável | AL5: 0 | AN5: FCL | AO5: 0 | AP5: 1 | AQ5: 40 HIGH CUBE | AR5: 0 | AS5: 46022 | AT5: 46029 | AU5: =MONTH(AT5) -> 1 | AY5: PF004090/25-01 | AZ5: TGBU5829514 | BA5: Bruna Kelsch | BD5: 634.93 | BE5: 3336.88 | BF5: 545.08 | BG5: 545.08 | BH5: 1180.01 | BI5: 1180.01 | BK5: 46022.383 | BL5: 3243.25 | BM5: 3243.25 | BN5: 6580.13 | BO5: 6580.13 | BP5: 45931 | BQ5: 45931 | BR5: 2 | BT5: Sincronizado | BU5: Falso | BW5: 0 | BX5: Ativo | BY5: Ativo
A6: 1 | B6: Demurrage | C6: Back to back | D6: DEMU0104-25 | E6: HD IMPORTADORA E DISTRIBUIDORA LTDA | F6: HD IMPORTADORA E DISTRIBUIDORA LTDA | G6: SHANDONG JINPENG GRINDING MATERIAL & TOOLS CO., LTD | H6: 45850.99 | I6: 45939 | J6: FOB | K6: ONEYTA5PV1521500 | L6: 45967.694 | M6: 45967.694 | N6: Desembarcado | O6: ONE | P6: KDSY25070012 | Q6: QINGDAO | S6: HMM OSLO | T6: PARANAGUA | U6: ONE PARANA | V6: 33.492.169/0001-65 | X6: HD IMPORTADORA E DISTRIBUIDORA LTDA | Y6: REACH LOGISTICS CO., LTD | Z6: 375667+381540 HD - IM1117-25 | AA6: Prepaid | AB6: DEMU0104-25 | AE6: Sem pagamento | AF6: Sem recebimento | AG6: Sem acerto com agente | AH6: Não aplicável | AL6: 0 | AN6: FCL | AO6: 0 | AP6: 3 | AQ6: 40 NOR | AR6: 0 | AT6: 46034 | AU6: =MONTH(AT6) -> 1 | AV6: Grupo Pinho | AY6: PF002997/25-03 | AZ6: BMOU9863811, OTPU6395803, TGHU9947522 | BA6: Matheus Bourscheid | BD6: 2444.4 | BE6: 13049.58 | BF6: 2325.6 | BG6: 2325.6 | BH6: 4770 | BI6: 4770 | BK6: 46010.585 | BL6: 13628.02 | BM6: 13628.02 | BN6: 26677.6 | BO6: 26677.6 | BP6: 45939 | BR6: 6 | BT6: Tracking inativo | BU6: Falso | BW6: 0 | BX6: Ativo | BY6: Ativo
A7: 1 | B7: Marítimo importação | C7: Back to back | D7: IM1770-25 | E7: OVERSEAS NETWORK SALES & MARKETING | F7: Ceres Atacadista Ltda | G7: ZHEJIANG PINZHONG IMP.& EXP.CO.,LIMITED | H7: 45902 | I7: 45939.892 | J7: CFR | K7: NGP2812555 | L7: 45918.602 | M7: 45918.602 | N7: Desembarcado | O7: COMPAGNIE GENERALE MARITIME - CMA CGM | P7: NGBNVT25090034 | Q7: NINGBO | S7: EVER FUTURE | T7: ITAJAI | X7: Ceres Atacadista Ltda | Y7: RPCARGO INTERNATIONAL FORWARDING (NINGBO) CO., LTD. | Z7: NGBNVT25090034 | AB7: IM1770-25 | AE7: Pago | AF7: Recebido | AG7: Sem acerto com agente | AH7: Não aplicável | AL7: 0 | AN7: FCL | AO7: 0 | AP7: 1 | AQ7: 40 HIGH CUBE | AR7: 0 | AS7: 46043 | AT7: 46044 | AU7: =MONTH(AT7) -> 1 | AY7: PF004843/25-01 | AZ7: TCKU6180214 | BA7: Bruna Kelsch | BD7: 601.45 | BE7: 3381.02 | BF7: 367.97 | BG7: 367.97 | BH7: 969.42 | BI7: 969.42 | BK7: 46043.769 | BL7: 2024.78 | BM7: 2024.78 | BN7: 5405.8 | BO7: 5405.8 | BP7: 45939.892 | BQ7: 45939.892 | BR7: 2 | BT7: Sincronizado | BU7: Falso | BW7: 0 | BX7: Ativo | BY7: Ativo
A8: 1 | B8: Aéreo importação | C8: Back to back | D8: IA0587-25 | E8: HENRICH & CIA LTDA | F8: HENRICH & CIA LTDA | G8: HONGKONG FUHENG LEATHER TRADE PTY LIMITED | H8: 45964 | I8: 45971 | J8: COURIER | K8: 9767764075 | L8: 45959.752 | M8: 45959.752 | N8: Desembarcado | O8: DHL | P8: 9767764075 | Q8: DONGGUAN | T8: PORTO ALEGRE | V8: 89.238.133/0001-04 | X8: HENRICH & CIA LTDA | Y8: LEADER LOGISTICS LTDA FILIAL ITJ | Z8: SAMPLE ORDER 0200/25 | AA8: Collect | AB8: IA0587-25 | AE8: Parcialmente pago | AF8: Recebido | AG8: Sem acerto com agente | AH8: Sem vínculo master | AJ8: 0.036 | AK8: 5 | AL8: 6 | AM8: 0.5 | AN8: Aéreo | AR8: 6 | AS8: 46045 | AT8: 46045 | AU8: =MONTH(AT8) -> 1 | AY8: PF005854/25-01 | BA8: Matheus Bourscheid | BD8: 56.69 | BE8: 418.96 | BF8: 667.93 | BG8: 665.02 | BH8: 724.62 | BI8: 724.62 | BK8: 46044.584 | BL8: 3677.69 | BM8: 3661.24 | BN8: 4096.65 | BO8: 4096.65 | BP8: 45973 | BQ8: 45971 | BT8: Tracking inativo | BU8: Falso | BW8: 0 | BX8: Ativo | BY8: Ativo
A9: 1 | B9: Aéreo importação | C9: Back to back | D9: IA0543-25 | E9: HENRICH & CIA LTDA | F9: HENRICH & CIA LTDA | G9: PRIME INTERNATIONAL INDIA PVT. LTD. | H9: 45962 | I9: 45971 | J9: COURIER | K9: 2512397005 | L9: 45944.724 | M9: 45944.724 | N9: Desembarcado | O9: DHL | P9: 2512397005 | Q9: DELHI | T9: PORTO ALEGRE | V9: 89.238.133/0001-04 | X9: HENRICH & CIA LTDA | Y9: LEADER LOGISTICS LTDA FILIAL ITJ | Z9: SAMPLE ORDER 0199/25 (PT1) - PRI/25-26/327 | AA9: Collect | AB9: IA0543-25 | AE9: Parcialmente pago | AF9: Recebido | AG9: Sem acerto com agente | AH9: Sem vínculo master | AJ9: 0.011 | AK9: 7 | AL9: 1.875 | AM9: 7 | AN9: Aéreo | AR9: 7 | AS9: 46045 | AT9: 46045 | AU9: =MONTH(AT9) -> 1 | AY9: PF005883/25-01 | BA9: Matheus Bourscheid | BD9: 113.69 | BE9: 713.68 | BF9: 268.93 | BG9: 263.4 | BH9: 382.62 | BI9: 382.62 | BK9: 46044.569 | BL9: 1449.48 | BM9: 1418.22 | BN9: 2163.16 | BO9: 2163.16 | BP9: 45971 | BQ9: 45971 | BT9: Tracking inativo | BU9: Falso | BW9: 0 | BX9: Ativo | BY9: Ativo
A10: 1 | B10: Aéreo importação | C10: Back to back | D10: IA0589-25 | E10: HENRICH & CIA LTDA | F10: HENRICH & CIA LTDA | G10: PRIME INTERNATIONAL INDIA PVT. LTD. | H10: 45962 | I10: 45971 | J10: COURIER | K10: 2512408485 | L10: 45961.676 | M10: 45961.676 | N10: Desembarcado | O10: DHL | P10: 2512408485 | Q10: DELHI | T10: PORTO ALEGRE | V10: 89.238.133/0001-04 | X10: HENRICH & CIA LTDA | Y10: LEADER LOGISTICS LTDA FILIAL ITJ | Z10: SAMPLE ORDER 0199/25 (PT2) - PRI/25-26/328 | AA10: Collect | AB10: IA0589-25 | AE10: Parcialmente pago | AF10: Recebido | AG10: Sem acerto com agente | AH10: Sem vínculo master | AJ10: 0.011 | AK10: 4.8 | AL10: 1.875 | AM10: 5 | AN10: Aéreo | AR10: 4.8 | AS10: 46045 | AT10: 46045 | AU10: =MONTH(AT10) -> 1 | AY10: PF005885/25-01 | BA10: Matheus Bourscheid | BD10: 88.22 | BE10: 576.39 | BF10: 685.56 | BG10: 671.74 | BH10: 773.78 | BI10: 773.78 | BK10: 46044.587 | BL10: 3798.17 | BM10: 3720.04 | BN10: 4374.56 | BO10: 4374.56 | BP10: 45972 | BQ10: 45971 | BT10: Tracking inativo | BU10: Falso | BW10: 0 | BX10: Ativo | BY10: Ativo
A11: 1 | B11: Aéreo importação | C11: Back to back | D11: IA0574-25 | E11: HENRICH & CIA LTDA | F11: HENRICH & CIA LTDA | G11: ITALTESSIL DI MARCONCINI S.R.L. - S.A.S. | H11: 45964 | I11: 45972 | J11: EXW | K11: 047-32471972 | L11: 45954.698 | M11: 45954.698 | N11: Desembarcado | O11: TAP | P11: 250900909472 | Q11: SEGRATE (MILAN) | T11: PORTO ALEGRE | V11: 89.238.133/0001-04 | X11: HENRICH & CIA LTDA | Y11: ALISPED S.P.A. | Z11: OC 1267872 | AA11: Prepaid | AB11: IA0574-25 | AE11: Pago | AF11: Recebido | AG11: Quitado | AH11: Desconsolidado | AJ11: 0.975 | AK11: 181.8 | AL11: 300 | AM11: 182 | AN11: Aéreo | AR11: 300 | AS11: 45985 | AT11: 46076 | AU11: =MONTH(AT11) -> 2 | AY11: PF005703/25-01 | BA11: Matheus Bourscheid | BB11: Mariana Reis | BD11: -312.13 | BE11: -1745 | BF11: 1115.93 | BG11: 1115.93 | BH11: 803.8 | BI11: 803.8 | BK11: 45982.723 | BL11: 6905.55 | BM11: 7061.28 | BN11: 5160.55 | BO11: 5160.55 | BP11: 45972 | BQ11: 45972 | BS11: Back to back | BT11: Tracking inativo | BU11: Falso | BV11: 10280 | BW11: 0 | BX11: Ativo | BY11: Ativo
A12: 1 | B12: Aéreo importação | C12: Back to back | D12: IA0599-25 | E12: HENRICH & CIA LTDA | F12: HENRICH & CIA LTDA | G12: PRIME INTERNATIONAL INDIA PVT. LTD. | H12: 45968 | I12: 45978 | J12: COURIER | K12: 2295719333 | L12: 45967.725 | M12: 45967.725 | N12: Desembarcado | O12: DHL | P12: 2295719333 | Q12: DELHI | T12: PORTO ALEGRE | V12: 89.238.133/0001-04 | X12: HENRICH & CIA LTDA | Y12: LEADER LOGISTICS LTDA FILIAL ITJ | Z12: SAMPLE ORDER 0199/25 (PT3) - PRI/25-26/331 | AA12: Collect | AB12: IA0599-25 | AE12: Parcialmente pago | AF12: Recebido | AG12: Sem acerto com agente | AH12: Sem vínculo master | AJ12: 0.011 | AK12: 9.4 | AL12: 1.875 | AM12: 9.4 | AN12: Aéreo | AR12: 9.4 | AS12: 46045 | AT12: 46045 | AU12: =MONTH(AT12) -> 1 | AY12: PF005883/25-01 | BA12: Matheus Bourscheid | BD12: 78.95 | BE12: 647.2 | BF12: 1121.84 | BG12: 1100.42 | BH12: 1200.79 | BI12: 1200.79 | BK12: 46044.591 | BL12: 6141.46 | BM12: 6020.36 | BN12: 6788.66 | BO12: 6788.66 | BP12: 45978 | BQ12: 45978 | BT12: Tracking inativo | BU12: Falso | BW12: 0 | BX12: Ativo | BY12: Ativo
A13: 1 | B13: Demurrage | C13: Back to back | D13: DEMU0118-25 | E13: B. & C. SPEAKERS BRASIL COMERCIO DE EQUIPAMENTOS DE AUDIO LTDA | F13: B. & C. SPEAKERS BRASIL COMERCIO DE EQUIPAMENTOS DE AUDIO LTDA | G13: B&C SPEAKERS S.P.A | H13: 45940 | I13: 45979 | J13: EXW | K13: MEDURL176654 | L13: 46010.621 | M13: 46010.621 | N13: Desembarcado | O13: MSC MEDITERRANEAN SHIPPING DO BRASIL LTDA. | P13: 944723/2025/09 | Q13: LIVORNO | S13: MSC MELINE | T13: NAVEGANTES | V13: 11.330.240/0001-70 | X13: B. & C. SPEAKERS BRASIL COMERCIO DE EQUIPAMENTOS DE AUDIO LTDA | Y13: ALISPED S.P.A. | Z13: SPED-25-01228 + ILOG 4684/25 + IM1866-25 | AB13: DEMU0118-25 | AE13: Sem pagamento | AF13: Sem recebimento | AG13: Sem acerto com agente | AH13: Não aplicável | AL13: 0 | AN13: FCL | AO13: 0 | AP13: 1 | AQ13: 40 HIGH CUBE | AR13: 0 | AT13: 46030 | AU13: =MONTH(AT13) -> 1 | AV13: LEADER LOGISTICS LTDA FILIAL ITJ | AY13: PF005074/25-01 | AZ13: MSMU7761965 | BA13: Matheus Bourscheid | BD13: 420.08 | BE13: 2853.43 | BF13: 0 | BG13: 0 | BH13: 420.08 | BI13: 420.08 | BK13: 46013.664 | BL13: 0 | BM13: 0 | BN13: 2853.43 | BO13: 2853.43 | BP13: 45979 | BR13: 2 | BT13: Tracking inativo | BU13: Falso | BW13: 0 | BX13: Ativo | BY13: Ativo
A14: 1 | B14: Aéreo importação | C14: Back to back | D14: IA0604-25 | E14: HENRICH & CIA LTDA | F14: HENRICH & CIA LTDA | G14: DONGGUAN GRAND ADVANCE TRADING CO.,LTD | H14: 45974 | I14: 45982 | J14: COURIER | K14: 8455006442 | L14: 45968.756 | M14: 45968.756 | N14: Desembarcado | O14: DHL | P14: 8455006442 | Q14: DONGGUAN | T14: PORTO ALEGRE | V14: 89.238.133/0001-04 | X14: HENRICH & CIA LTDA | Y14: LEADER LOGISTICS LTDA FILIAL ITJ | Z14: SAMPLE ORDER 0216/25 | AA14: Collect | AB14: IA0604-25 | AE14: Parcialmente pago | AF14: Recebido | AG14: Sem acerto com agente | AH14: Sem vínculo master | AJ14: 0.013 | AK14: 2.05 | AL14: 2.083 | AM14: 2.05 | AN14: Aéreo | AR14: 2.083 | AS14: 46051 | AT14: 46051 | AU14: =MONTH(AT14) -> 1 | AY14: PF006133/25-01 | BA14: Matheus Bourscheid | BD14: 57.19 | BE14: 383.65 | BF14: 309.21 | BG14: 302.96 | BH14: 366.4 | BI14: 366.4 | BK14: 46051.708 | BL14: 1687.81 | BM14: 1652.48 | BN14: 2071.46 | BO14: 2071.46 | BP14: 45982 | BQ14: 45982 | BT14: Tracking inativo | BU14: Falso | BW14: 0 | BX14: Ativo | BY14: Ativo
A15: 1 | B15: Aéreo importação | C15: Back to back | D15: IA0608-25 | E15: HENRICH & CIA LTDA | F15: HENRICH & CIA LTDA | G15: DONGYI LEATHER (HK) LIMITED | H15: 45973 | I15: 45982 | J15: COURIER | K15: 6489424255 | L15: 45971.723 | M15: 45971.723 | N15: Desembarcado | O15: DHL | P15: 6489424255 | Q15: DONGGUAN | T15: PORTO ALEGRE | V15: 89.238.133/0001-04 | X15: HENRICH & CIA LTDA | Y15: LEADER LOGISTICS LTDA FILIAL ITJ | Z15: SAMPLE ORDER 0212/25 | AA15: Collect | AB15: IA0608-25 | AE15: Parcialmente pago | AF15: Recebido | AG15: Sem acerto com agente | AH15: Sem vínculo master | AJ15: 0.039 | AK15: 5.8 | AL15: 6.5 | AM15: 6.5 | AN15: Aéreo | AR15: 6.5 | AS15: 46051 | AT15: 46051 | AU15: =MONTH(AT15) -> 1 | AY15: PF006095/25-01 | BA15: Matheus Bourscheid | BD15: 47.14 | BE15: 416.72 | BF15: 758.67 | BG15: 743.33 | BH15: 805.81 | BI15: 805.81 | BK15: 46051.706 | BL15: 4138.96 | BM15: 4052.24 | BN15: 4555.68 | BO15: 4555.68 | BP15: 45982 | BQ15: 45982 | BT15: Tracking inativo | BU15: Falso | BW15: 0 | BX15: Ativo | BY15: Ativo
A16: 1 | B16: Demurrage | C16: Back to back | D16: DEMU0121-25 | E16: METALURGICA DE TONI LTDA | F16: METALURGICA DE TONI LTDA | G16: HISENER INDUSTRIAL CO.,LTD | H16: 45936.372 | I16: 45984 | J16: FOB | K16: ONEYSHAFT8272300 | L16: 46010.651 | M16: 46010.651 | N16: Desembarcado | O16: ONE | P16: KDSY25090147 | Q16: SHANGHAI | S16: ONE STRENGTH | T16: RIO GRANDE | U16: HYUNDAI INTEGRAL | V16: 89.041.560/0001-06 | X16: METALURGICA DE TONI LTDA | Y16: REACH LOGISTICS CO., LTD | Z16: 026-25 - Hisener - IM1787-25 | AA16: Collect | AB16: DEMU0121-25 | AE16: Sem pagamento | AF16: Sem recebimento | AG16: Sem acerto com agente | AH16: Não aplicável | AJ16: 21.53 | AK16: 24680.59 | AL16: 21530 | AN16: FCL | AO16: 0 | AP16: 1 | AQ16: 40 NOR | AR16: 24.681 | AT16: 46034 | AU16: =MONTH(AT16) -> 1 | AY16: PF004848/25-02 | AZ16: TTNU8772441 | BA16: Matheus Bourscheid | BD16: 1179.5 | BE16: 6603.02 | BF16: 0 | BG16: 0 | BH16: 1179.5 | BI16: 1179.5 | BK16: 46021.684 | BL16: 0 | BM16: 0 | BN16: 6603.02 | BO16: 6603.02 | BP16: 45984 | BQ16: 45984 | BR16: 2 | BT16: Tracking inativo | BU16: Verdadeiro | BW16: 0 | BX16: Ativo | BY16: Ativo
A17: 1 | B17: Aéreo importação | C17: Back to back | D17: IA0607-25 | E17: HENRICH & CIA LTDA | F17: HENRICH & CIA LTDA | G17: CONCERIA M2 S.R.L. | H17: 45982 | I17: 45987 | J17: COURIER | K17: 5007582440 | L17: 45971.719 | M17: 45971.719 | N17: Desembarcado | O17: DHL | P17: 5007582440 | Q17: MALPENSA (MILAN) | T17: PORTO ALEGRE | V17: 89.238.133/0001-04 | X17: HENRICH & CIA LTDA | Y17: LEADER LOGISTICS LTDA FILIAL ITJ | Z17: SAMPLE ORDER 0219/25 | AA17: Collect | AB17: IA0607-25 | AE17: Pago | AF17: Recebido | AG17: Sem acerto com agente | AH17: Sem vínculo master | AJ17: 0.012 | AK17: 2 | AL17: 2 | AM17: 2 | AN17: Aéreo | AR17: 2 | AS17: 46078 | AT17: 46078 | AU17: =MONTH(AT17) -> 2 | AY17: PF006244/25-01 | BA17: Matheus Bourscheid | BD17: 70.19 | BE17: 332.06 | BF17: 351.67 | BG17: 351.67 | BH17: 421.86 | BI17: 421.86 | BK17: 46078.451 | BL17: 1939.34 | BM17: 1939.34 | BN17: 2271.4 | BO17: 2271.4 | BP17: 45989 | BQ17: 45987 | BT17: Tracking inativo | BU17: Falso | BW17: 0 | BX17: Ativo | BY17: Ativo
A18: 1 | B18: Demurrage | C18: Back to back | D18: DEMU0006-26 | E18: BRX IMPORT E EXPORT LTDA | F18: Self It Academias Holding S.A. | G18: SHUHUASPORTS CO., LTD | H18: 45911 | I18: 45988 | J18: FOB | K18: MEDUYQ162735 | L18: 46024.662 | M18: 46024.662 | N18: Desembarcado | O18: MSC MEDITERRANEAN SHIPPING DO BRASIL LTDA. | P18: ZJQRSE250640R | Q18: XIAMEN | S18: ZIM MOUNT DENALI | T18: Suape | U18: MSC AURIGA | V18: 16.690.730/0001-00 | X18: BRX IMPORT E EXPORT LTDA | Y18: NINGBO QR INTERNATIONAL LOGISTIC CO.,LTD | Z18: BRX-228 - IM1564-25 | AA18: Collect | AB18: DEMU0006-26 | AE18: Sem pagamento | AF18: Sem recebimento | AG18: Sem acerto com agente | AH18: Não aplicável | AL18: 0 | AN18: FCL | AO18: 0 | AP18: 3 | AQ18: 40 HIGH CUBE | AR18: 0 | AT18: 46052 | AU18: =MONTH(AT18) -> 1 | AV18: MasterSul | AY18: PF004206/25-02 | AZ18: CAIU4821351, FFAU2387078, MSDU7221641 | BA18: Matheus Bourscheid | BD18: 2250 | BE18: 12386.18 | BF18: 0 | BG18: 0 | BH18: 2250 | BI18: 2250 | BK18: 46031.73 | BL18: 0 | BM18: 0 | BN18: 12386.18 | BO18: 12386.18 | BP18: 45990 | BR18: 6 | BT18: Tracking inativo | BU18: Falso | BW18: 0 | BX18: Ativo | BY18: Ativo
A19: 1 | B19: Demurrage | C19: Back to back | D19: DEMU0004-26 | E19: BRX IMPORT E EXPORT LTDA | F19: Self It Academias Holding S.A. | G19: SHUHUASPORTS CO., LTD | H19: 45911 | I19: 45988 | J19: FOB | K19: MEDUYQ162727 | L19: 46024.635 | M19: 46024.635 | N19: Desembarcado | O19: MSC MEDITERRANEAN SHIPPING DO BRASIL LTDA. | P19: ZJQRSE250642R | Q19: XIAMEN | S19: ZIM MOUNT DENALI | T19: Suape | U19: MSC AURIGA | V19: 16.690.730/0001-00 | X19: BRX IMPORT E EXPORT LTDA | Y19: NINGBO QR INTERNATIONAL LOGISTIC CO.,LTD | Z19: BRX-230 - IM1563-25 | AA19: Collect | AB19: DEMU0004-26 | AE19: Sem pagamento | AF19: Sem recebimento | AG19: Sem acerto com agente | AH19: Não aplicável | AL19: 0 | AN19: FCL | AO19: 0 | AP19: 3 | AQ19: 40 HIGH CUBE | AR19: 0 | AT19: 46052 | AU19: =MONTH(AT19) -> 1 | AV19: MasterSul | AY19: PF004206/25-02 | AZ19: CAAU7894220, MSDU8248694, MSNU7384572 | BA19: Matheus Bourscheid | BD19: 250 | BE19: 1376.24 | BF19: 0 | BG19: 0 | BH19: 250 | BI19: 250 | BK19: 46031.722 | BL19: 0 | BM19: 0 | BN19: 1376.24 | BO19: 1376.24 | BP19: 45988 | BR19: 6 | BT19: Tracking inativo | BU19: Falso | BW19: 0 | BX19: Ativo | BY19: Ativo
A20: 1 | B20: Demurrage | C20: Back to back | D20: DEMU0005-26 | E20: BRX IMPORT E EXPORT LTDA | F20: Self It Academias Holding S.A. | G20: SHUHUASPORTS CO., LTD | H20: 45911 | I20: 45988 | J20: FOB | K20: MEDUYQ162842 | L20: 46024.65 | M20: 46024.65 | N20: Desembarcado | O20: MSC MEDITERRANEAN SHIPPING DO BRASIL LTDA. | P20: ZJQRSE250641R | Q20: XIAMEN | S20: ZIM MOUNT DENALI | T20: Suape | U20: MSC AURIGA | V20: 16.690.730/0001-00 | X20: BRX IMPORT E EXPORT LTDA | Y20: NINGBO QR INTERNATIONAL LOGISTIC CO.,LTD | Z20: BRX-229 - IM1562-25 | AA20: Collect | AB20: DEMU0005-26 | AE20: Sem pagamento | AF20: Sem recebimento | AG20: Sem acerto com agente | AH20: Não aplicável | AL20: 0 | AN20: FCL | AO20: 0 | AP20: 3 | AQ20: 40 HIGH CUBE | AR20: 0 | AT20: 46052 | AU20: =MONTH(AT20) -> 1 | AV20: MasterSul | AY20: PF004206/25-02 | AZ20: CAAU5105195, MSDU8131590, TCNU3713490 | BA20: Matheus Bourscheid | BD20: 2500 | BE20: 13762.42 | BF20: 0 | BG20: 0 | BH20: 2500 | BI20: 2500 | BK20: 46031.725 | BL20: 0 | BM20: 0 | BN20: 13762.42 | BO20: 13762.42 | BP20: 45988 | BR20: 6 | BT20: Tracking inativo | BU20: Falso | BW20: 0 | BX20: Ativo | BY20: Ativo
A21: 1 | B21: Demurrage | C21: Back to back | D21: DEMU0027-26 | E21: INDUSTRIA DE CALCADOS BEIRA RIO LTDA | F21: INDUSTRIA DE CALCADOS BEIRA RIO LTDA | G21: XIAMEN LONGSHUNDA TRADING CO., LTD | H21: 45957 | I21: 45991 | J21: FOB | K21: MAEU260440519 | L21: 46041.605 | M21: 46041.605 | N21: Desembarcado | O21: MAERSK | P21: KDSY25100010 | Q21: XIAMEN | S21: PANCON CHAMPION | T21: SANTOS | U21: CAP SAN ARTEMISSIO | V21: 43.176.072/0001-05 | X21: INDUSTRIA DE CALCADOS BEIRA RIO LTDA | Y21: REACH LOGISTICS CO., LTD | Z21: KJ20250408 // ILOG: 4458/25 - IM1928-25 | AA21: Collect | AB21: DEMU0027-26 | AE21: Sem pagamento | AF21: Sem recebimento | AG21: Sem acerto com agente | AH21: Não aplicável | AJ21: 50 | AK21: 26380 | AL21: 50000 | AN21: FCL | AO21: 0 | AP21: 1 | AQ21: 40 HIGH CUBE | AR21: 50 | AT21: 46051 | AU21: =MONTH(AT21) -> 1 | AY21: PF005010/25-02 | AZ21: MSKU0814912 | BA21: Matheus Bourscheid | BD21: 1972.64 | BE21: 11313.53 | BF21: 4102.36 | BG21: 4102.36 | BH21: 6075 | BI21: 6075 | BK21: 46043.711 | BL21: 22728.58 | BM21: 22728.58 | BN21: 34042.11 | BO21: 34042.11 | BP21: 45991.292 | BR21: 2 | BT21: Tracking inativo | BU21: Falso | BW21: 0 | BX21: Ativo | BY21: Ativo
A22: 1 | B22: Aéreo importação | C22: Back to back | D22: IA0624-25 | E22: HENRICH & CIA LTDA | F22: HENRICH & CIA LTDA | G22: HUNG HING METAL MANUFACTORY LTD | H22: 45987 | I22: 45992 | J22: COURIER | K22: 3206989015 | L22: 45974.722 | M22: 45974.722 | N22: Desembarcado | O22: DHL | Q22: DONGGUAN | T22: PORTO ALEGRE | V22: 89.238.133/0001-04 | X22: HENRICH & CIA LTDA | Z22: SAMPLE ORDER 0220/25 | AA22: Collect | AB22: IA0624-25 | AE22: Pago | AF22: Recebido | AG22: Sem acerto com agente | AH22: Sem AWB house | AJ22: 0.016 | AK22: 1 | AL22: 2.621 | AM22: 2.5 | AN22: Aéreo | AR22: 2.621 | AS22: 46045 | AT22: 46045 | AU22: =MONTH(AT22) -> 1 | AY22: PF004032/25-01 | BA22: Matheus Bourscheid | BD22: 64.83 | BE22: 414.87 | BF22: 244.98 | BG22: 244.98 | BH22: 309.81 | BI22: 309.81 | BK22: 46044.59 | BL22: 1336.66 | BM22: 1336.66 | BN22: 1751.53 | BO22: 1751.53 | BP22: 45995 | BQ22: 45992 | BT22: Tracking inativo | BU22: Falso | BW22: 0 | BX22: Ativo | BY22: Ativo
A23: 1 | B23: Marítimo importação | C23: Back to back | D23: IM2078-25 | E23: OVERSEAS NETWORK SALES & MARKETING | F23: ENGEL'S GLOBAL COMERCIO EXTERIOR LTDA | G23: YIWU HONGSHENG IMP AND EXP CO., LIMITED | H23: 45958.035 | I23: 45994 | J23: CFR | K23: YMJAB232105572 | L23: 45951.613 | M23: 45951.613 | N23: Desembarcado | O23: YANG MING | P23: UNI25100097 | Q23: NINGBO | S23: COSCO SHIPPING PERU | T23: NAVEGANTES | X23: ENGEL'S GLOBAL COMERCIO EXTERIOR LTDA | Y23: NINGBO UNION NB INTERNATIONAL FREIGHT AGENCY CO.,LTD. | Z23: UNI25100097 | AB23: IM2078-25 | AE23: Pago | AF23: Recebido | AG23: Quitado | AH23: Não aplicável | AL23: 0 | AN23: FCL | AO23: 0 | AP23: 1 | AQ23: 40 HIGH CUBE | AR23: 0 | AS23: 46024 | AT23: 46029 | AU23: =MONTH(AT23) -> 1 | AY23: PF005601/25-01 | AZ23: YMMU6797732 | BA23: Bruna Kelsch | BD23: 534.15 | BE23: 3047.1 | BF23: 364.37 | BG23: 364.37 | BH23: 898.52 | BI23: 898.52 | BK23: 46024.617 | BL23: 2150.39 | BM23: 2150.39 | BN23: 5197.49 | BO23: 5178.46 | BP23: 45994 | BQ23: 45994 | BR23: 2 | BT23: Sincronizado | BU23: Falso | BW23: 0 | BX23: Ativo | BY23: Ativo
A24: 1 | B24: Marítimo importação | C24: Back to back | D24: IM2018-25 | E24: OVERSEAS NETWORK SALES & MARKETING | F24: ENGEL'S GLOBAL COMERCIO EXTERIOR LTDA | G24: YIWU HONGSHENG IMP AND EXP CO., LIMITED | H24: 45960 | I24: 45994 | J24: CFR | K24: EGLV143550143379 | L24: 45945.559 | M24: 45945.559 | N24: Desembarcado | O24: EVERGREEN | P24: UNI25100054 | Q24: NINGBO | S24: KOTA PUSAKA | T24: ITAJAI | X24: ENGEL'S GLOBAL COMERCIO EXTERIOR LTDA | Y24: NINGBO UNION NB INTERNATIONAL FREIGHT AGENCY CO.,LTD. | Z24: UNI25100054 | AB24: IM2018-25 | AE24: Pago | AF24: Recebido | AG24: Quitado | AH24: Não aplicável | AL24: 0 | AN24: FCL | AO24: 0 | AP24: 1 | AQ24: 40 HIGH CUBE | AR24: 0 | AS24: 46022 | AT24: 46029 | AU24: =MONTH(AT24) -> 1 | AY24: PF005448/25-01 | AZ24: TXGU6131372 | BA24: Bruna Kelsch | BD24: 547.33 | BE24: 3107.22 | BF24: 466.19 | BG24: 466.19 | BH24: 1013.52 | BI24: 1013.52 | BK24: 46022.393 | BL24: 2750.02 | BM24: 2750.02 | BN24: 5857.24 | BO24: 5843.71 | BP24: 45999 | BQ24: 45994 | BR24: 2 | BT24: Sincronizado | BU24: Falso | BW24: 0 | BX24: Ativo | BY24: Ativo
A25: 1 | B25: Marítimo importação | C25: Back to back | D25: IM2051-25 | E25: OVERSEAS NETWORK SALES & MARKETING | F25: ENGEL'S GLOBAL COMERCIO EXTERIOR LTDA | G25: YIWU HONGSHENG IMP AND EXP CO., LIMITED | H25: 45963 | I25: 45994 | J25: CFR | K25: EGLV149507446551 | L25: 45950.523 | M25: 45950.523 | N25: Desembarcado | O25: EVERGREEN | P25: CSZ2510566 | Q25: YANTIAN | S25: KOTA PUSAKA | T25: ITAJAI | X25: ENGEL'S GLOBAL COMERCIO EXTERIOR LTDA | Y25: SHENZHEN SUPERSONIC CARGO, CO., LTD. | Z25: CSZ2510566 | AB25: IM2051-25 | AE25: Pago | AF25: Recebido | AG25: Sem acerto com agente | AH25: Não aplicável | AL25: 0 | AN25: FCL | AO25: 0 | AP25: 1 | AQ25: 40 HIGH CUBE | AR25: 0 | AS25: 46022 | AT25: 46029 | AU25: =MONTH(AT25) -> 1 | AY25: PF005561/25-01 | AZ25: EGHU9442583 | BA25: Bruna Kelsch | BD25: 456.29 | BE25: 2571.41 | BF25: 412.23 | BG25: 412.23 | BH25: 868.52 | BI25: 868.52 | BK25: 46030.423 | BL25: 2452.75 | BM25: 2452.75 | BN25: 5024.16 | BO25: 5024.16 | BP25: 45999 | BQ25: 45994 | BR25: 2 | BT25: Sincronizado | BU25: Falso | BW25: 0 | BX25: Ativo | BY25: Ativo
A26: 1 | B26: Marítimo importação | C26: Back to back | D26: IM1993-25 | E26: OVERSEAS NETWORK SALES & MARKETING | F26: ENGEL MACHINERY (SHANGHAI) CO., LTD. | G26: YIWU HONGSHENG IMP AND EXP CO., LIMITED | H26: 45960.801 | I26: 45994 | J26: CFR | K26: OOLU2163052210 | L26: 45943.635 | M26: 45943.635 | N26: Desembarcado | O26: OOCL | P26: TCNB2510328 | Q26: NINGBO | S26: KOTA PUSAKA | T26: ITAJAI | X26: ENGEL'S GLOBAL COMERCIO EXTERIOR LTDA | Y26: XIAMEN TRANS-CHINA LOGISTICS CO. | Z26: TCNB2510328 | AA26: Prepaid | AB26: IM1993-25 | AE26: Pago | AF26: Recebido | AG26: Em aberto | AH26: Não aplicável | AL26: 0 | AN26: FCL | AO26: 0 | AP26: 1 | AQ26: 40 HIGH CUBE | AR26: 0 | AS26: 46022 | AT26: 46029 | AU26: =MONTH(AT26) -> 1 | AY26: PF005389/25-01 | AZ26: OOCU9457365 | BA26: Bruna Kelsch | BD26: 715.6 | BE26: 4158.87 | BF26: 261.69 | BG26: 261.69 | BH26: 977.29 | BI26: 927.29 | BK26: 46042.562 | BL26: 1485 | BM26: 1485 | BN26: 5643.87 | BO26: 5364.16 | BP26: 45996 | BQ26: 45994 | BR26: 2 | BT26: Sincronizado | BU26: Falso | BW26: 0 | BX26: Ativo | BY26: Ativo
A27: 1 | B27: Marítimo importação | C27: Back to back | D27: IM2047-25 | E27: OVERSEAS NETWORK SALES & MARKETING | F27: ENGEL'S GLOBAL COMERCIO EXTERIOR LTDA | G27: YIWU HONGSHENG IMP AND EXP CO., LIMITED | H27: 45963 | I27: 45994 | J27: CFR | K27: EGLV149507446542 | L27: 45950.318 | M27: 45950.318 | N27: Desembarcado | O27: EVERGREEN | P27: CSZ2510562 | Q27: YANTIAN | S27: KOTA PUSAKA | T27: ITAJAI | X27: ENGEL'S GLOBAL COMERCIO EXTERIOR LTDA | Y27: SHENZHEN SUPERSONIC CARGO, CO., LTD. | Z27: CSZ2510562 | AB27: IM2047-25 | AE27: Pago | AF27: Recebido | AG27: Sem acerto com agente | AH27: Não aplicável | AL27: 0 | AN27: FCL | AO27: 0 | AP27: 1 | AQ27: 40 HIGH CUBE | AR27: 0 | AT27: 46108 | AU27: =MONTH(AT27) -> 3 | AY27: PF005545/25-01 | AZ27: EISU9343037 | BA27: Bruna Kelsch | BD27: 615.8 | BE27: 3340.02 | BF27: 456.23 | BG27: 456.23 | BH27: 1072.03 | BI27: 1072.03 | BK27: 46035.654 | BL27: 2715.55 | BM27: 2715.55 | BN27: 6055.57 | BO27: 6055.57 | BP27: 45999 | BQ27: 45994 | BR27: 2 | BT27: Sincronizado | BU27: Falso | BW27: 0 | BX27: Ativo | BY27: Ativo
A28: 1 | B28: Marítimo importação | C28: Back to back | D28: IM2252-25 | E28: OVERSEAS NETWORK SALES & MARKETING | F28: ENGEL'S GLOBAL COMERCIO EXTERIOR LTDA | G28: YIWU HONGSHENG IMP AND EXP CO., LIMITED | H28: 45960 | I28: 45994 | J28: CFR | K28: NGP2953297 | L28: 45971.635 | M28: 45971.635 | N28: Desembarcado | O28: COMPAGNIE GENERALE MARITIME - CMA CGM | P28: NGBNVT25100190 | Q28: NINGBO | S28: KOTA PUSAKA | T28: ITAJAI | X28: ENGEL'S GLOBAL COMERCIO EXTERIOR LTDA | Y28: RPCARGO INTERNATIONAL FORWARDING (NINGBO) CO., LTD. | Z28: NGBNVT25100190 | AB28: IM2252-25 | AE28: Pago | AF28: Recebido | AG28: Sem acerto com agente | AH28: Não aplicável | AJ28: 68 | AK28: 19821.6 | AL28: 68000 | AN28: FCL | AO28: 0 | AP28: 1 | AQ28: 40 HIGH CUBE | AR28: 68 | AT28: 46108 | AU28: =MONTH(AT28) -> 3 | AY28: PF006019/25-01 | AZ28: GESU6274261 | BA28: Bruna Kelsch | BD28: 620.86 | BE28: 3496.78 | BF28: 312.42 | BG28: 312.42 | BH28: 933.28 | BI28: 933.28 | BK28: 46038.726 | BL28: 1775 | BM28: 1775 | BN28: 5271.78 | BO28: 5271.78 | BP28: 45999 | BQ28: 45994 | BR28: 2 | BT28: Tracking inativo | BU28: Falso | BW28: 0 | BX28: Ativo | BY28: Ativo
A29: 1 | B29: Aéreo importação | C29: Back to back | D29: IA0643-25 | E29: CALCADOS RAMARIM LTDA | F29: CALCADOS RAMARIM LTDA | G29: TSAN CHEN TEXTILE TRADING CO., LTD | H29: 45988 | I29: 45995 | J29: EXW | L29: 45985.626 | M29: 45985.626 | N29: Desembarcado | O29: DHL | Q29: TAOYUAN INTL (TAIPEI) | T29: Novo Hamburgo - Cidade | V29: 88.104.328/0001-07 | X29: CALCADOS RAMARIM LTDA | Y29: LEADER LOGISTICS LTDA FILIAL ITJ | Z29: OC 807051 - PI-20251119 | AA29: Collect | AB29: IA0643-25 | AE29: Pago | AF29: Recebido | AG29: Sem acerto com agente | AH29: Sem AWB house | AJ29: 0.015 | AK29: 7.4 | AL29: 2.562 | AM29: 7.5 | AN29: Aéreo | AR29: 7.4 | AS29: 46064 | AT29: 46064 | AU29: =MONTH(AT29) -> 2 | AY29: PF006281/25-01 | BA29: Bruna Kelsch | BD29: 165.32 | BE29: 894.49 | BF29: 696.66 | BG29: 696.66 | BH29: 861.98 | BI29: 861.98 | BK29: 46002.397 | BL29: 3806.8 | BM29: 3806.8 | BN29: 4701.29 | BO29: 4701.29 | BP29: 45996 | BQ29: 45995 | BT29: Tracking inativo | BU29: Falso | BW29: 0 | BX29: Ativo | BY29: Ativo
A30: 1 | B30: Marítimo importação | C30: Back to back | D30: IM1970-25 | E30: BBB COMERCIO ELETRONICO LTDA | F30: BBB COMERCIO ELETRONICO LTDA | G30: SONIFEST S.A | H30: 45960.811 | I30: 45996 | J30: FOB | K30: CMDUNGP2920609 | L30: 45940.427 | M30: 45940.427 | N30: Desembarcado | O30: COMPAGNIE GENERALE MARITIME - CMA CGM | P30: KDSY25100063 | Q30: NINGBO | S30: KOTA PUSAKA | T30: ITAJAI | V30: 34.098.618/0002-39 | X30: BBB COMERCIO ELETRONICO LTDA | Y30: REACH LOGISTICS CO., LTD | Z30: ILOG 4909/25 - L-SON250827 | AA30: Prepaid | AB30: 4909/25 | AE30: Pago | AF30: Recebido | AG30: Quitado | AH30: Não aplicável | AJ30: 50 | AK30: 24420 | AL30: 50000 | AN30: FCL | AO30: 0 | AP30: 1 | AQ30: 40 HIGH CUBE | AR30: 50 | AS30: 46022 | AT30: 46028 | AU30: =MONTH(AT30) -> 1 | AV30: LEADER LOGISTICS LTDA FILIAL ITJ | AY30: PF005318/25-01 | AZ30: CMAU8830267 | BA30: Matheus Bourscheid | BD30: 202.09 | BE30: 1595.63 | BF30: 2448.48 | BG30: 2448.48 | BH30: 2650.57 | BI30: 2650.57 | BK30: 46022.459 | BL30: 13267.5 | BM30: 12910.47 | BN30: 14863.13 | BO30: 14863.13 | BP30: 45996.25 | BQ30: 45996 | BR30: 2 | BT30: Sincronizado | BU30: Falso | BW30: 0 | BX30: Ativo | BY30: Ativo
A31: 1 | B31: Marítimo importação | C31: Back to back | D31: IM1471-25 | E31: CALCADOS RAMARIM LTDA | F31: CALCADOS RAMARIM LTDA | G31: TIEN KANG CO., LTD | H31: 45915 | I31: 45996.264 | J31: EXW | L31: 45887.462 | M31: 45887.462 | N31: Desembarcado | O31: MSL | P31: LHKTCG-25090344RIG | Q31: TAICHUNG | S31: KANWAY GLOBAL | T31: RIO GRANDE | U31: MERCOSUL SUAPE | V31: 88.104.328/0001-07 | X31: CALCADOS RAMARIM LTDA | Y31: MSL CORPORATE | Z31: OC 795127 | AA31: Collect | AB31: IM1471-25 | AE31: Pago | AF31: Recebido | AG31: Sem acerto com agente | AH31: Não aplicável | AJ31: 0.31 | AK31: 102 | AL31: 310 | AN31: LCL | AO31: 0 | AP31: 0 | AR31: 1 | AS31: 46037 | AT31: 46037 | AU31: =MONTH(AT31) -> 1 | AV31: OCEAN EXPRESS SERVICOS EM COMERCIO EXTERIOR LTDA | AY31: PF003961/25-01 | AZ31: CMAU7635610 | BA31: Bruna Kelsch | BD31: 77.91 | BE31: 341.14 | BF31: 337.08 | BG31: 337.08 | BH31: 414.99 | BI31: 414.99 | BK31: 46002.359 | BL31: 1941.6 | BM31: 1941.6 | BN31: 2282.74 | BO31: 2282.74 | BP31: 45996.167 | BQ31: 45996.264 | BR31: 0 | BT31: Divergência viagens | BU31: Falso | BW31: 0 | BX31: Ativo | BY31: Ativo
A32: 1 | B32: Marítimo importação | C32: Back to back | D32: IM1352-25 | E32: CALCADOS RAMARIM LTDA | F32: CALCADOS RAMARIM LTDA | G32: Jin Meng International Industry Co., Ltd. | H32: 45908 | I32: 45996.264 | J32: FOB | L32: 45874.35 | M32: 45874.35 | N32: Desembarcado | O32: MSL | P32: LXMRGD25082487RGD | Q32: XIAMEN | S32: TBA | T32: RIO GRANDE | U32: MERCOSUL SUAPE | V32: 88.104.328/0001-07 | X32: CALCADOS RAMARIM LTDA | Y32: MSL CORPORATE | Z32: PI NO.: 20250731001 | AA32: Collect | AB32: IM1352-25 | AE32: Pago | AF32: Recebido | AG32: Sem acerto com agente | AH32: Não aplicável | AJ32: 13.732 | AK32: 2221 | AL32: 13732 | AN32: LCL | AO32: 0 | AP32: 0 | AR32: 13.732 | AS32: 46037 | AT32: 46037 | AU32: =MONTH(AT32) -> 1 | AY32: PF003678/25-01 | AZ32: CMAU7635610 | BA32: Bruna Kelsch | BD32: 109.74 | BE32: 292.26 | BF32: 1200.88 | BG32: 1200.88 | BH32: 1310.62 | BI32: 1310.62 | BK32: 46002.361 | BL32: 6917.06 | BM32: 6917.06 | BN32: 7209.32 | BO32: 7209.32 | BP32: 45996.167 | BQ32: 45996.264 | BR32: 0 | BT32: Divergência viagens | BU32: Falso | BW32: 0 | BX32: Ativo | BY32: Ativo
A33: 1 | B33: Aéreo importação | C33: Back to back | D33: IA0653-25 | E33: PERBRAS EMPRESA BRASILEIRA DE PERFURACOES LTDA | F33: PERBRAS EMPRESA BRASILEIRA DE PERFURACOES LTDA | G33: Jiangsu Rushi Machinery Co., Ltd | H33: 45996 | I33: 45997 | J33: EXW | K33: 057-56004723 | L33: 45987.693 | M33: 45987.693 | N33: Desembarcado | O33: AIR FRANCE | P33: HYKC25110062 | Q33: PEQUIM (BEIJING) | T33: SALVADOR | V33: 15.126.451/0002-28 | X33: PERBRAS EMPRESA BRASILEIRA DE PERFURACOES LTDA | Y33: Shanghai Weiming Cargo Transportation co., Ltd. | AA33: Prepaid | AB33: IA0653-25 | AE33: Parcialmente pago | AF33: Recebido | AG33: Quitado | AH33: Desconsolidado | AJ33: 0.065 | AK33: 56 | AL33: 10.838 | AM33: 83 | AN33: Aéreo | AR33: 83 | AS33: 46031 | AT33: 46031 | AU33: =MONTH(AT33) -> 1 | AY33: PF006361/25-01 | BA33: Matheus Bourscheid | BB33: Mariana Reis | BD33: 43.57 | BE33: 544.36 | BF33: 1414.49 | BG33: 1404.96 | BH33: 1458.06 | BI33: 1458.06 | BK33: 46020.66 | BL33: 7760.97 | BM33: 7398.35 | BN33: 8305.33 | BO33: 8305.33 | BP33: 45997 | BQ33: 45997 | BT33: Tracking inativo | BU33: Falso | BW33: 0 | BX33: Ativo | BY33: Ativo
A34: 1 | B34: Aéreo importação | C34: Back to back | D34: IA0595-25 | E34: PERBRAS EMPRESA BRASILEIRA DE PERFURACOES LTDA | F34: PERBRAS EMPRESA BRASILEIRA DE PERFURACOES LTDA | G34: QINGDAO HONGNNENG POWER TECHNOLOGY | H34: 45996 | I34: 45997 | J34: EXW | K34: 057-56004723 | L34: 45966.372 | M34: 45966.372 | N34: Desembarcado | O34: AIR FRANCE | P34: HYKC25110056 | Q34: PEQUIM (BEIJING) | T34: SALVADOR | V34: 15.126.451/0002-28 | X34: PERBRAS EMPRESA BRASILEIRA DE PERFURACOES LTDA | Y34: Shanghai Weiming Cargo Transportation co., Ltd. | Z34: 22/10/2025 | AA34: Prepaid | AB34: IA0595-25 | AE34: Parcialmente pago | AF34: Recebido | AG34: Quitado | AH34: Desconsolidado | AJ34: 0.03 | AK34: 12 | AL34: 5.04 | AM34: 17 | AN34: Aéreo | AR34: 12 | AS34: 46031 | AT34: 46030 | AU34: =MONTH(AT34) -> 1 | AY34: PF005747/25-01 | BA34: Matheus Bourscheid | BB34: Mariana Reis | BD34: 48.14 | BE34: 349.27 | BF34: 385.94 | BG34: 383.63 | BH34: 434.1 | BI34: 434.08 | BK34: 46017.762 | BL34: 2123.43 | BM34: 2033.08 | BN34: 2472.7 | BO34: 2472.6 | BP34: 45997 | BQ34: 45997 | BS34: Back to back | BT34: Tracking inativo | BU34: Falso | BW34: 0 | BX34: Ativo | BY34: Ativo
A35: 1 | B35: Demurrage | C35: Back to back | D35: DEMU0003-26 | E35: MAVE COMERCIO DE ACESSORIOS LTDA | F35: MAVE COMERCIO DE ACESSORIOS LTDA | G35: VALENACERE S.A . | H35: 45933.668 | I35: 45998 | J35: FOB | K35: ONEYNB5BEEB36800 | L35: 46024.62 | M35: 46024.62 | N35: Desembarcado | O35: ONE | P35: KDSY25090134 | Q35: NINGBO | S35: ONE STRENGTH | T35: RIO GRANDE | U35: SEASPAN BELIEF | V35: 11.044.498/0001-00 | X35: WINNING TRADING S.A. (RO) | Y35: REACH LOGISTICS CO., LTD | Z35: ILOG: 3450/25 - P/I NO.:2025-VSB-004 - IM1777-25 | AA35: Collect | AB35: DEMU0003-26 | AE35: Sem pagamento | AF35: Sem recebimento | AG35: Sem acerto com agente | AH35: Não aplicável | AJ35: 24.49 | AK35: 25666.5 | AL35: 24490 | AN35: FCL | AO35: 0 | AP35: 1 | AQ35: 40 NOR | AR35: 25.666 | AT35: 46035 | AU35: =MONTH(AT35) -> 1 | AV35: LEADER LOGISTICS LTDA FILIAL ITJ | AY35: PF004809/25-01 | AZ35: ONEU9173765 | BA35: Matheus Bourscheid | BD35: 680 | BE35: 3862.8 | BF35: 380 | BG35: 380 | BH35: 1060 | BI35: 1060 | BK35: 46024.622 | BL35: 2188.8 | BM35: 2188.8 | BN35: 6051.6 | BO35: 6051.6 | BP35: 45998 | BR35: 2 | BT35: Tracking inativo | BU35: Falso | BW35: 0 | BX35: Ativo | BY35: Ativo
A36: 1 | B36: Demurrage | C36: Back to back | D36: DEMU0002-26 | E36: MAVE COMERCIO DE ACESSORIOS LTDA | F36: MAVE COMERCIO DE ACESSORIOS LTDA | G36: VALENACERE S.A . | H36: 45933 | I36: 45998 | J36: FOB | K36: ONEYNB5BEEB35700 | L36: 46024.611 | M36: 46024.611 | N36: Desembarcado | O36: ONE | P36: KDSY25090135 | Q36: NINGBO | S36: ONE STRENGTH | T36: RIO GRANDE | U36: SEASPAN BELIEF | V36: 11.044.498/0001-00 | X36: WINNING TRADING S.A. (RO) | Y36: REACH LOGISTICS CO., LTD | Z36: ILOG: 3449/25 - P/I NO.:2025-VSB-003 - IM1776-25 | AA36: Collect | AB36: DEMU0002-26 | AE36: Sem pagamento | AF36: Sem recebimento | AG36: Sem acerto com agente | AH36: Não aplicável | AJ36: 30.39 | AK36: 26321.4 | AL36: 30390 | AN36: FCL | AO36: 0 | AP36: 1 | AQ36: 40 NOR | AR36: 30.39 | AT36: 46035 | AU36: =MONTH(AT36) -> 1 | AV36: LEADER LOGISTICS LTDA FILIAL ITJ | AY36: PF004808/25-01 | AZ36: OTPU6308054 | BA36: Matheus Bourscheid | BD36: 680 | BE36: 3862.8 | BF36: 380 | BG36: 380 | BH36: 1060 | BI36: 1060 | BK36: 46024.615 | BL36: 2188.8 | BM36: 2188.8 | BN36: 6051.6 | BO36: 6051.6 | BP36: 45998 | BR36: 2 | BT36: Tracking inativo | BU36: Falso | BW36: 0 | BX36: Ativo | BY36: Ativo
A37: 1 | B37: Marítimo importação | C37: Back to back | D37: IM2071-25 | E37: VERALLIA BRASIL S.A. | F37: VERALLIA BRASIL S.A. | G37: CHINA BRIDGE HOLDINGS LIMITED | H37: 45964.853 | I37: 45998.686 | J37: FOB | K37: PSLSHASTS03667 | L37: 45951.45 | M37: 45951.45 | N37: Desembarcado | O37: KINGSHIP LINE LTDA | P37: SWS2510073 | Q37: SHANGHAI | S37: EVER FINE | T37: SANTOS | V37: 60.853.942/0007-30 | X37: VERALLIA BRASIL S.A. | Y37: (LCL) SHENZHEN SMOOTHWIN INTERNATIONAL | Z37: PO 5502161136 | AA37: Collect | AB37: IM2071-25 | AE37: Parcialmente pago | AF37: Em aberto | AG37: Quitado | AH37: Não aplicável | AJ37: 0.35 | AK37: 736 | AL37: 350 | AN37: LCL | AO37: 0 | AP37: 0 | AR37: 1 | AS37: 46029 | AT37: 46031 | AU37: =MONTH(AT37) -> 1 | AY37: PF005569/25-01 | AZ37: OTPU6160373 | BA37: Tiago Schneider | BB37: Mariana Reis | BD37: 136.42 | BE37: 816.27 | BF37: 500.16 | BG37: 498.24 | BH37: 636.58 | BI37: 0 | BK37: 46029.698 | BL37: 2809.79 | BM37: 2795.45 | BN37: 3626.06 | BO37: 0 | BR37: 0 | BT37: Divergência viagens | BU37: Falso | BW37: 0 | BX37: Ativo | BY37: Ativo
A38: 1 | B38: Marítimo importação | C38: Back to back | D38: IM2039-25 | E38: VERALLIA BRASIL S.A. | F38: VERALLIA BRASIL S.A. | G38: CHINA BRIDGE HOLDINGS LIMITED | H38: 45964.853 | I38: 45998.686 | J38: FOB | K38: PSLSHASTS03660 | L38: 45947.62 | M38: 45947.62 | N38: Desembarcado | O38: KINGSHIP LINE LTDA | P38: SWS2510065 | Q38: SHANGHAI | S38: EVER FINE | T38: SANTOS | V38: 60.853.942/0017-01 | X38: VERALLIA BRASIL S.A. | Y38: (LCL) SHENZHEN SMOOTHWIN INTERNATIONAL | Z38: PO 5502163794 +5502163792 | AA38: Collect | AB38: IM2039-25 | AE38: Parcialmente pago | AF38: Em aberto | AG38: Parcialmente quitado | AH38: Não aplicável | AJ38: 1.825 | AK38: 3010 | AL38: 1825 | AN38: LCL | AO38: 0 | AP38: 0 | AR38: 3.01 | AS38: 46031 | AT38: 46031 | AU38: =MONTH(AT38) -> 1 | AY38: PF005474/25-01 | AZ38: OTPU6160373 | BA38: Tiago Schneider | BB38: Mariana Reis | BD38: 157.52 | BE38: 962.64 | BF38: 1159.38 | BG38: 1094.46 | BH38: 1316.9 | BI38: 0 | BK38: 46028.647 | BL38: 6524.58 | BM38: 6151.39 | BN38: 7487.22 | BO38: 0 | BR38: 0 | BT38: Sincronizado | BU38: Falso | BW38: 0 | BX38: Ativo | BY38: Ativo
A39: 1 | B39: Marítimo importação | C39: Back to back | D39: IM1727-25 | E39: CALCADOS RAMARIM LTDA | F39: CALCADOS RAMARIM LTDA | G39: KEYI (FUJIAN) IMPORT AND EXPORT CO.,LTD. | H39: 45958.632 | I39: 45999.476 | J39: EXW | L39: 45912.682 | M39: 45912.682 | N39: Desembarcado | O39: ALLINK TRANSPORTES INTERNACIONAIS LTDA (ITAJAÍ) | P39: 16422080 | Q39: SHANGHAI | S39: HYUNDAI TOKYO | T39: RIO GRANDE | V39: 88.104.328/0001-07 | X39: CALCADOS RAMARIM LTDA | Y39: ALLINK TRANSPORTES INTERNACIONAIS LTDA (ITAJAÍ) | Z39: OC 799887 | AA39: Collect | AB39: IM1727-25 | AE39: Pago | AF39: Recebido | AG39: Sem acerto com agente | AH39: Não aplicável | AJ39: 0.174 | AK39: 91 | AL39: 174 | AN39: LCL | AO39: 0 | AP39: 0 | AR39: 1 | AS39: 46037 | AT39: 46037 | AU39: =MONTH(AT39) -> 1 | AV39: OCEAN EXPRESS SERVICOS EM COMERCIO EXTERIOR LTDA | AY39: PF004709/25-01 | AZ39: HMMU5493810 | BA39: Bruna Kelsch | BB39: Mariana Reis | BD39: 110.74 | BE39: 558.62 | BF39: 269.83 | BG39: 269.83 | BH39: 380.57 | BI39: 380.57 | BK39: 46002.369 | BL39: 1569.96 | BM39: 1569.96 | BN39: 2128.58 | BO39: 2128.58 | BP39: 45999.083 | BQ39: 45999.476 | BR39: 0 | BT39: Sincronizado | BU39: Falso | BW39: 0 | BX39: Ativo | BY39: Ativo
A40: 1 | B40: Marítimo importação | C40: Back to back | D40: IM1830-25 | E40: BRISA INDUSTRIA DE TECIDOS TECNOLOGICOS S.A | F40: BRISA INDUSTRIA DE TECIDOS TECNOLOGICOS S.A | G40: C.CENTAURUS TECHNOLOGY LTD | H40: 45945.833 | I40: 45999.858 | J40: FOB | K40: 259801566 | L40: 45924.435 | M40: 45924.435 | N40: Desembarcado | O40: MAERSK | P40: SZES25101014B | Q40: SHANGHAI | S40: AL NASRIYAH | T40: SALVADOR | U40: CMA CGM YUKON | V40: 02.036.823/0001-00 | X40: BRISA INDUSTRIA DE TECIDOS TECNOLOGICOS S.A | Y40: SHENZHEN EVERSEAS INTERNATIONAL LOGISTICS CO | Z40: CCTBS-0453 | AA40: Collect | AB40: IM1830-25 | AE40: Pago | AF40: Recebido | AG40: Quitado | AH40: Não aplicável | AL40: 0 | AN40: FCL | AO40: 1 | AP40: 0 | AQ40: 20 DRY BOX | AS40: 46006 | AT40: 46065 | AU40: =MONTH(AT40) -> 2 | AZ40: HASU1120310 | BA40: Enila Kawely | BD40: 262.34 | BE40: 1840.88 | BF40: 1085.93 | BG40: 1085.93 | BH40: 1348.27 | BI40: 1348.27 | BK40: 46014.452 | BL40: 5805.36 | BM40: 5890.2 | BN40: 7646.24 | BO40: 7646.24 | BP40: 45999.833 | BQ40: 45999.858 | BR40: 1 | BT40: Sincronizado | BU40: Falso | BX40: Ativo | BY40: Ativo
A41: 1 | B41: Marítimo importação | C41: Back to back | D41: IM1831-25 | E41: BRISA INDUSTRIA DE TECIDOS TECNOLOGICOS S.A | F41: BRISA INDUSTRIA DE TECIDOS TECNOLOGICOS S.A | G41: HARMONY PROSPERITY INTERNATIONAL LIMITED | H41: 45945.833 | I41: 45999.858 | J41: FOB | K41: 259801566 | L41: 45924.436 | M41: 45924.436 | N41: Desembarcado | O41: MAERSK | P41: SZES25101014C | Q41: SHANGHAI | S41: AL NASRIYAH | T41: SALVADOR | U41: CMA CGM YUKON | V41: 02.036.823/0001-00 | X41: BRISA INDUSTRIA DE TECIDOS TECNOLOGICOS S.A | Y41: SHENZHEN EVERSEAS INTERNATIONAL LOGISTICS CO | Z41: CCTBS-0452-1 | AA41: Collect | AB41: IM1831-25 | AE41: Pago | AF41: Recebido | AG41: Quitado | AH41: Não aplicável | AL41: 0 | AN41: FCL | AO41: 1 | AP41: 0 | AQ41: 20 DRY BOX | AS41: 46006 | AT41: 46065 | AU41: =MONTH(AT41) -> 2 | AZ41: HASU1120310 | BA41: Enila Kawely | BD41: 190.24 | BE41: 1121.25 | BF41: 130.31 | BG41: 130.31 | BH41: 320.55 | BI41: 320.55 | BK41: 46014.453 | BL41: 696.66 | BM41: 706.84 | BN41: 1817.91 | BO41: 1817.91 | BP41: 45999.833 | BQ41: 45999.858 | BR41: 1 | BT41: Sincronizado | BU41: Falso | BX41: Ativo | BY41: Ativo
A42: 1 | B42: Marítimo importação | C42: Back to back | D42: IM1829-25 | E42: BRISA INDUSTRIA DE TECIDOS TECNOLOGICOS S.A | F42: BRISA INDUSTRIA DE TECIDOS TECNOLOGICOS S.A | G42: XUCHUAN CHEMICAL (SUZHOU) CO., LTD | H42: 45945.833 | I42: 45999.858 | J42: FOB | K42: 259801566 | L42: 45924.431 | M42: 45924.431 | N42: Desembarcado | O42: MAERSK | P42: SZES25101014D | Q42: SHANGHAI | S42: AL NASRIYAH | T42: SALVADOR | U42: CMA CGM YUKON | V42: 02.036.823/0001-00 | X42: BRISA INDUSTRIA DE TECIDOS TECNOLOGICOS S.A | Y42: SHENZHEN EVERSEAS INTERNATIONAL LOGISTICS CO | Z42: SPU202509-14-1 - CARGA DG | AA42: Collect | AB42: IM1829-25 | AE42: Pago | AF42: Recebido | AG42: Quitado | AH42: Não aplicável | AL42: 0 | AN42: FCL | AO42: 1 | AP42: 0 | AQ42: 20 DRY BOX | AS42: 46006 | AT42: 46065 | AU42: =MONTH(AT42) -> 2 | AZ42: HASU1120310 | BA42: Enila Kawely | BD42: 245.46 | BE42: 1774.27 | BF42: 1146.58 | BG42: 1146.58 | BH42: 1392.04 | BI42: 1392.04 | BK42: 46014.452 | BL42: 6120.21 | BM42: 6212.33 | BN42: 7894.48 | BO42: 7894.48 | BP42: 45999.833 | BQ42: 45999.858 | BR42: 1 | BT42: Sincronizado | BU42: Falso | BX42: Ativo | BY42: Ativo
A43: 1 | B43: Marítimo importação | C43: Back to back | D43: IM1832-25 | E43: BRISA INDUSTRIA DE TECIDOS TECNOLOGICOS S.A | F43: BRISA INDUSTRIA DE TECIDOS TECNOLOGICOS S.A | G43: HUAFON MICROFIBER (JIANGSU)CO.,LTD | H43: 45945.833 | I43: 45999.858 | J43: FOB | K43: 259801566 | L43: 45924.439 | M43: 45924.439 | N43: Desembarcado | O43: MAERSK | P43: SZES25101014A | Q43: SHANGHAI | S43: AL NASRIYAH | T43: SALVADOR | U43: CMA CGM YUKON | V43: 02.036.823/0001-00 | X43: BRISA INDUSTRIA DE TECIDOS TECNOLOGICOS S.A | Y43: SHENZHEN EVERSEAS INTERNATIONAL LOGISTICS CO | Z43: CCTBS-0448A | AA43: Collect | AB43: IM1832-25 | AE43: Pago | AF43: Recebido | AG43: Quitado | AH43: Não aplicável | AL43: 0 | AN43: FCL | AO43: 1 | AP43: 0 | AQ43: 20 DRY BOX | AS43: 46006 | AT43: 46065 | AU43: =MONTH(AT43) -> 2 | AZ43: HASU1120310 | BA43: Enila Kawely | BD43: 322.95 | BE43: 2665.57 | BF43: 2493.26 | BG43: 2493.26 | BH43: 2816.21 | BI43: 2816.21 | BK43: 46014.453 | BL43: 13305.61 | BM43: 13508.79 | BN43: 15971.18 | BO43: 15971.18 | BP43: 45999.833 | BQ43: 45999.858 | BR43: 1 | BT43: Sincronizado | BU43: Falso | BX43: Ativo | BY43: Ativo
A44: 1 | B44: Marítimo importação | C44: Back to back | D44: IM1957-25 | E44: ROYAL DISTRIBUICAO LTDA | F44: ROYAL DISTRIBUICAO LTDA | G44: QUANZHOU GUDE VOLCANO FURNITURE CO., LTD | H44: 45959.557 | I44: 46000 | J44: FOB | L44: 45938.748 | M44: 45938.748 | N44: Desembarcado | O44: ECU WORLDWIDE LOGISTICS DO BRAZIL LTDA | P44: SHSUA25237972E | Q44: SHANGHAI | S44: CAP SAN ARTEMISSIO | T44: Suape | U44: BARTOLOMEU DIAS | V44: 52.225.107/0002-12 | X44: ROYAL DISTRIBUICAO LTDA | Y44: ECU WORLDWIDE LOGISTICS DO BRAZIL LTDA | Z44: PI-25056 | AA44: Collect | AB44: IM1957-25 | AE44: Em aberto | AF44: Recebido | AG44: Quitado | AH44: Não aplicável | AJ44: 13.254 | AK44: 1700 | AL44: 13254 | AN44: LCL | AO44: 0 | AP44: 0 | AR44: 13.254 | AS44: 46031 | AT44: 46031 | AU44: =MONTH(AT44) -> 1 | AY44: PF005160/25-01 | AZ44: TLLU1157705 | BA44: Tiago Schneider | BB44: Mariana Reis | BD44: 34.27 | BE44: -35.29 | BF44: 939.29 | BG44: 933.04 | BH44: 973.56 | BI44: 973.56 | BK44: 46029.707 | BL44: 5613.66 | BM44: 5579.55 | BN44: 5578.37 | BO44: 5578.37 | BP44: 46000 | BQ44: 46000 | BR44: 0 | BT44: Sincronizado | BU44: Falso | BW44: 0 | BX44: Ativo | BY44: Ativo
A45: 1 | B45: Demurrage | C45: Back to back | D45: DEMU0046-26 | E45: JCLS COMERCIO LTDA | F45: JCLS COMERCIO LTDA | G45: Evanza Tableware | H45: 45937 | I45: 46001 | J45: FOB | K45: MEDUKD886900 | L45: 46049.779 | M45: 46049.779 | N45: Desembarcado | O45: MSC MEDITERRANEAN SHIPPING DO BRASIL LTDA. | P45: GUJ1460103640 | Q45: MUNDRA | S45: KLEVEN | T45: NAVEGANTES | U45: MSC AMALFI | V45: 59.436.062/0001-93 | X45: JCLS COMERCIO LTDA | Y45: CARGO MARKETING INTERNATIONAL PVT LTD. | Z45: LIV-226 - ILOG 3162/25 - IM1747-25 | AA45: Collect | AB45: DEMU0046-26 | AE45: Sem pagamento | AF45: Sem recebimento | AG45: Sem acerto com agente | AH45: Não aplicável | AJ45: 37.33 | AK45: 13797.7 | AL45: 37330 | AN45: FCL | AO45: 0 | AP45: 1 | AQ45: 40 HIGH CUBE | AR45: 37.33 | AT45: 46051 | AU45: =MONTH(AT45) -> 1 | AV45: LEADER LOGISTICS LTDA FILIAL ITJ | AY45: PF004790/25-01 | AZ45: DFSU6529947 | BA45: Matheus Bourscheid | BD45: 1320.22 | BE45: 7655.77 | BF45: 3078.14 | BG45: 3078.14 | BH45: 4398.36 | BI45: 4398.36 | BK45: 46049.781 | BL45: 16765.2 | BM45: 16765.2 | BN45: 24420.97 | BO45: 24420.97 | BP45: 46001 | BR45: 2 | BT45: Tracking inativo | BU45: Falso | BW45: 0 | BX45: Ativo | BY45: Ativo
A46: 1 | B46: Marítimo importação | C46: Back to back | D46: IM1747-25 | E46: JCLS COMERCIO LTDA | F46: JCLS COMERCIO LTDA | G46: Evanza Tableware | H46: 45937 | I46: 46001 | J46: FOB | K46: MEDUKD886900 | L46: 45916.636 | M46: 45916.636 | N46: Desembarcado | O46: MSC MEDITERRANEAN SHIPPING DO BRASIL LTDA. | P46: GUJ1460103640 | Q46: MUNDRA | S46: KLEVEN | T46: NAVEGANTES | U46: MSC AMALFI | V46: 59.436.062/0001-93 | X46: JCLS COMERCIO LTDA | Y46: CARGO MARKETING INTERNATIONAL PVT LTD. | Z46: LIV-226 - ILOG 3162/25 | AA46: Collect | AB46: 3162/25 | AE46: Pago | AF46: Recebido | AG46: Quitado | AH46: Não aplicável | AJ46: 37.33 | AK46: 13797.7 | AL46: 37330 | AN46: FCL | AO46: 0 | AP46: 1 | AQ46: 40 HIGH CUBE | AR46: 37.33 | AS46: 46052 | AT46: 46055 | AU46: =MONTH(AT46) -> 2 | AV46: LEADER LOGISTICS LTDA FILIAL ITJ | AY46: PF004790/25-01 | AZ46: DFSU6529947 | BA46: Annie Audrien | BB46: Mariana Reis | BD46: 558.19 | BE46: 2428.84 | BF46: 2574.69 | BG46: 2574.69 | BH46: 3132.88 | BI46: 3132.88 | BK46: 46052.644 | BL46: 15295.13 | BM46: 15246.3 | BN46: 17723.97 | BO46: 17723.97 | BP46: 46001 | BQ46: 46001 | BR46: 2 | BT46: Divergência viagens | BU46: Falso | BW46: 0 | BX46: Ativo | BY46: Ativo
A47: 1 | B47: Demurrage | C47: Back to back | D47: DEMU0008-26 | E47: TRELLO COMERCIO DE COMPONENTES AUTOMOTIVOS LTDA | F47: TRELLO COMERCIO DE COMPONENTES AUTOMOTIVOS LTDA | G47: CHANGZHOU E&E TURBO-POWER CO., LTD | H47: 45954.46 | I47: 46001 | J47: FOB | K47: CHN2733270 | L47: 46024.686 | M47: 46024.686 | N47: Desembarcado | O47: COMPAGNIE GENERALE MARITIME - CMA CGM | P47: KDSY25090181 | Q47: SHANGHAI | S47: COSCO SHIPPING PERU | T47: ITAPOA | U47: CMA CGM PARATY | V47: 34.638.044/0001-63 | X47: WINNING TRADING S.A. (RO) | Y47: REACH LOGISTICS CO., LTD | Z47: ILOG 4592/25 - 252270BT | AA47: Prepaid | AB47: 4592/25 | AE47: Sem pagamento | AF47: Sem recebimento | AG47: Sem acerto com agente | AH47: Não aplicável | AL47: 0 | AN47: FCL | AO47: 0 | AP47: 1 | AQ47: 40 HIGH CUBE | AR47: 0 | AT47: 46029 | AU47: =MONTH(AT47) -> 1 | AV47: LEADER LOGISTICS LTDA FILIAL ITJ | AY47: PF004960/25-02 | AZ47: SEGU4963836 | BA47: Matheus Bourscheid | BD47: 250 | BE47: 1416.58 | BF47: 0 | BG47: 0 | BH47: 250 | BI47: 250 | BK47: 46028.446 | BL47: 0 | BM47: 0 | BN47: 1416.58 | BO47: 1416.58 | BP47: 46001 | BR47: 2 | BT47: Tracking inativo | BU47: Falso | BW47: 0 | BX47: Ativo | BY47: Ativo
A48: 1 | B48: Aéreo importação | C48: Back to back | D48: IA0645-25 | E48: HENRICH & CIA LTDA | F48: HENRICH & CIA LTDA | G48: PRIME INTERNATIONAL INDIA PVT. LTD. | H48: 45996 | I48: 46001 | J48: FCA | K48: 057-56317623 | L48: 45985.691 | M48: 45985.691 | N48: Desembarcado | O48: AIR FRANCE | P48: 10595 | Q48: MADRAS (CHENNAI) | T48: GUARULHOS | V48: 89.238.133/0001-04 | X48: HENRICH & CIA LTDA | Y48: FLOMIC GLOBAL LOGISTICS | Z48: OC 1272818 | AA48: Prepaid | AB48: IA0645-25 | AE48: Parcialmente pago | AF48: Recebido | AG48: Quitado | AH48: Pendente desc. house | AJ48: 2.574 | AK48: 790.7 | AL48: 429 | AM48: 791 | AN48: Aéreo | AR48: 790.7 | AS48: 46031 | AT48: 46031 | AU48: =MONTH(AT48) -> 1 | AY48: PF006283/25-05 | BA48: Matheus Bourscheid | BB48: Mariana Reis | BD48: 46.58 | BE48: 1274.69 | BF48: 4660.67 | BG48: 4572.78 | BH48: 4707.25 | BI48: 4707.25 | BK48: 46024.768 | BL48: 25739.66 | BM48: 23694.24 | BN48: 27014.35 | BO48: 27014.35 | BP48: 46001 | BQ48: 46001 | BT48: Tracking inativo | BU48: Falso | BV48: 60277.29 | BW48: 0 | BX48: Ativo | BY48: Ativo
A49: 1 | B49: Aéreo importação | C49: Back to back | D49: IA0661-25 | E49: HENRICH & CIA LTDA | F49: HENRICH & CIA LTDA | G49: HENAN PROSPER & COLOMER MODA CO., LTD. | H49: 45995 | I49: 46002 | J49: COURIER | K49: 7729590094 | L49: 45992.659 | M49: 45992.659 | N49: Desembarcado | O49: DHL | P49: 7729590094 | Q49: PU DONG (SHANGHAI) | T49: PORTO ALEGRE | V49: 89.238.133/0001-04 | X49: HENRICH & CIA LTDA | Z49: SAMPLE ORDER 0218/25 | AA49: Collect | AB49: IA0661-25 | AE49: Parcialmente pago | AF49: Recebido | AG49: Sem acerto com agente | AH49: Sem vínculo master | AJ49: 0.016 | AK49: 1 | AL49: 2.621 | AM49: 2.5 | AN49: Aéreo | AR49: 2.621 | AS49: 46031 | AT49: 46031 | AU49: =MONTH(AT49) -> 1 | AY49: PF004032/25-01 | BA49: Matheus Bourscheid | BD49: 68.09 | BE49: 409.52 | BF49: 352.03 | BG49: 349.44 | BH49: 420.12 | BI49: 420.12 | BK49: 46024.717 | BL49: 1943.35 | BM49: 1928.84 | BN49: 2352.87 | BO49: 2352.87 | BP49: 46006 | BQ49: 46002 | BT49: Tracking inativo | BU49: Falso | BW49: 0 | BX49: Ativo | BY49: Ativo
A50: 1 | B50: Aéreo importação | C50: Back to back | D50: IA0663-25 | E50: HENRICH & CIA LTDA | F50: HENRICH & CIA LTDA | H50: 45997 | I50: 46002 | J50: EXW | K50: 5274870753 | L50: 45993.606 | M50: 45993.606 | N50: Desembarcado | O50: DHL | P50: 5274870753 | Q50: DONGGUAN | T50: PORTO ALEGRE | V50: 89.238.133/0001-04 | X50: HENRICH & CIA LTDA | Y50: LEADER LOGISTICS LTDA FILIAL ITJ | Z50: SAMPLE ORDER 0229/25 | AA50: Prepaid | AB50: IA0663-25 | AE50: Parcialmente pago | AF50: Recebido | AG50: Sem acerto com agente | AH50: Sem vínculo master | AM50: 2.7 | AN50: Aéreo | AS50: 46031 | AT50: 46031 | AU50: =MONTH(AT50) -> 1 | AY50: PF005859/25-01 | BA50: Matheus Bourscheid | BD50: 63.65 | BE50: 387.42 | BF50: 352.43 | BG50: 345.16 | BH50: 416.08 | BI50: 416.08 | BK50: 46024.719 | BL50: 1942.84 | BM50: 1902.12 | BN50: 2330.26 | BO50: 2330.26 | BP50: 46006 | BQ50: 46002 | BT50: Tracking inativo | BU50: Falso | BW50: 0 | BX50: Ativo | BY50: Ativo
A51: 1 | B51: Demurrage | C51: Back to back | D51: DEMU0036-26 | E51: NA WEB GROUP DE MARCAS LICENCIADAS LTDA | F51: NA WEB GROUP DE MARCAS LICENCIADAS LTDA | G51: DIGO TOYS INDUSTRIAL COMPANY LIMITED | H51: 45972.676 | I51: 46002 | J51: FOB | K51: CANM79012300 | L51: 46043.672 | M51: 46043.672 | N51: Desembarcado | O51: HYUNDAI | P51: KDSY25100225 | Q51: SHEKOU | S51: HYUNDAI BRAVE | T51: SANTOS | V51: 39.269.114/0003-39 | X51: NA WEB GROUP DE MARCAS LICENCIADAS LTDA | Y51: REACH LOGISTICS CO., LTD | Z51: WD20250402003 - PRO25000600 - NAWEB136OUT25 - IM2173-25 | AA51: Prepaid | AB51: DEMU0036-26 | AE51: Sem pagamento | AF51: Sem recebimento | AG51: Sem acerto com agente | AH51: Não aplicável | AJ51: 69.69 | AK51: 4101 | AL51: 69690 | AN51: FCL | AO51: 0 | AP51: 1 | AQ51: 40 HIGH CUBE | AR51: 69.69 | AT51: 46066 | AU51: =MONTH(AT51) -> 2 | AY51: PF005704/25-01 | AZ51: BMOU4762710 | BA51: Matheus Bourscheid | BD51: 60 | BE51: 25.12 | BF51: 300 | BG51: 300 | BH51: 360 | BI51: 360 | BK51: 46059.665 | BL51: 1878 | BM51: 1878 | BN51: 1903.12 | BO51: 1903.12 | BP51: 46002 | BR51: 2 | BT51: Tracking inativo | BU51: Falso | BW51: 0 | BX51: Ativo | BY51: Ativo
A52: 1 | B52: Demurrage | C52: Back to back | D52: DEMU0080-26 | E52: NA WEB GROUP DE MARCAS LICENCIADAS LTDA | F52: NA WEB GROUP DE MARCAS LICENCIADAS LTDA | G52: GUANGXI GLORY HOUSEHOLD CO., LTD. | H52: 45972.676 | I52: 46002 | J52: FOB | K52: CANM63380200 | L52: 46084.652 | M52: 46084.652 | N52: Desembarcado | O52: HYUNDAI | P52: KDSY25100213 | Q52: SHEKOU | S52: HYUNDAI BRAVE | T52: SANTOS | V52: 39.269.114/0003-39 | X52: NA WEB GROUP DE MARCAS LICENCIADAS LTDA | Y52: REACH LOGISTICS CO., LTD | Z52: MG5316H0, MG5316G9, MG5316H2, MG5316H1, MG5316G8 - VIMP/3670 - IM2171-25 | AA52: Prepaid | AB52: DEMU0080-26 | AE52: Sem pagamento | AF52: Sem recebimento | AG52: Sem acerto com agente | AH52: Não aplicável | AJ52: 343.43 | AK52: 57680 | AL52: 343430 | AN52: FCL | AO52: 0 | AP52: 5 | AQ52: 40 HIGH CUBE | AR52: 343.43 | AT52: 46100 | AU52: =MONTH(AT52) -> 3 | AY52: PF005800/25-01 | AZ52: BSIU9619190, KOCU4531927, KOCU4751829, KOCU4798894, KOCU4994074 | BA52: Matheus Bourscheid | BD52: 1800 | BE52: 9122.69 | BF52: 630 | BG52: 630 | BH52: 2430 | BI52: 2430 | BK52: 46091.692 | BL52: 3546.9 | BM52: 3546.9 | BN52: 12669.59 | BO52: 12669.59 | BP52: 46002 | BR52: 10 | BT52: Tracking inativo | BU52: Falso | BW52: 0 | BX52: Ativo | BY52: Ativo
A53: 1 | B53: Aéreo importação | C53: Back to back | D53: IA0644-25 | E53: HENRICH & CIA LTDA | F53: HENRICH & CIA LTDA | G53: HONG KONG MILAIDUO INTERNATIONAL LIMITE | H53: 45994 | I53: 46002 | J53: EXW | K53: 729-92609974 | L53: 45985.679 | M53: 45985.679 | N53: Desembarcado | O53: AVIANCA | P53: HYKC25110267 | Q53: HONG KONG | T53: GUARULHOS | V53: 89.238.133/0001-04 | X53: HENRICH & CIA LTDA | Y53: Shanghai Weiming Cargo Transportation co., Ltd. | Z53: OC 1267897 | AA53: Prepaid | AB53: IA0644-25 | AE53: Parcialmente pago | AF53: Recebido | AG53: Quitado | AH53: Desconsolidado | AJ53: 0.45 | AK53: 160 | AL53: 75 | AM53: 160 | AN53: Aéreo | AR53: 160 | AS53: 46031 | AT53: 46031 | AU53: =MONTH(AT53) -> 1 | AY53: PF006287/25-04 | BA53: Matheus Bourscheid | BB53: Mariana Reis | BD53: 38.13 | BE53: 561.4 | BF53: 1606.08 | BG53: 1574.04 | BH53: 1644.21 | BI53: 1644.21 | BK53: 46024.74 | BL53: 8802.2 | BM53: 8293.15 | BN53: 9363.6 | BO53: 9363.6 | BP53: 46002 | BQ53: 46002 | BT53: Tracking inativo | BU53: Falso | BW53: 0 | BX53: Ativo | BY53: Ativo
A54: 1 | B54: Aéreo importação | C54: Back to back | D54: IA0668-25 | E54: HENRICH & CIA LTDA | F54: HENRICH & CIA LTDA | G54: LAN HUI HARDWARE (HONG KONG) LIMITED | H54: 45999 | I54: 46003 | J54: EXW | K54: 2956933405 | L54: 45994.573 | M54: 45994.573 | N54: Desembarcado | O54: DHL | Q54: DONGGUAN | T54: PORTO ALEGRE | V54: 89.238.133/0001-04 | X54: HENRICH & CIA LTDA | Y54: LEADER LOGISTICS LTDA FILIAL ITJ | Z54: SAMPLE ORDER 0197/25 | AA54: Prepaid | AB54: IA0668-25 | AE54: Parcialmente pago | AF54: Recebido | AG54: Sem acerto com agente | AH54: Sem AWB house | AM54: 1.5 | AN54: Aéreo | AS54: 46031 | AT54: 46031 | AU54: =MONTH(AT54) -> 1 | AY54: PF005859/25-01 | BA54: Matheus Bourscheid | BD54: 65.29 | BE54: 386.39 | BF54: 157.75 | BG54: 156.39 | BH54: 223.04 | BI54: 223.04 | BK54: 46024.721 | BL54: 862.77 | BM54: 855.15 | BN54: 1249.16 | BO54: 1249.16 | BP54: 46007 | BQ54: 46003 | BT54: Tracking inativo | BU54: Falso | BW54: 0 | BX54: Ativo | BY54: Ativo
A55: 1 | B55: Demurrage | C55: Back to back | D55: DEMU0026-26 | E55: NA WEB GROUP DE MARCAS LICENCIADAS LTDA | F55: NA WEB GROUP DE MARCAS LICENCIADAS LTDA | G55: TIANJIN TEXTILE GROUP IMPORT AND EXPORT INC. | H55: 45963.526 | I55: 46004.001 | J55: FOB | K55: 260750769 | L55: 46041.598 | M55: 46041.598 | N55: Desembarcado | O55: MAERSK | P55: KDSY25100032 | Q55: XINGANG | S55: ESL SHEKOU | T55: SANTOS | U55: CMA CGM LISA MARIE | V55: 39.269.114/0003-39 | X55: NA WEB GROUP DE MARCAS LICENCIADAS LTDA | Y55: REACH LOGISTICS CO., LTD | Z55: 25D01C0900KB - PRO25000560 - NAWEB113OUT25 - IM1942-25 | AA55: Prepaid | AB55: DEMU0026-26 | AE55: Sem pagamento | AF55: Sem recebimento | AG55: Sem acerto com agente | AH55: Não aplicável | AJ55: 70.7 | AK55: 9100 | AL55: 70700 | AN55: FCL | AO55: 0 | AP55: 1 | AQ55: 40 HIGH CUBE | AR55: 70.7 | AT55: 46058 | AU55: =MONTH(AT55) -> 2 | AY55: PF005271/25-01 | AZ55: TCNU1524327 | BA55: Matheus Bourscheid | BD55: 387.59 | BE55: 1932.68 | BF55: 332.41 | BG55: 332.41 | BH55: 720 | BI55: 720 | BK55: 46050.751 | BL55: 1836.98 | BM55: 1836.98 | BN55: 3769.66 | BO55: 3769.66 | BP55: 46003 | BR55: 2 | BT55: Tracking inativo | BU55: Falso | BW55: 0 | BX55: Ativo | BY55: Ativo
A56: 1 | B56: Demurrage | C56: Back to back | D56: DEMU0033-26 | E56: FITESA NAOTECIDOS S/A | F56: FITESA NAOTECIDOS S/A | G56: Zschimmer & Schwarz GmbH & Co KG | H56: 45974.946 | I56: 46004.579 | J56: FCA | K56: HLCUHAM251129735 | L56: 46042.763 | M56: 46042.763 | N56: Desembarcado | O56: HAPAG LLOYD | P56: 2511517ANRIG001 | Q56: ANTWERP | S56: MSC INSA | T56: RIO GRANDE | V56: 93.211.084/0001-93 | X56: FITESA NAOTECIDOS S/A | Y56: NEXUS LOGISTICS | Z56: GRV-001382 | AA56: Collect | AB56: IM2200-25 | AE56: Sem pagamento | AF56: Sem recebimento | AG56: Sem acerto com agente | AH56: Não aplicável | AJ56: 30 | AK56: 19116 | AL56: 30000 | AN56: FCL | AO56: 1 | AP56: 0 | AQ56: 20 DRY BOX | AR56: 30 | AT56: 46059 | AU56: =MONTH(AT56) -> 2 | AY56: PF005825/25-01 | AZ56: HLBU3950980 | BA56: Matheus Bourscheid | BD56: 146.07 | BE56: 998.82 | BF56: 363.03 | BG56: 363.03 | BH56: 509.1 | BI56: 509.1 | BK56: 46048.642 | BL56: 2325.06 | BM56: 2325.06 | BN56: 3323.88 | BO56: 3323.88 | BP56: 46004.625 | BR56: 1 | BT56: Tracking inativo | BU56: Falso | BW56: 0 | BX56: Ativo | BY56: Ativo
A57: 1 | B57: Marítimo importação | C57: Back to back | D57: IM2200-25 | E57: FITESA NAOTECIDOS S/A | F57: FITESA NAOTECIDOS S/A | G57: Zschimmer & Schwarz GmbH & Co KG | H57: 45974.946 | I57: 46004.579 | J57: FCA | K57: HLCUHAM251129735 | L57: 45961.699 | M57: 45961.699 | N57: Desembarcado | O57: HAPAG LLOYD | P57: 2511517ANRIG001 | Q57: ANTWERP | S57: MSC INSA | T57: RIO GRANDE | V57: 93.211.084/0001-93 | X57: FITESA NAOTECIDOS S/A | Y57: NEXUS LOGISTICS | Z57: GRV-001382 | AA57: Collect | AB57: IM2200-25 | AE57: Pago | AF57: Recebido | AG57: Quitado | AH57: Não aplicável | AJ57: 30 | AK57: 19116 | AL57: 30000 | AN57: FCL | AO57: 1 | AP57: 0 | AQ57: 20 DRY BOX | AR57: 30 | AS57: 46013 | AT57: 46037 | AU57: =MONTH(AT57) -> 1 | AY57: PF005825/25-01 | AZ57: HLBU3950980 | BA57: Matheus Bourscheid | BB57: Mariana Reis | BD57: 71.42 | BE57: 1102.15 | BF57: 1769.45 | BG57: 1769.45 | BH57: 1840.87 | BI57: 1840.87 | BK57: 46037.468 | BL57: 11453.27 | BM57: 11610.27 | BN57: 12555.42 | BO57: 12555.42 | BP57: 46004.625 | BQ57: 46004.579 | BR57: 1 | BT57: Sincronizado | BU57: Falso | BW57: 0 | BX57: Ativo | BY57: Ativo
A58: 1 | B58: Marítimo importação | C58: Back to back | D58: IM2137-25 | E58: VERALLIA BRASIL S.A. | F58: VERALLIA BRASIL S.A. | G58: CHINA BRIDGE HOLDINGS LIMITED | H58: 45972.994 | I58: 46004.967 | J58: FOB | K58: PSLSHASTS03678 | L58: 45954.76 | M58: 45954.76 | N58: Desembarcado | O58: KINGSHIP LINE LTDA | P58: SWS2511015 | Q58: SHANGHAI | S58: KOTA PAHLAWAN | T58: SANTOS | V58: 60.853.942/0017-01 | X58: VERALLIA BRASIL S.A. | Y58: (LCL) SHENZHEN SMOOTHWIN INTERNATIONAL | Z58: 5502163798 | AA58: Collect | AB58: IM2137-25 | AE58: Parcialmente pago | AF58: Em aberto | AG58: Quitado | AH58: Não aplicável | AJ58: 0.927 | AK58: 1870 | AL58: 927 | AN58: LCL | AO58: 0 | AP58: 0 | AR58: 1.87 | AS58: 46031 | AT58: 46031 | AU58: =MONTH(AT58) -> 1 | AY58: PF005715/25-01 | AZ58: FSCU5928887 | BA58: Tiago Schneider | BB58: Mariana Reis | BD58: 231.02 | BE58: 1311.24 | BF58: 905.79 | BG58: 854.37 | BH58: 1136.81 | BI58: 0 | BK58: 46029.702 | BL58: 5126.01 | BM58: 4822.44 | BN58: 6437.25 | BO58: 0 | BR58: 0 | BT58: Pendente atualização dados | BU58: Falso | BW58: 0 | BX58: Ativo | BY58: Ativo
A59: 1 | B59: Demurrage | C59: Back to back | D59: DEMU0040-26 | E59: CALCADOS BEIRA RIO S/A | F59: CALCADOS BEIRA RIO S/A | G59: L'STRIVER TECH.(H.K.)CO.,LIMITED | H59: 45969.353 | I59: 46005 | J59: FOB | K59: HDMUNBOZH7026800 | L59: 46043.706 | M59: 46043.706 | N59: Desembarcado | O59: HYUNDAI | P59: KDSY25100157 | Q59: NINGBO | S59: HYUNDAI BRAVE | T59: RIO GRANDE | V59: 88.379.771/0035-21 | X59: CALCADOS BEIRA RIO S/A | Y59: REACH LOGISTICS CO., LTD | Z59: 678/25- L'STRIVER - 2510002 - SISLOG 26953/25 - IM2083-25 | AA59: Prepaid | AB59: DEMU0040-26 | AE59: Sem pagamento | AF59: Sem recebimento | AG59: Sem acerto com agente | AH59: Não aplicável | AJ59: 68 | AK59: 26030 | AL59: 68000 | AN59: FCL | AO59: 0 | AP59: 1 | AQ59: 40 HIGH CUBE | AR59: 68 | AT59: 46052 | AU59: =MONTH(AT59) -> 1 | AV59: Commander Logistica Ltda | AZ59: KOCU4975808 | BA59: Matheus Bourscheid | BD59: 500 | BE59: 2788.7 | BF59: 0 | BG59: 0 | BH59: 500 | BI59: 500 | BK59: 46044.629 | BL59: 0 | BM59: 0 | BN59: 2788.7 | BO59: 2788.7 | BP59: 46006 | BR59: 2 | BT59: Tracking inativo | BU59: Falso | BW59: 0 | BX59: Ativo | BY59: Ativo
A60: 1 | B60: Marítimo importação | C60: Back to back | D60: IM2060-25 | E60: FITESA NAOTECIDOS S/A | F60: FITESA NAOTECIDOS S/A | G60: DRSCHENK | H60: 45983.822 | I60: 46005.888 | J60: FCA | K60: ONEYHAMF99017700 | L60: 45950.749 | M60: 45950.749 | N60: Desembarcado | O60: ONE | P60: S2501842 | Q60: HAMBURG | S60: BROOKLYN BRIDGE | T60: SANTOS | V60: 93.211.084/0001-93 | X60: FITESA NAOTECIDOS S/A | Y60: MENZELL DÖHLE LOGISTICS GMBH | Z60: COS-000373 | AA60: Collect | AB60: IM2060-25 | AE60: Pago | AF60: Recebido | AG60: Quitado | AH60: Não aplicável | AJ60: 12.967 | AK60: 1862 | AL60: 12967 | AN60: FCL | AO60: 0 | AP60: 1 | AQ60: 40 HIGH CUBE | AR60: 12.967 | AS60: 46013 | AT60: 46029 | AU60: =MONTH(AT60) -> 1 | AY60: PF005486/25-01 | AZ60: BEAU5299864 | BA60: Matheus Bourscheid | BD60: 243.63 | BE60: 2356.37 | BF60: 2581.68 | BG60: 2581.68 | BH60: 2825.31 | BI60: 2825.31 | BK60: 46020.664 | BL60: 16853.96 | BM60: 16002.67 | BN60: 19210.33 | BO60: 19210.33 | BP60: 46005.888 | BQ60: 46005.888 | BR60: 2 | BT60: Sincronizado | BU60: Falso | BW60: 0 | BX60: Ativo | BY60: Ativo
A61: 1 | B61: Demurrage | C61: Back to back | D61: DEMU0015-26 | E61: NA WEB GROUP DE MARCAS LICENCIADAS LTDA | F61: NA WEB GROUP DE MARCAS LICENCIADAS LTDA | G61: CHARISMA HOUSEWARE (HUIZHOU) CO., LIMITED | H61: 45968.332 | I61: 46006 | J61: FOB | K61: CANM78007000 | L61: 46031.754 | M61: 46031.754 | N61: Desembarcado | O61: HYUNDAI | P61: KDSY25100029 | Q61: SHEKOU | S61: HYUNDAI PARAMOUNT | T61: SANTOS | V61: 39.269.114/0003-39 | X61: NA WEB GROUP DE MARCAS LICENCIADAS LTDA | Y61: REACH LOGISTICS CO., LTD | Z61: WEB-JY21 - VIMP/3596 - IM1944-25 | AA61: Prepaid | AB61: DEMU0015-25 | AE61: Sem pagamento | AF61: Sem recebimento | AG61: Sem acerto com agente | AH61: Não aplicável | AJ61: 204.31 | AK61: 34720 | AL61: 204310 | AN61: FCL | AO61: 0 | AP61: 3 | AQ61: 40 HIGH CUBE | AR61: 204.31 | AT61: 46052 | AU61: =MONTH(AT61) -> 1 | AY61: PF005273/25-01 | AZ61: HMMU6463321, HMMU6895330, HMMU7179161 | BA61: Matheus Bourscheid | BD61: 1600 | BE61: 8460.11 | BF61: 150 | BG61: 150 | BH61: 1750 | BI61: 1750 | BK61: 46044.753 | BL61: 928.5 | BM61: 928.5 | BN61: 9388.61 | BO61: 9388.61 | BP61: 46006 | BR61: 6 | BT61: Tracking inativo | BU61: Falso | BW61: 0 | BX61: Ativo | BY61: Ativo
A62: 1 | B62: Marítimo importação | C62: Back to back | D62: IM2004-25 | E62: BRIELLI HOME IMPORTACAO LTDA | F62: BRIELLI HOME IMPORTACAO LTDA | G62: Shenzhen City Yongxing Sports Equipment Company Limited | H62: 45968.332 | I62: 46006 | J62: FOB | K62: CANM59727200 | L62: 45944.587 | M62: 45944.587 | N62: Desembarcado | O62: HYUNDAI | P62: KDSY25100096 | Q62: SHEKOU | S62: HYUNDAI PARAMOUNT | T62: SANTOS | V62: 61.836.272/0001-10 | X62: BRIELLI HOME IMPORTACAO LTDA | Y62: REACH LOGISTICS CO., LTD | Z62: VIMP/3634 | AA62: Prepaid | AB62: IM2004-25 | AE62: Pago | AF62: Recebido | AG62: Quitado | AH62: Não aplicável | AJ62: 65.12 | AK62: 7238 | AL62: 65120 | AN62: FCL | AO62: 0 | AP62: 1 | AQ62: 40 HIGH CUBE | AR62: 65.12 | AS62: 46042 | AT62: 46043 | AU62: =MONTH(AT62) -> 1 | AY62: PF005418/25-01 | AZ62: KOCU4741292 | BA62: Annie Audrien | BD62: 587.22 | BE62: 3857.6 | BF62: 2584.57 | BG62: 2584.57 | BH62: 3171.79 | BI62: 3171.79 | BK62: 46042.776 | BL62: 14162.86 | BM62: 13822.41 | BN62: 18020.46 | BO62: 18020.46 | BP62: 46005.208 | BQ62: 46006 | BR62: 2 | BT62: Sincronizado | BU62: Falso | BW62: 0 | BX62: Ativo | BY62: Ativo
A63: 1 | B63: Demurrage | C63: Back to back | D63: DEMU0043-26 | E63: BRISA INDUSTRIA DE TECIDOS TECNOLOGICOS S.A | F63: BRISA INDUSTRIA DE TECIDOS TECNOLOGICOS S.A | G63: HUAFON MICROFIBER (JIANGSU)CO.,LTD | H63: 45963 | I63: 46006 | J63: FOB | K63: CSC45390404500 | L63: 46045.663 | M63: 46045.664 | N63: Desembarcado | O63: CSSC - COSCO SHIPPING SPECIALIZED | P63: SZES25101010 | Q63: TAICANG | S63: GREEN ITAJAI | T63: SALVADOR | V63: 02.036.823/0001-00 | X63: BRISA INDUSTRIA DE TECIDOS TECNOLOGICOS S.A | Y63: SHENZHEN EVERSEAS INTERNATIONAL LOGISTICS CO | Z63: CCTBS-0464 / HF-CT25006 - IM1670-25 | AA63: Prepaid | AB63: DEMU0043-26 | AE63: Sem pagamento | AF63: Sem recebimento | AG63: Sem acerto com agente | AH63: Não aplicável | AL63: 0 | AN63: FCL | AO63: 1 | AP63: 0 | AQ63: HC BOX | AT63: 46065 | AU63: =MONTH(AT63) -> 2 | AZ63: SEKU6851001 | BA63: Matheus Bourscheid | BD63: 1270 | BE63: 6944.38 | BF63: 480 | BG63: 480 | BH63: 1750 | BI63: 1750 | BK63: 46057.703 | BL63: 2676.59 | BM63: 2676.59 | BN63: 9620.97 | BO63: 9620.97 | BP63: 46006 | BR63: 1 | BT63: Tracking inativo | BU63: Falso | BX63: Ativo | BY63: Ativo
A64: 1 | B64: Marítimo importação | C64: Back to back | D64: IM1670-25 | E64: BRISA INDUSTRIA DE TECIDOS TECNOLOGICOS S.A | F64: BRISA INDUSTRIA DE TECIDOS TECNOLOGICOS S.A | G64: HUAFON MICROFIBER (JIANGSU)CO.,LTD | H64: 45963 | I64: 46006 | J64: FOB | K64: CSC45390404500 | L64: 45909.496 | M64: 45909.496 | N64: Desembarcado | O64: CSSC - COSCO SHIPPING SPECIALIZED | P64: SZES25101010 | Q64: TAICANG | S64: GREEN ITAJAI | T64: SALVADOR | V64: 02.036.823/0001-00 | X64: BRISA INDUSTRIA DE TECIDOS TECNOLOGICOS S.A | Y64: SHENZHEN EVERSEAS INTERNATIONAL LOGISTICS CO | Z64: CCTBS-0464 / HF-CT25006 | AA64: Prepaid | AB64: IM1670-25 | AE64: Pago | AF64: Recebido | AG64: Quitado | AH64: Não aplicável | AL64: 0 | AN64: FCL | AO64: 1 | AP64: 0 | AQ64: HC BOX | AS64: 46045 | AT64: 46048 | AU64: =MONTH(AT64) -> 1 | AZ64: SEKU6851001 | BA64: Enila Kawely | BD64: 359.08 | BE64: 2658.6 | BF64: 2956.18 | BG64: 2956.18 | BH64: 3315.26 | BI64: 3315.26 | BK64: 46045.74 | BL64: 16114.21 | BM64: 15740.9 | BN64: 18772.81 | BO64: 18772.81 | BP64: 46006 | BQ64: 46006 | BR64: 1 | BT64: Tracking inativo | BU64: Falso | BX64: Ativo | BY64: Ativo
A65: 1 | B65: Marítimo importação | C65: Back to back | D65: IM2002-25 | E65: BRISA INDUSTRIA DE TECIDOS TECNOLOGICOS S.A | F65: BRISA INDUSTRIA DE TECIDOS TECNOLOGICOS S.A | G65: HUZHOU DOMAIN TEXTILES CO., LTD | H65: 45966 | I65: 46006 | J65: FOB | K65: CSC4539040DT00 | L65: 45944.414 | M65: 45944.414 | N65: Desembarcado | O65: CSSC - COSCO SHIPPING SPECIALIZED | P65: SZES25101295 | Q65: NINGBO | S65: GREEN ITAJAI | T65: SALVADOR | V65: 02.036.823/0001-00 | X65: BRISA INDUSTRIA DE TECIDOS TECNOLOGICOS S.A | Y65: SHENZHEN EVERSEAS INTERNATIONAL LOGISTICS CO | Z65: CCTBS-0460 -SHORTAGE OF PAOLA CREMA | AA65: Collect | AB65: IM2002-25 | AE65: Pago | AF65: Recebido | AG65: Quitado | AH65: Não aplicável | AL65: 0 | AN65: FCL | AO65: 1 | AP65: 0 | AQ65: 20 DRY BOX | AS65: 46045 | AT65: 46048 | AU65: =MONTH(AT65) -> 1 | AZ65: MAGU2510754 | BA65: Enila Kawely | BD65: 315.4 | BE65: 2274.78 | BF65: 2509.03 | BG65: 2509.03 | BH65: 2824.43 | BI65: 2824.43 | BK65: 46045.742 | BL65: 13718.71 | BM65: 13382.88 | BN65: 15993.49 | BO65: 15993.49 | BP65: 46006 | BQ65: 46006 | BR65: 1 | BT65: Tracking inativo | BU65: Falso | BX65: Ativo | BY65: Ativo
A66: 1 | B66: Marítimo importação | C66: Back to back | D66: IM2198-25 | E66: R.BRANDS LTDA | F66: R.BRANDS LTDA | G66: 3H HEADWEAR MANUFACTURING CO., LTD | H66: 45977.042 | I66: 46008 | J66: EXW | K66: SZNAV25144855 | L66: 45961.667 | M66: 45961.667 | N66: Desembarcado | O66: CHARTER LINK | P66: SWS2511047 | Q66: YANTIAN | S66: KOTA PAHLAWAN | T66: NAVEGANTES | V66: 13.992.333/0001-96 | X66: R.BRANDS LTDA | Y66: (LCL) SHENZHEN SMOOTHWIN INTERNATIONAL | Z66: 3HM-12213 + 3HM-12276 - ILOG 5380/25 | AA66: Collect | AB66: 5380/25 | AE66: Pago | AF66: Recebido | AG66: Quitado | AH66: Não aplicável | AJ66: 3.412 | AK66: 433.5 | AL66: 3412 | AN66: LCL | AO66: 0 | AP66: 0 | AR66: 3.412 | AS66: 46028 | AT66: 46028 | AU66: =MONTH(AT66) -> 1 | AV66: LEADER LOGISTICS LTDA FILIAL ITJ | AY66: PF005857/25-01 | AZ66: TCLU6569306 | BA66: Tiago Schneider | BB66: Mariana Reis | BD66: 280.39 | BE66: 1610.06 | BF66: 197.46 | BG66: 197.46 | BH66: 477.85 | BI66: 477.85 | BK66: 46028.757 | BL66: 1101.51 | BM66: 1090.03 | BN66: 2711.57 | BO66: 2711.57 | BP66: 46009 | BQ66: 46008 | BR66: 0 | BT66: Sincronizado | BU66: Falso | BV66: 15756 | BW66: 0 | BX66: Ativo | BY66: Ativo
A67: 1 | B67: Marítimo importação | C67: Back to back | D67: IM2079-25 | E67: OIW INDUSTRIA ELETRONICA S.A | F67: OIW INDUSTRIA ELETRONICA S.A | G67: OP FIBRA | H67: 45962.238 | I67: 46008.015 | J67: FOB | L67: 45951.687 | M67: 45951.687 | N67: Desembarcado | O67: WORLD FREIGHT 03-03 | P67: NBOITJ25A183 | Q67: NINGBO | S67: HYUNDAI TOKYO | T67: NAVEGANTES | V67: 07.212.549/0008-65 | X67: OIW INDUSTRIA ELETRONICA S.A | Y67: WORLD FREIGHT AG. E TRANSP. LTDA | Z67: PO OIW-BA-20250813B - ILOG 5192/25 | AA67: Collect | AB67: 5192/25 | AE67: Parcialmente pago | AF67: Recebido | AG67: Sem acerto com agente | AH67: Não aplicável | AJ67: 2.59 | AK67: 383 | AL67: 2590 | AN67: LCL | AO67: 0 | AP67: 0 | AR67: 2.59 | AS67: 46041 | AT67: 46041 | AU67: =MONTH(AT67) -> 1 | AV67: LEADER LOGISTICS LTDA FILIAL ITJ | AY67: PF005574/25-01 | AZ67: HMMU5501221 | BA67: Bruna Kelsch | BD67: 71.5 | BE67: 406.03 | BF67: 15.24 | BG67: 14.95 | BH67: 86.74 | BI67: 86.74 | BK67: 46041.615 | BL67: 88.53 | BM67: 86.85 | BN67: 494.56 | BO67: 494.56 | BR67: 0 | BT67: Sincronizado | BU67: Falso | BW67: 0 | BX67: Ativo | BY67: Ativo
A68: 1 | B68: Marítimo importação | C68: Back to back | D68: IM2130-25 | E68: CALCADOS BEIRA RIO S/A | F68: CALCADOS BEIRA RIO S/A | G68: ATTIVO INTERNATIONAL LIMITED | H68: 45977.549 | I68: 46008.799 | J68: FOB | K68: SZNSTS25A319 | L68: 45954.623 | M68: 45954.623 | N68: Desembarcado | O68: HYUNDAI | P68: SWS2511018 | Q68: SHEKOU | S68: HMM IVY | T68: SANTOS | V68: 88.379.771/0035-21 | X68: CALCADOS BEIRA RIO S/A | Y68: (LCL) SHENZHEN SMOOTHWIN INTERNATIONAL | Z68: 699/25- ATTIVO - PI 2510264 - ILOG 5223/25 | AA68: Collect | AB68: 5223/25 | AE68: Pago | AF68: Recebido | AG68: Quitado | AH68: Não aplicável | AJ68: 8.8 | AK68: 3268 | AL68: 8800 | AN68: LCL | AO68: 0 | AP68: 0 | AR68: 8.8 | AS68: 46029 | AT68: 46031 | AU68: =MONTH(AT68) -> 1 | AV68: LEADER LOGISTICS LTDA FILIAL ITJ | AZ68: HDMU5634587 | BA68: Matheus Ropelato | BD68: 410.53 | BE68: 2232.01 | BF68: 1009.03 | BG68: 1009.03 | BH68: 1419.56 | BI68: 1419.56 | BK68: 46029.77 | BL68: 5823.38 | BM68: 5819.94 | BN68: 8055.39 | BO68: 8055.39 | BP68: 46020 | BQ68: 46020.522 | BR68: 0 | BT68: Sincronizado | BU68: Falso | BW68: 0 | BX68: Ativo | BY68: Ativo
A69: 1 | B69: Marítimo importação | C69: Back to back | D69: IM2185-25 | E69: R.BRANDS LTDA | F69: CAMARA DOS DEPUTADOS | G69: R. BRANDS LTDA LLC | H69: 45977.549 | I69: 46008.799 | J69: DAP | K69: PSLSZXSTS01521 | L69: 45960.66 | M69: 45960.66 | N69: Desembarcado | O69: KINGSHIP LINE LTDA | P69: SWS2511043 | Q69: SHEKOU | S69: HMM IVY | T69: SANTOS | V69: 13.992.333/0001-96 | X69: CAMARA DOS DEPUTADOS | Y69: (LCL) SHENZHEN SMOOTHWIN INTERNATIONAL | Z69: LLC-12225 + LLC-12296-Licitação | AA69: Collect | AB69: IM2185-25 | AE69: Pago | AF69: Recebido | AG69: Parcialmente quitado | AH69: Não aplicável | AJ69: 5.84 | AK69: 1376 | AL69: 5840 | AN69: LCL | AO69: 0 | AP69: 0 | AR69: 5.84 | AT69: 46059 | AU69: =MONTH(AT69) -> 2 | AV69: LEADER LOGISTICS LTDA FILIAL ITJ | AY69: PF005774/25-01 | AZ69: TCLU6363193 | BA69: Tiago Schneider | BB69: Mariana Reis | BD69: 1166.44 | BE69: 6167.85 | BF69: 94.21 | BG69: 94.21 | BH69: 1260.65 | BI69: 304.59 | BK69: 46114.458 | BL69: 512.54 | BM69: 509.01 | BN69: 6680.39 | BO69: 1674.56 | BP69: 46008.57 | BQ69: 46008.799 | BR69: 0 | BT69: Sincronizado | BU69: Falso | BV69: 117000 | BW69: 0 | BX69: Ativo | BY69: Ativo
A70: 1 | B70: Aéreo importação | C70: Back to back | D70: IA0680-25 | E70: CALCADOS BEIRA RIO S/A | F70: CALCADOS BEIRA RIO S/A | G70: ATTIVO INTERNATIONAL LIMITED | H70: 46008 | I70: 46009 | J70: FCA | K70: 02020904074 | L70: 46001.698 | M70: 46001.698 | N70: Desembarcado | O70: LUFTHANSA CARGO | P70: WA251201955 | Q70: PU DONG (SHANGHAI) | T70: GUARULHOS | V70: 88.379.771/0035-21 | X70: CALCADOS BEIRA RIO S/A | Y70: FREIGHTSHOP FREIGHT CO.,LTD | Z70: 832/25- ATTIVO - PI 2512355 - ILOG 6308/25 | AA70: Prepaid | AB70: 6308/25 | AE70: Pago | AF70: Recebido | AG70: Quitado | AH70: Desconsolidado | AJ70: 0.05 | AK70: 26 | AL70: 8.115 | AM70: 26 | AN70: Aéreo | AR70: 26 | AS70: 46021 | AT70: 46028 | AU70: =MONTH(AT70) -> 1 | AV70: LEADER LOGISTICS LTDA FILIAL ITJ | BA70: Matheus Ropelato | BD70: 153.73 | BE70: 1119.74 | BF70: 1080.37 | BG70: 1080.37 | BH70: 1234.1 | BI70: 1234.1 | BK70: 46021.737 | BL70: 5907.4 | BM70: 5650.7 | BN70: 7027.14 | BO70: 7027.14 | BP70: 46015 | BQ70: 46015.333 | BS70: Back to back | BT70: Tracking inativo | BU70: Falso | BW70: 0 | BX70: Ativo | BY70: Ativo
A71: 1 | B71: Demurrage | C71: Back to back | D71: DEMU0039-26 | E71: NA WEB GROUP DE MARCAS LICENCIADAS LTDA | F71: NA WEB GROUP DE MARCAS LICENCIADAS LTDA | G71: HEBEI ZHONGTAI BICYCLE MANUFACTURING CO.,LTD | H71: 45934.083 | I71: 46010.958 | J71: FOB | K71: TJN0768784 | L71: 46043.686 | M71: 46043.686 | N71: Desembarcado | O71: COMPAGNIE GENERALE MARITIME - CMA CGM | P71: KDSY25090096 | Q71: XINGANG | S71: CMA CGM DIGNITY | T71: SANTOS | U71: SANTA INES | V71: 39.269.114/0003-39 | X71: NA WEB GROUP DE MARCAS LICENCIADAS LTDA | Y71: REACH LOGISTICS CO., LTD | Z71: WEB192025 - PRO25000526 - NAWEB100SET25 - IM1715-25 | AA71: Prepaid | AB71: DEMU0039-26 | AE71: Sem pagamento | AF71: Sem recebimento | AG71: Sem acerto com agente | AH71: Não aplicável | AJ71: 133.64 | AK71: 8470.6 | AL71: 133640 | AN71: FCL | AO71: 0 | AP71: 2 | AQ71: 40 HIGH CUBE | AR71: 133.64 | AT71: 46058 | AU71: =MONTH(AT71) -> 2 | AY71: PF004698/25-01 | AZ71: CMAU6863826, TRHU4722844 | BA71: Matheus Bourscheid | BD71: 210 | BE71: 1099.48 | BF71: 0 | BG71: 0 | BH71: 210 | BI71: 210 | BK71: 46050.735 | BL71: 0 | BM71: 0 | BN71: 1099.48 | BO71: 1099.48 | BP71: 46010.958 | BR71: 4 | BT71: Tracking inativo | BU71: Falso | BW71: 0 | BX71: Ativo | BY71: Ativo
A72: 1 | B72: Demurrage | C72: Back to back | D72: DEMU0031-26 | E72: J A QUADROS INDUSTRIAL COMERCIAL DE CALCADOS E SOJ | F72: J A QUADROS INDUSTRIAL COMERCIAL DE CALCADOS E SOJ | G72: FUJIAN FULONG SUPPLY CHAIN MANAGEMENT CO.,LTD | H72: 45967.428 | I72: 46011.035 | J72: FOB | K72: MAEU260150068 | L72: 46042.742 | M72: 46042.742 | N72: Desembarcado | O72: MAERSK | P72: KDSY25100046 | Q72: XIAMEN | S72: G. DRAGON | T72: PECEM | U72: VICENTE PINZON | V72: 08.984.431/0001-41 | X72: J A QUADROS INDUSTRIAL COMERCIAL DE CALCADOS E SOJ | Y72: REACH LOGISTICS CO., LTD | Z72: 2025.10.03 + XCD20250620 + ILOG 4659/25 - IM1991-25 | AA72: Collect | AB72: DEMU0031-26 | AE72: Sem pagamento | AF72: Sem recebimento | AG72: Sem acerto com agente | AH72: Não aplicável | AJ72: 68 | AK72: 20702 | AL72: 68000 | AN72: FCL | AO72: 0 | AP72: 1 | AQ72: 40 HIGH CUBE | AR72: 68 | AT72: 46051 | AU72: =MONTH(AT72) -> 1 | AY72: PF005385/25-01 | AZ72: MRSU7710166 | BA72: Matheus Bourscheid | BD72: 678.8 | BE72: 3855.69 | BF72: 821.2 | BG72: 821.2 | BH72: 1500 | BI72: 1500 | BK72: 46043.694 | BL72: 4549.77 | BM72: 4549.77 | BN72: 8405.46 | BO72: 8405.46 | BP72: 46011.035 | BR72: 2 | BT72: Tracking inativo | BU72: Falso | BW72: 0 | BX72: Ativo | BY72: Ativo
A73: 1 | B73: Marítimo importação | C73: Back to back | D73: IM2151-25 | E73: ACTIA DO BRASIL INDUSTRIA E COMERCIO LTDA | F73: ACTIA DO BRASIL INDUSTRIA E COMERCIO LTDA | G73: HONG KONG FREEDOM TRADING LIMITED | H73: 45985.44 | I73: 46011.661 | J73: EXW | K73: 2025110546 | L73: 45958.625 | M73: 45958.625 | N73: Desembarcado | O73: WORLD FREIGHT 03-03 | P73: SWS2511038 | Q73: HONG KONG | S73: ZIM CANADA | T73: SANTOS | V73: 01.733.265/0001-61 | X73: ACTIA DO BRASIL INDUSTRIA E COMERCIO LTDA | Y73: (LCL) SHENZHEN SMOOTHWIN INTERNATIONAL | Z73: 250102 | AA73: Collect | AB73: IM2151-25 | AE73: Pago | AF73: Recebido | AG73: Quitado | AH73: Não aplicável | AJ73: 4.08 | AK73: 1155 | AL73: 4080 | AN73: LCL | AO73: 0 | AP73: 0 | AR73: 4.08 | AS73: 45666 | AT73: 46031 | AU73: =MONTH(AT73) -> 1 | AV73: LEADER LOGISTICS LTDA FILIAL ITJ | AY73: PF005761/25-01 | AZ73: MRSU7792190 | BA73: Tiago Schneider | BD73: 635.14 | BE73: 3673.52 | BF73: 2058.95 | BG73: 2058.95 | BH73: 2694.09 | BI73: 2694.09 | BK73: 46030.656 | BL73: 11248.78 | BM73: 10942.21 | BN73: 14922.3 | BO73: 14922.3 | BP73: 46027 | BQ73: 46027.54 | BR73: 0 | BT73: Sincronizado | BU73: Falso | BW73: 0 | BX73: Ativo | BY73: Ativo
A74: 1 | B74: Marítimo importação | C74: Back to back | D74: IM1891-25 | E74: PROJETO DISTRIBUIÇÃO CSL | F74: INFINITY GOODS DISTRIBUIDORA LTDA | G74: Elite International Co., Ltd. | H74: 45959 | I74: 46012 | J74: FOB | K74: HDMUTAOM36164000 | L74: 45930.478 | M74: 45930.478 | N74: Desembarcado | O74: HYUNDAI | P74: KDSY25100009 | Q74: QINGDAO | S74: HYUNDAI BRAVE | T74: NAVEGANTES | X74: INFINITY GOODS DISTRIBUIDORA LTDA | Y74: REACH LOGISTICS CO., LTD | Z74: PI NO.: 25E6258 - ILOG 5153/25 | AA74: Prepaid | AB74: 5153/25 | AE74: Pago | AF74: Recebido | AG74: Quitado | AH74: Não aplicável | AJ74: 128 | AK74: 54160 | AL74: 128000 | AN74: FCL | AO74: 0 | AP74: 2 | AQ74: 40 HIGH CUBE | AR74: 128 | AS74: 46030 | AT74: 46030 | AU74: =MONTH(AT74) -> 1 | AV74: LEADER LOGISTICS LTDA FILIAL ITJ | AY74: PF005110/25-01 | AZ74: KOCU4063702, KOCU4811851 | BA74: Matheus Ropelato | BD74: 345.39 | BE74: 4294.68 | BF74: 5720.36 | BG74: 5720.36 | BH74: 6065.75 | BI74: 6065.75 | BK74: 46031.668 | BL74: 30982.77 | BM74: 29827.81 | BN74: 35277.45 | BO74: 35277.45 | BP74: 46014 | BQ74: 46012 | BR74: 4 | BT74: Divergência viagens | BU74: Falso | BW74: 0 | BX74: Ativo | BY74: Ativo
A75: 1 | B75: Demurrage | C75: Back to back | D75: DEMU0045-26 | E75: PROJETO DISTRIBUIÇÃO CSL | F75: INFINITY GOODS DISTRIBUIDORA LTDA | G75: Elite International Co., Ltd. | H75: 45959 | I75: 46012 | J75: FOB | K75: HDMUTAOM36164000 | L75: 46045.685 | M75: 46045.685 | N75: Desembarcado | O75: HYUNDAI | P75: KDSY25100009 | Q75: QINGDAO | S75: HYUNDAI BRAVE | T75: NAVEGANTES | X75: INFINITY GOODS DISTRIBUIDORA LTDA | Y75: REACH LOGISTICS CO., LTD | Z75: PI NO.: 25E6258 - ILOG 5153/25 | AA75: Prepaid | AB75: 5153/25 | AE75: Sem pagamento | AF75: Sem recebimento | AG75: Sem acerto com agente | AH75: Não aplicável | AJ75: 128 | AK75: 54160 | AL75: 128000 | AN75: FCL | AO75: 0 | AP75: 2 | AQ75: 40 HIGH CUBE | AR75: 128 | AT75: 46066 | AU75: =MONTH(AT75) -> 2 | AV75: LEADER LOGISTICS LTDA FILIAL ITJ | AY75: PF005110/25-01 | AZ75: KOCU4063702, KOCU4811851 | BA75: Matheus Bourscheid | BD75: 700 | BE75: 3640.7 | BF75: 300 | BG75: 300 | BH75: 1000 | BI75: 1000 | BK75: 46057.715 | BL75: 1857 | BM75: 1857 | BN75: 5497.7 | BO75: 5497.7 | BP75: 46014 | BR75: 4 | BT75: Tracking inativo | BU75: Falso | BW75: 0 | BX75: Ativo | BY75: Ativo
A76: 1 | B76: Aéreo importação | C76: Back to back | D76: IA0682-25 | E76: TADMEDICAL COMERCIO E IMPORTACAO DE MATERIAL MEDICO LTDA | F76: TADMEDICAL COMERCIO E IMPORTACAO DE MATERIAL MEDICO LTDA | G76: Fengh Medical Co., LTD | H76: 46010 | I76: 46012 | J76: EXW | K76: 05757598553 | L76: 46002.612 | M76: 46002.612 | N76: Desembarcado | O76: AIR FRANCE | P76: BNBA2512034 | Q76: PEQUIM (BEIJING) | T76: SALVADOR | V76: 15.347.273/0001-84 | X76: TADMEDICAL COMERCIO E IMPORTACAO DE MATERIAL MEDICO LTDA | Y76: BVL - BON VOYAGE LOGISTICS INC. | Z76: FENGH | AA76: Prepaid | AB76: IA0682-25 | AE76: Pago | AF76: Recebido | AG76: Quitado | AH76: Desconsolidado | AJ76: 0.19 | AK76: 18 | AL76: 31.667 | AM76: 32 | AN76: Aéreo | AR76: 31.667 | AS76: 46051 | AT76: 46051 | AU76: =MONTH(AT76) -> 1 | AY76: PF006678/25-01 | BA76: Bruna Kelsch | BD76: -28.75 | BE76: 256.36 | BF76: 1455.22 | BG76: 1455.22 | BH76: 1426.47 | BI76: 1426.47 | BK76: 46051.65 | BL76: 8039.78 | BM76: 7577.46 | BN76: 8296.14 | BO76: 8296.14 | BP76: 46013 | BQ76: 46012 | BS76: Back to back | BT76: Tracking inativo | BU76: Falso | BW76: 0 | BX76: Ativo | BY76: Ativo
A77: 1 | B77: Marítimo importação | C77: Back to back | D77: IM2057-25 | E77: R.R INDUSTRIA E COMERCIO DE MALHAS LTDA | F77: R.R INDUSTRIA E COMERCIO DE MALHAS LTDA | G77: GOLDEN-AGRI INTERNATIONAL CO.,LIMITED | H77: 45965.965 | I77: 46012.585 | J77: FOB | K77: HDMUSHAZE6U79300 | L77: 45950.711 | M77: 45950.711 | N77: Desembarcado | O77: HYUNDAI | P77: KDSY25100172 | Q77: SHANGHAI | S77: HYUNDAI BRAVE | T77: NAVEGANTES | V77: 08.827.389/0001-55 | X77: R.R INDUSTRIA E COMERCIO DE MALHAS LTDA | Y77: REACH LOGISTICS CO., LTD | Z77: ILOG 4579/25 - PI NO. AGR/250919 | AA77: Prepaid | AB77: 4579/25 | AE77: Pago | AF77: Recebido | AG77: Quitado | AH77: Não aplicável | AJ77: 60 | AK77: 26180 | AL77: 60000 | AN77: FCL | AO77: 0 | AP77: 1 | AQ77: 40 HIGH CUBE | AR77: 60 | AS77: 46020 | AT77: 46028 | AU77: =MONTH(AT77) -> 1 | AV77: LEADER LOGISTICS LTDA FILIAL ITJ | AY77: PF005543/25-01 | AZ77: SEGU5851804 | BA77: Annie Audrien | BD77: 365.84 | BE77: 3346.79 | BF77: 2677.96 | BG77: 2677.96 | BH77: 3043.8 | BI77: 3043.8 | BK77: 46024.72 | BL77: 14467.34 | BM77: 14002.44 | BN77: 17814.13 | BO77: 17814.13 | BP77: 46012.585 | BQ77: 46012.585 | BR77: 2 | BT77: Sincronizado | BU77: Falso | BW77: 0 | BX77: Ativo | BY77: Ativo
A78: 1 | B78: Demurrage | C78: Back to back | D78: DEMU0023-26 | E78: DL SOLUCOES EM COMEX LTDA | F78: FHC PINTURAS E MAQUINAS LTDA | G78: Shandong Hongniu Laser Equipment Co., LTD. | H78: 45959.237 | I78: 46012.585 | J78: FOB | K78: HDMUTAOM90756000 | L78: 46036.631 | M78: 46036.631 | N78: Desembarcado | O78: HYUNDAI | P78: KDSY25100031 | Q78: QINGDAO | S78: HYUNDAI BRAVE | T78: NAVEGANTES | V78: 36.616.150/0001-71 | X78: FHC PINTURAS E MAQUINAS LTDA | Y78: REACH LOGISTICS CO., LTD | Z78: PI HN-20250809DL - ILOG 4808/25 - IM1907-25 | AA78: Collect | AB78: DEMU0023-26 | AE78: Sem pagamento | AF78: Sem recebimento | AG78: Sem acerto com agente | AH78: Não aplicável | AJ78: 42.49 | AK78: 9100 | AL78: 42490 | AN78: FCL | AO78: 0 | AP78: 1 | AQ78: 40 HIGH CUBE | AR78: 42.49 | AT78: 46038 | AU78: =MONTH(AT78) -> 1 | AV78: LEADER LOGISTICS LTDA FILIAL ITJ | AY78: PF002900/25-02 | AZ78: HMMU6131224 | BA78: Matheus Bourscheid | BD78: 350 | BE78: 1958.74 | BF78: 150 | BG78: 150 | BH78: 500 | BI78: 500 | BK78: 46036.634 | BL78: 865.5 | BM78: 865.5 | BN78: 2824.24 | BO78: 2824.24 | BP78: 46012.585 | BR78: 2 | BT78: Tracking inativo | BU78: Falso | BW78: 0 | BX78: Ativo | BY78: Ativo
A79: 1 | B79: Marítimo importação | C79: Back to back | D79: IM1852-25 | E79: BRISA INDUSTRIA DE TECIDOS TECNOLOGICOS S.A | F79: BRISA INDUSTRIA DE TECIDOS TECNOLOGICOS S.A | G79: GUANGDONG CCENTAURUS TECHNOLOGY CO., LTD | H79: 45932.172 | I79: 46013 | J79: FOB | K79: 259516559 | L79: 45925.48 | M79: 45925.48 | N79: Desembarcado | O79: MAERSK | P79: SZES25091048B | Q79: CHONGQING | S79: DUMMY BARGE | T79: SALVADOR | U79: MAERSK LOTA | V79: 02.036.823/0001-00 | X79: BRISA INDUSTRIA DE TECIDOS TECNOLOGICOS S.A | Y79: SHENZHEN EVERSEAS INTERNATIONAL LOGISTICS CO | Z79: CCT0011-25 + CCT0013-25 | AA79: Collect | AB79: IM1852-25 | AE79: Pago | AF79: Recebido | AG79: Quitado | AH79: Não aplicável | AL79: 0 | AN79: FCL | AO79: 1 | AP79: 0 | AQ79: HC BOX | AS79: 46024 | AT79: 46029 | AU79: =MONTH(AT79) -> 1 | AZ79: TCKU7329534 | BA79: Enila Kawely | BD79: 179.79 | BE79: 1056.2 | BF79: 28.2 | BG79: 28.2 | BH79: 207.99 | BI79: 207.99 | BK79: 46052.701 | BL79: 160.49 | BM79: 160.27 | BN79: 1216.69 | BO79: 1216.69 | BP79: 46013.833 | BQ79: 46013 | BR79: 1 | BT79: Sincronizado | BU79: Falso | BX79: Ativo | BY79: Ativo
A80: 1 | B80: Demurrage | C80: Back to back | D80: DEMU0030-26 | E80: BRISA INDUSTRIA DE TECIDOS TECNOLOGICOS S.A | F80: BRISA INDUSTRIA DE TECIDOS TECNOLOGICOS S.A | G80: FINPARC SRL | H80: 45991.62 | I80: 46013 | J80: FOB | K80: 261815946 | L80: 46042.735 | M80: 46042.735 | N80: Desembarcado | O80: MAERSK | P80: 945401/2025/09 | Q80: GENOA | S80: SHIJING | T80: SALVADOR | U80: MAERSK LOTA | V80: 02.036.823/0001-00 | X80: BRISA INDUSTRIA DE TECIDOS TECNOLOGICOS S.A | Y80: ALISPED S.P.A. | Z80: 1X40'HC CARGA IMO - WEEK 47 - IM2282-25 | AA80: Collect | AB80: DEMU0030-26 | AE80: Sem pagamento | AF80: Sem recebimento | AG80: Sem acerto com agente | AH80: Não aplicável | AJ80: 23 | AK80: 10350 | AL80: 23000 | AN80: FCL | AO80: 1 | AP80: 0 | AQ80: HC BOX | AR80: 23 | AT80: 46063 | AU80: =MONTH(AT80) -> 2 | AY80: PF000508/23-01 | AZ80: MRKU4386940 | BA80: Matheus Bourscheid | BD80: 366.51 | BE80: 2403.03 | BF80: 142.53 | BG80: 142.53 | BH80: 509.04 | BI80: 509.04 | BK80: 46055.718 | BL80: 909.95 | BM80: 909.95 | BN80: 3312.98 | BO80: 3312.98 | BP80: 46013 | BR80: 1 | BT80: Tracking inativo | BU80: Falso | BW80: 0 | BX80: Ativo | BY80: Ativo
A81: 1 | B81: Demurrage | C81: Back to back | D81: DEMU0052-26 | E81: BRISA INDUSTRIA DE TECIDOS TECNOLOGICOS S.A | F81: BRISA INDUSTRIA DE TECIDOS TECNOLOGICOS S.A | G81: GUANGDONG CCENTAURUS TECHNOLOGY CO., LTD | H81: 45932.172 | I81: 46013 | J81: FOB | K81: 259516559 | L81: 46055.657 | M81: 46055.657 | N81: Desembarcado | O81: MAERSK | P81: SZES25091048B | Q81: CHONGQING | S81: DUMMY BARGE | T81: SALVADOR | U81: MAERSK LOTA | V81: 02.036.823/0001-00 | X81: BRISA INDUSTRIA DE TECIDOS TECNOLOGICOS S.A | Y81: SHENZHEN EVERSEAS INTERNATIONAL LOGISTICS CO | Z81: CCT0011-25 + CCT0013-25 - IM1852-25 + IM1390-25 | AA81: Collect | AB81: DEMU0052-26 | AE81: Sem pagamento | AF81: Sem recebimento | AG81: Sem acerto com agente | AH81: Não aplicável | AL81: 0 | AN81: FCL | AO81: 1 | AP81: 0 | AQ81: HC BOX | AT81: 46066 | AU81: =MONTH(AT81) -> 2 | AZ81: TCKU7329534 | BA81: Matheus Bourscheid | BD81: 910 | BE81: 4832.45 | BF81: 1890 | BG81: 1890 | BH81: 2800 | BI81: 2800 | BK81: 46059.714 | BL81: 10555.8 | BM81: 10555.8 | BN81: 15388.25 | BO81: 15388.25 | BP81: 46013.833 | BR81: 1 | BT81: Tracking inativo | BU81: Falso | BX81: Ativo | BY81: Ativo
A82: 1 | B82: Marítimo importação | C82: Back to back | D82: IM1390-25 | E82: BRISA INDUSTRIA DE TECIDOS TECNOLOGICOS S.A | F82: BRISA INDUSTRIA DE TECIDOS TECNOLOGICOS S.A | G82: C.CENTAURUS TECHNOLOGY LTD | H82: 45932.172 | I82: 46013 | J82: FOB | K82: 259516559 | L82: 45876.7 | M82: 45876.7 | N82: Desembarcado | O82: MAERSK | P82: SZES25091048A | Q82: CHONGQING | S82: DUMMY BARGE | T82: SALVADOR | U82: MAERSK LOTA | V82: 02.036.823/0001-00 | X82: BRISA INDUSTRIA DE TECIDOS TECNOLOGICOS S.A | Y82: SHENZHEN EVERSEAS INTERNATIONAL LOGISTICS CO | Z82: CCTBS-0457 | AA82: Collect | AB82: IM1390-25 | AE82: Pago | AF82: Recebido | AG82: Quitado | AH82: Não aplicável | AL82: 0 | AN82: FCL | AO82: 1 | AP82: 0 | AQ82: HC BOX | AS82: 46024 | AT82: 46029 | AU82: =MONTH(AT82) -> 1 | AZ82: TCKU7329534 | BA82: Enila Kawely | BD82: 584.15 | BE82: 4068.44 | BF82: 4258.32 | BG82: 4258.32 | BH82: 4842.47 | BI82: 4842.47 | BK82: 46052.7 | BL82: 24258.84 | BM82: 24251.73 | BN82: 28327.28 | BO82: 28327.28 | BP82: 46013.833 | BQ82: 46013 | BR82: 1 | BT82: Sincronizado | BU82: Falso | BX82: Ativo | BY82: Ativo
A83: 1 | B83: Marítimo importação | C83: Back to back | D83: IM2282-25 | E83: BRISA INDUSTRIA DE TECIDOS TECNOLOGICOS S.A | F83: BRISA INDUSTRIA DE TECIDOS TECNOLOGICOS S.A | G83: FINPARC SRL | H83: 45991.62 | I83: 46013 | J83: FOB | K83: 261815946 | L83: 45974.389 | M83: 45974.389 | N83: Desembarcado | O83: MAERSK | P83: 945401/2025/09 | Q83: GENOA | S83: SHIJING | T83: SALVADOR | U83: MAERSK LOTA | V83: 02.036.823/0001-00 | X83: BRISA INDUSTRIA DE TECIDOS TECNOLOGICOS S.A | Y83: ALISPED S.P.A. | Z83: 1X40'HC CARGA IMO - WEEK 47 | AA83: Collect | AB83: IM2282-25 | AE83: Pago | AF83: Recebido | AG83: Quitado | AH83: Não aplicável | AJ83: 23 | AK83: 10350 | AL83: 23000 | AN83: FCL | AO83: 1 | AP83: 0 | AQ83: HC BOX | AR83: 23 | AS83: 46065 | AT83: 46065 | AU83: =MONTH(AT83) -> 2 | AY83: PF000508/23-01 | AZ83: MRKU4386940 | BA83: Enila Kawely | BD83: 354.54 | BE83: 2956.39 | BF83: 1322.04 | BG83: 1322.04 | BH83: 1676.58 | BI83: 1676.58 | BK83: 46041.656 | BL83: 8580.25 | BM83: 8460.72 | BN83: 11536.64 | BO83: 11536.64 | BP83: 46013 | BQ83: 46013 | BR83: 1 | BT83: Sincronizado | BU83: Falso | BW83: 0 | BX83: Ativo | BY83: Ativo
A84: 1 | B84: Marítimo importação | C84: Back to back | D84: IM2184-25 | E84: BRISA INDUSTRIA DE TECIDOS TECNOLOGICOS S.A | F84: BRISA INDUSTRIA DE TECIDOS TECNOLOGICOS S.A | G84: FINPARC SRL | H84: 45987.669 | I84: 46013.821 | J84: FOB | K84: 261369935 | L84: 45960.615 | M84: 45960.615 | N84: Desembarcado | O84: MAERSK | P84: 945202/2025/09 | Q84: GENOA | S84: MAERSK SEMBAWANG | T84: SALVADOR | U84: MAERSK LOTA | V84: 02.036.823/0001-00 | X84: BRISA INDUSTRIA DE TECIDOS TECNOLOGICOS S.A | Y84: ALISPED S.P.A. | Z84: CARGA GERAL - 1X40'HC | AA84: Collect | AB84: IM2184-25 | AE84: Pago | AF84: Recebido | AG84: Quitado | AH84: Não aplicável | AJ84: 23 | AK84: 10350 | AL84: 23000 | AN84: FCL | AO84: 1 | AP84: 0 | AQ84: HC BOX | AR84: 23 | AS84: 46024 | AT84: 46029 | AU84: =MONTH(AT84) -> 1 | AY84: PF000508/23-01 | AZ84: MRSU6822916 | BA84: Enila Kawely | BD84: 341.94 | BE84: 2734.36 | BF84: 1052.23 | BG84: 1052.23 | BH84: 1394.17 | BI84: 1394.17 | BK84: 46035.674 | BL84: 6859.03 | BM84: 6718.07 | BN84: 9593.39 | BO84: 9593.39 | BP84: 46013.833 | BQ84: 46013.821 | BR84: 1 | BT84: Sincronizado | BU84: Falso | BW84: 0 | BX84: Ativo | BY84: Ativo
A85: 1 | B85: Marítimo importação | C85: Back to back | D85: IM1805-25 | E85: Nexen Energias Renovaveis Ltda | F85: Nexen Energias Renovaveis Ltda | G85: HUANSHENG PHOTOVOLTAIC (JIANGSU) CO., LTD | H85: 45954.342 | I85: 46014 | J85: FOB | K85: COSU6433266400 | L85: 45922.599 | M85: 45922.599 | N85: Desembarcado | O85: COSCO BRASIL | P85: ESL25091378 | Q85: XINGANG | S85: CSCL AUTUMN | T85: ITAPOA | U85: COSCO SHIPPING CHILE | V85: 31.841.964/0001-96 | X85: WINNING TRADING S.A. (SC) | Y85: EAST SHINE SHIPPING CO., LTD. | Z85: ILOG 3877/25 | AA85: Collect | AB85: 3877/25 | AE85: Pago | AF85: Recebido | AG85: Quitado | AH85: Não aplicável | AJ85: 404.46 | AK85: 148080 | AL85: 404460 | AN85: FCL | AO85: 0 | AP85: 6 | AQ85: 40 HIGH CUBE | AR85: 404.46 | AS85: 46041 | AT85: 46041 | AU85: =MONTH(AT85) -> 1 | AV85: LEADER LOGISTICS LTDA FILIAL ITJ | AY85: PF004149/25-03 | AZ85: CSNU6560770, FSCU8696682, OOCU7652402, OOCU8154410, TIIU5723199, UETU5611684 | BA85: Annie Audrien | BD85: 3189.61 | BE85: 22118.57 | BF85: 17554.44 | BG85: 17554.44 | BH85: 20744.05 | BI85: 20744.05 | BK85: 46041.359 | BL85: 94744.41 | BM85: 96176.74 | BN85: 116862.98 | BO85: 116862.98 | BP85: 46014.312 | BQ85: 46014.293 | BR85: 12 | BT85: Sincronizado | BU85: Falso | BW85: 0 | BX85: Ativo | BY85: Ativo
A86: 1 | B86: Demurrage | C86: Back to back | D86: DEMU0035-26 | E86: NA WEB GROUP DE MARCAS LICENCIADAS LTDA | F86: NA WEB GROUP DE MARCAS LICENCIADAS LTDA | G86: HEBEI ZHONGTAI BICYCLE MANUFACTURING CO.,LTD | H86: 45952.535 | I86: 46014 | J86: FOB | K86: TS5QJ3724500 | L86: 46043.66 | M86: 46043.66 | N86: Desembarcado | O86: ONE | P86: KDSY25100043 | Q86: XINGANG | S86: CHANG SHUN QIAN CHENG | T86: SANTOS | U86: MOL EXPERIENCE | V86: 39.269.114/0003-39 | X86: NA WEB GROUP DE MARCAS LICENCIADAS LTDA | Y86: REACH LOGISTICS CO., LTD | Z86: WEB122025 - PRO25000561 - NAWEB114OUT25 - IM1943-25 | AA86: Prepaid | AB86: DEMU0035-26 | AE86: Sem pagamento | AF86: Sem recebimento | AG86: Sem acerto com agente | AH86: Não aplicável | AJ86: 67.26 | AK86: 8691 | AL86: 67260 | AN86: FCL | AO86: 0 | AP86: 1 | AQ86: 40 HIGH CUBE | AR86: 67.26 | AT86: 46058 | AU86: =MONTH(AT86) -> 2 | AY86: PF005272/25-01 | AZ86: TCLU4619624 | BA86: Matheus Bourscheid | BD86: 200 | BE86: 1047.13 | BF86: 0 | BG86: 0 | BH86: 200 | BI86: 200 | BK86: 46050.743 | BL86: 0 | BM86: 0 | BN86: 1047.13 | BO86: 1047.13 | BP86: 46014.042 | BR86: 2 | BT86: Tracking inativo | BU86: Falso | BW86: 0 | BX86: Ativo | BY86: Ativo
A87: 1 | B87: Marítimo importação | C87: Back to back | D87: IM1673-25 | E87: BRISA INDUSTRIA DE TECIDOS TECNOLOGICOS S.A | F87: BRISA INDUSTRIA DE TECIDOS TECNOLOGICOS S.A | G87: EASTEX INDUSTRIAL SCIENCE AND TECHNOLOGY CO., LTD | H87: 45970 | I87: 46014 | J87: FOB | K87: CSC45320805C00 | L87: 45909.535 | M87: 45909.535 | N87: Desembarcado | O87: CSSC - COSCO SHIPPING SPECIALIZED | P87: SZES25101250 | Q87: QINGDAO | S87: GREEN TAICANG | T87: SALVADOR | V87: 02.036.823/0001-00 | X87: BRISA INDUSTRIA DE TECIDOS TECNOLOGICOS S.A | Y87: SHENZHEN EVERSEAS INTERNATIONAL LOGISTICS CO | Z87: CCTBS-0459 | AA87: Prepaid | AB87: IM1673-25 | AE87: Pago | AF87: Recebido | AG87: Quitado | AH87: Não aplicável | AL87: 0 | AN87: FCL | AO87: 1 | AP87: 0 | AQ87: HC BOX | AS87: 46045 | AT87: 46048 | AU87: =MONTH(AT87) -> 1 | AZ87: BEAU6453779 | BA87: Enila Kawely | BD87: 278.76 | BE87: 3173.98 | BF87: 3878.87 | BG87: 3878.87 | BH87: 4157.63 | BI87: 4157.63 | BK87: 46045.755 | BL87: 21147.16 | BM87: 20610.59 | BN87: 24321.14 | BO87: 24321.14 | BP87: 46014 | BQ87: 46014 | BR87: 1 | BT87: Tracking inativo | BU87: Falso | BX87: Ativo | BY87: Ativo
A88: 1 | B88: Marítimo importação | C88: Back to back | D88: IM1943-25 | E88: NA WEB GROUP DE MARCAS LICENCIADAS LTDA | F88: NA WEB GROUP DE MARCAS LICENCIADAS LTDA | G88: HEBEI ZHONGTAI BICYCLE MANUFACTURING CO.,LTD | H88: 45952.535 | I88: 46014 | J88: FOB | K88: TS5QJ3724500 | L88: 45938.599 | M88: 45938.599 | N88: Desembarcado | O88: ONE | P88: KDSY25100043 | Q88: XINGANG | S88: CHANG SHUN QIAN CHENG | T88: SANTOS | U88: MOL EXPERIENCE | V88: 39.269.114/0003-39 | X88: NA WEB GROUP DE MARCAS LICENCIADAS LTDA | Y88: REACH LOGISTICS CO., LTD | Z88: WEB122025 - PRO25000561 - NAWEB114OUT25 | AA88: Prepaid | AB88: IM1943-25 | AE88: Parcialmente pago | AF88: Em aberto | AG88: Quitado | AH88: Não aplicável | AJ88: 67.26 | AK88: 8691 | AL88: 67260 | AN88: FCL | AO88: 0 | AP88: 1 | AQ88: 40 HIGH CUBE | AR88: 67.26 | AS88: 46029 | AT88: 46034 | AU88: =MONTH(AT88) -> 1 | AY88: PF005272/25-01 | AZ88: TCLU4619624 | BA88: Tiago Schneider | BB88: Mariana Reis | BD88: 139.91 | BE88: 1050.81 | BF88: 2869.38 | BG88: 2706.35 | BH88: 3009.29 | BI88: 0 | BK88: 46037.473 | BL88: 15861.23 | BM88: 14472.27 | BN88: 16912.04 | BO88: 0 | BP88: 46014.042 | BQ88: 46014 | BR88: 2 | BT88: Sincronizado | BU88: Falso | BW88: 0 | BX88: Ativo | BY88: Ativo
A89: 1 | B89: Marítimo importação | C89: Back to back | D89: IM1945-25 | E89: NA WEB GROUP DE MARCAS LICENCIADAS LTDA | F89: NA WEB GROUP DE MARCAS LICENCIADAS LTDA | G89: UNIQUE PACK LIMITED | H89: 45952.535 | I89: 46014.546 | J89: FOB | K89: TS5QJ3724501 | L89: 45938.608 | M89: 45938.608 | N89: Desembarcado | O89: ONE | P89: KDSY25100052 | Q89: XINGANG | S89: CHANG SHUN QIAN CHENG | T89: SANTOS | U89: MOL EXPERIENCE | V89: 39.269.114/0003-39 | X89: NA WEB GROUP DE MARCAS LICENCIADAS LTDA | Y89: REACH LOGISTICS CO., LTD | Z89: WEBUH375 - PRO25000555 - NAWEB109OUT25 | AA89: Prepaid | AB89: IM1945-25 | AE89: Pago | AF89: Em aberto | AG89: Quitado | AH89: Não aplicável | AJ89: 67.95 | AK89: 9370 | AL89: 67950 | AN89: FCL | AO89: 0 | AP89: 1 | AQ89: 40 HIGH CUBE | AR89: 67.95 | AS89: 46058 | AT89: 46059 | AU89: =MONTH(AT89) -> 2 | AY89: PF005274/25-01 | AZ89: ONEU5481538 | BA89: Tiago Schneider | BB89: Mariana Reis | BD89: 141.14 | BE89: 1043.07 | BF89: 2868.15 | BG89: 2868.15 | BH89: 3009.29 | BI89: 0 | BK89: 46037.476 | BL89: 15868.97 | BM89: 15396.23 | BN89: 16912.04 | BO89: 0 | BP89: 46013 | BQ89: 46014.546 | BR89: 2 | BT89: Sincronizado | BU89: Falso | BW89: 0 | BX89: Ativo | BY89: Ativo
A90: 1 | B90: Marítimo importação | C90: Back to back | D90: IM1882-25 | E90: INTELCAV TECNOLOGIAS E CARTÕES S.A. | F90: INTELCAV TECNOLOGIAS E CARTÕES S.A. | G90: JIANG YIN ZHONGKA CARD-BASE NEWMATERIALCO., LTD. | H90: 45948.322 | I90: 46015 | J90: FOB | K90: MAEU264829783 | L90: 45929.667 | M90: 45929.667 | N90: Desembarcado | O90: MAERSK | P90: KDSY25090213 | Q90: SHANGHAI | S90: MAERSK SAN JUAN | T90: ITAJAI | U90: BARTOLOMEU DIAS | V90: 03.935.003/0007-09 | X90: INTELCAV TECNOLOGIAS E CARTÕES S.A. | Y90: REACH LOGISTICS CO., LTD | Z90: PO 16 // ILOG 4616/25 | AA90: Collect | AB90: 4616/25 | AE90: Pago | AF90: Recebido | AG90: Quitado | AH90: Não aplicável | AJ90: 40 | AK90: 22280 | AL90: 40000 | AN90: FCL | AO90: 0 | AP90: 1 | AQ90: 40 NOR | AR90: 40 | AS90: 46030 | AT90: 46031 | AU90: =MONTH(AT90) -> 1 | AY90: PF005018/25-04 | AZ90: MNBU3926149 | BA90: Matheus Bourscheid | BB90: Mariana Reis | BD90: 109.54 | BE90: 1339.62 | BF90: 1880.27 | BG90: 1880.27 | BH90: 1989.81 | BI90: 1989.81 | BK90: 46030.678 | BL90: 10224.64 | BM90: 9957.95 | BN90: 11564.26 | BO90: 11564.26 | BP90: 46015 | BQ90: 46015 | BR90: 2 | BT90: Divergência viagens | BU90: Falso | BV90: 39114 | BW90: 0 | BX90: Ativo | BY90: Ativo
A91: 1 | B91: Demurrage | C91: Back to back | D91: DEMU0054-26 | E91: INTELCAV TECNOLOGIAS E CARTÕES S.A. | F91: INTELCAV TECNOLOGIAS E CARTÕES S.A. | G91: JIANG YIN ZHONGKA CARD-BASE NEWMATERIALCO., LTD. | H91: 45948.322 | I91: 46015 | J91: FOB | K91: MAEU264829783 | L91: 46057.493 | M91: 46057.493 | N91: Desembarcado | O91: MAERSK | P91: KDSY25090213 | Q91: SHANGHAI | S91: MAERSK SAN JUAN | T91: ITAJAI | U91: BARTOLOMEU DIAS | V91: 03.935.003/0007-09 | X91: INTELCAV TECNOLOGIAS E CARTÕES S.A. | Y91: REACH LOGISTICS CO., LTD | Z91: PO 16 // ILOG 4616/25 - IM1882-26 | AA91: Collect | AB91: DEMU0054-26 | AE91: Sem pagamento | AF91: Sem recebimento | AG91: Sem acerto com agente | AH91: Não aplicável | AJ91: 40 | AK91: 22280 | AL91: 40000 | AN91: FCL | AO91: 0 | AP91: 1 | AQ91: 40 NOR | AR91: 40 | AT91: 46092 | AU91: =MONTH(AT91) -> 3 | AY91: PF005018/25-04 | AZ91: MNBU3926149 | BA91: Matheus Bourscheid | BD91: 2064.5 | BE91: 11328.97 | BF91: 970 | BG91: 970 | BH91: 3034.5 | BI91: 3034.5 | BK91: 46084.625 | BL91: 5516.6 | BM91: 5516.6 | BN91: 16845.57 | BO91: 16845.57 | BP91: 46015 | BR91: 2 | BT91: Tracking inativo | BU91: Falso | BV91: 39114 | BW91: 0 | BX91: Ativo | BY91: Ativo
A92: 1 | B92: Marítimo importação | C92: Back to back | D92: IM1959-25 | E92: RESFRI AR CLIMATIZADORES E EQUIPAMENTOS LTDA | F92: RESFRI AR CLIMATIZADORES E EQUIPAMENTOS LTDA | G92: NINGBO CIXI IMP. & EXP. HOLDINGS CO. LTD | H92: 45978.422 | I92: 46015.745 | J92: FOB | K92: 259933275 | L92: 45939.427 | M92: 45939.427 | N92: Desembarcado | O92: MAERSK | P92: KDSY25100092 | Q92: YANTIAN | S92: MAERSK LABERINTO | T92: ITAJAI | U92: BARTOLOMEU DIAS | V92: 01.986.608/0001-08 | X92: RESFRI AR CLIMATIZADORES E EQUIPAMENTOS LTDA | Y92: REACH LOGISTICS CO., LTD | Z92: P052-25 - ILOG 4897/25 | AA92: Prepaid | AB92: 4897/25 | AE92: Pago | AF92: Recebido | AG92: Quitado | AH92: Não aplicável | AJ92: 65 | AK92: 6800 | AL92: 65000 | AN92: FCL | AO92: 0 | AP92: 1 | AQ92: 40 HIGH CUBE | AR92: 65 | AS92: 46022 | AT92: 46029 | AU92: =MONTH(AT92) -> 1 | AV92: LEADER LOGISTICS LTDA FILIAL ITJ | AY92: PF005245/25-01 | AZ92: CAAU7241591 | BA92: Matheus Ropelato | BD92: 305.47 | BE92: 2726.46 | BF92: 2741.02 | BG92: 2741.02 | BH92: 3046.49 | BI92: 3046.49 | BK92: 46034.648 | BL92: 14978.98 | BM92: 14459.94 | BN92: 17705.44 | BO92: 17705.44 | BP92: 46015.167 | BQ92: 46015.745 | BR92: 2 | BT92: Sincronizado | BU92: Falso | BV92: 85800 | BW92: 0 | BX92: Ativo | BY92: Ativo
A93: 1 | B93: Aéreo importação | C93: Back to back | D93: IA0691-25 | E93: INTELCAV TECNOLOGIAS E CARTÕES S.A. | F93: INTELCAV TECNOLOGIAS E CARTÕES S.A. | G93: Hong Kong Synraid Development Co.,Limited | H93: 46015 | I93: 46016 | J93: EXW | K93: 071-59276696 | L93: 46008.618 | M93: 46008.618 | N93: Desembarcado | O93: ETHIOPIAN AIRLINES | P93: HYKC25120192 | Q93: XIAMEN | T93: GUARULHOS | V93: 03.935.003/0007-09 | X93: WINNING TRADING S.A. (SC) | Y93: Shanghai Weiming Cargo Transportation co., Ltd. | Z93: PO.13 - ILOG 6452/25 | AA93: Prepaid | AB93: 6452/25 | AE93: Pago | AF93: Recebido | AG93: Quitado | AH93: Desconsolidado | AJ93: 0.51 | AK93: 78 | AL93: 85 | AM93: 86 | AN93: Aéreo | AR93: 85 | AS93: 46022 | AT93: 46028 | AU93: =MONTH(AT93) -> 1 | AV93: LEADER LOGISTICS LTDA FILIAL ITJ | AY93: PF006777/25-01 | BA93: Matheus Bourscheid | BB93: Mariana Reis | BD93: 176.8 | BE93: 1306.21 | BF93: 1368.24 | BG93: 1368.24 | BH93: 1545.04 | BI93: 1545.04 | BK93: 46022.372 | BL93: 7683.37 | BM93: 7298.12 | BN93: 8989.58 | BO93: 8989.58 | BP93: 46020 | BQ93: 46020.375 | BS93: Back to back | BT93: Tracking inativo | BU93: Falso | BW93: 0 | BX93: Ativo | BY93: Ativo
A94: 1 | B94: Marítimo importação | C94: Back to back | D94: IM1737-25 | E94: CALCADOS RAMARIM LTDA | F94: CALCADOS RAMARIM LTDA | G94: SPEEDY SOURCE ENTERPRISE LIMITED | H94: 45982.667 | I94: 46016.625 | J94: FOB | K94: B232106811 | L94: 45916.337 | M94: 45916.337 | N94: Desembarcado | O94: YANG MING | P94: OLGM256949 | Q94: NINGBO | S94: COSCO SHIPPING ARGENTINA | T94: SANTOS | V94: 88.104.328/0015-02 | X94: CALCADOS RAMARIM LTDA | Y94: OWNERS LOGISTICS CO. LTD. | Z94: PI 20250913 | AA94: Prepaid | AB94: IM1737-25 | AE94: Pago | AF94: Recebido | AG94: Quitado | AH94: Não aplicável | AL94: 0 | AN94: FCL | AO94: 0 | AP94: 1 | AQ94: 40 HIGH CUBE | AR94: 0 | AS94: 46099 | AT94: 46100 | AU94: =MONTH(AT94) -> 3 | AV94: OCEAN EXPRESS SERVICOS EM COMERCIO EXTERIOR LTDA | AY94: PF004742/25-01 | AZ94: YMMU6483670 | BA94: Bruna Kelsch | BD94: 480.82 | BE94: 2449.32 | BF94: 2103.3 | BG94: 2103.3 | BH94: 2584.12 | BI94: 2584.12 | BK94: 46100.391 | BL94: 12299.62 | BM94: 12287.79 | BN94: 14748.94 | BO94: 14748.94 | BP94: 46016.625 | BQ94: 46016.625 | BR94: 2 | BT94: Sincronizado | BU94: Falso | BW94: 0 | BX94: Ativo | BY94: Ativo
A95: 1 | B95: Marítimo importação | C95: Back to back | D95: IM2049-25 | E95: BN - PAPEL CATARINENSE LTDA | F95: BN - PAPEL CATARINENSE LTDA | G95: Good Fortune New Materials Limited | H95: 45975 | I95: 46017 | J95: FOB | K95: ZSN0786171 | L95: 45950.419 | M95: 45950.419 | N95: Desembarcado | O95: COMPAGNIE GENERALE MARITIME - CMA CGM | P95: YON202508469 | Q95: ZHANJIAN | S95: NAN HANG 727 | T95: NAVEGANTES | U95: EVER FAME | V95: 02.237.016/0001-48 | X95: WINNING TRADING S.A. (SC) | Y95: Y-OCEAN LOGISTICS CO | Z95: 022-2025 - Ilog 4851/25 | AA95: Prepaid | AB95: 4851/25 | AE95: Pago | AF95: Recebido | AG95: Quitado | AH95: Não aplicável | AJ95: 58 | AK95: 25769 | AL95: 58000 | AN95: FCL | AO95: 0 | AP95: 1 | AQ95: 40 HIGH CUBE | AR95: 58 | AS95: 46029 | AT95: 46031 | AU95: =MONTH(AT95) -> 1 | AV95: LEADER LOGISTICS LTDA FILIAL ITJ | AY95: PF005478/25-01 | AZ95: APHU6821756 | BA95: Tiago Schneider | BB95: Mariana Reis | BD95: 888.31 | BE95: 5764.34 | BF95: 2819.36 | BG95: 2819.36 | BH95: 3707.67 | BI95: 3707.67 | BK95: 46035.649 | BL95: 15808.24 | BM95: 15528.14 | BN95: 21572.58 | BO95: 21572.58 | BP95: 46017 | BQ95: 46017 | BR95: 2 | BT95: Tracking inativo | BU95: Falso | BW95: 0 | BX95: Ativo | BY95: Ativo
A96: 1 | B96: Marítimo importação | C96: Back to back | D96: IM1981-25 | E96: R.BRANDS LTDA | F96: R.BRANDS LTDA | G96: CHINA XINXING IMPORT AND EXPORT CO., LTD | H96: 45978.536 | I96: 46017 | J96: FOB | K96: SHITI25227454 | L96: 45940.675 | M96: 45940.675 | N96: Desembarcado | O96: CHARTER LINK | P96: SWS2511040 | Q96: SHANGHAI | S96: EVER FAME | T96: NAVEGANTES | V96: 13.992.333/0001-96 | X96: R.BRANDS LTDA | Y96: (LCL) SHENZHEN SMOOTHWIN INTERNATIONAL | Z96: CXI-12293 Licitação + Privado - ILOG 4907/25 | AA96: Collect | AB96: 4907/25 | AE96: Pago | AF96: Recebido | AG96: Quitado | AH96: Não aplicável | AJ96: 2.851 | AK96: 400 | AL96: 2851 | AN96: LCL | AO96: 0 | AP96: 0 | AR96: 2.851 | AS96: 46029 | AT96: 46030 | AU96: =MONTH(AT96) -> 1 | AV96: LEADER LOGISTICS LTDA FILIAL ITJ | AY96: PF005315/25-01 | AZ96: TCNU2990551 | BA96: Tiago Schneider | BB96: Mariana Reis | BD96: 66.98 | BE96: 388.91 | BF96: 32.16 | BG96: 32.16 | BH96: 99.14 | BI96: 99.14 | BK96: 46029.673 | BL96: 176.92 | BM96: 173.46 | BN96: 565.83 | BO96: 565.83 | BP96: 46017.792 | BQ96: 46017 | BR96: 0 | BT96: Sincronizado | BU96: Falso | BV96: 21872 | BW96: 0 | BX96: Ativo | BY96: Ativo
A97: 1 | B97: Marítimo importação | C97: Back to back | D97: IM2082-25 | E97: INTELCAV TECNOLOGIAS E CARTÕES S.A. | F97: INTELCAV TECNOLOGIAS E CARTÕES S.A. | G97: JIANG YIN ZHONGKA CARD-BASE NEWMATERIALCO., LTD. | H97: 45978.501 | I97: 46017 | J97: FOB | L97: 45951.695 | M97: 45951.695 | N97: Desembarcado | O97: WORLD FREIGHT 03-03 | P97: SHAYTYPA0030 | Q97: SHANGHAI | S97: EVER FAME | T97: NAVEGANTES | V97: 03.935.003/0007-09 | X97: WINNING TRADING S.A. (SC) | Y97: WORLD FREIGHT AG. E TRANSP. LTDA | Z97: PO 31 2st - SEA - ILOG 5105/25 | AA97: Collect | AB97: 5105/25 | AE97: Pago | AF97: Recebido | AG97: Sem acerto com agente | AH97: Não aplicável | AJ97: 0.48 | AK97: 260 | AL97: 480 | AN97: LCL | AO97: 0 | AP97: 0 | AR97: 1 | AS97: 46031 | AT97: 46034 | AU97: =MONTH(AT97) -> 1 | AV97: LEADER LOGISTICS LTDA FILIAL ITJ | AY97: PF005595/25-01 | AZ97: SZLU9437252 | BA97: Annie Audrien | BB97: Mariana Reis | BD97: 53.16 | BE97: 299.96 | BF97: 7.83 | BG97: 7.83 | BH97: 60.99 | BI97: 60.99 | BK97: 46031.789 | BL97: 45.86 | BM97: 45.86 | BN97: 345.82 | BO97: 345.82 | BP97: 46017.417 | BQ97: 46017 | BR97: 0 | BT97: Sincronizado | BU97: Falso | BV97: 1280 | BW97: 0 | BX97: Ativo | BY97: Ativo
A98: 1 | B98: Marítimo importação | C98: Back to back | D98: IM2021-25 | E98: R.BRANDS LTDA | F98: R.BRANDS LTDA | G98: FASHION-FLYING PTE. LTD. | H98: 45970 | I98: 46017 | J98: FOB | K98: FCLNAV25003569 | L98: 45945.725 | M98: 45945.725 | N98: Desembarcado | O98: CHARTER LINK | P98: SWS2510074 | Q98: FUZHOU | S98: HUI JIN QIAO 11 | T98: NAVEGANTES | U98: EVER FAME | V98: 13.992.333/0001-96 | X98: R.BRANDS LTDA | Y98: (LCL) SHENZHEN SMOOTHWIN INTERNATIONAL | Z98: FFO-12330 + FFO-12240 licitação - ILOG 5002/25 | AA98: Collect | AB98: 5002/25 | AE98: Pago | AF98: Recebido | AG98: Quitado | AH98: Não aplicável | AJ98: 0.305 | AK98: 74.96 | AL98: 305 | AN98: LCL | AO98: 0 | AP98: 0 | AR98: 1 | AS98: 46029 | AT98: 46030 | AU98: =MONTH(AT98) -> 1 | AV98: LEADER LOGISTICS LTDA FILIAL ITJ | AY98: PF005454/25-01 | AZ98: TXGU8095850 | BA98: Tiago Schneider | BB98: Mariana Reis | BD98: 55 | BE98: 319.86 | BF98: 23.67 | BG98: 23.67 | BH98: 78.67 | BI98: 78.67 | BK98: 46029.675 | BL98: 129.15 | BM98: 125.69 | BN98: 449.01 | BO98: 449.01 | BP98: 46017 | BQ98: 46017 | BR98: 0 | BT98: Tracking inativo | BU98: Falso | BV98: 5678.4 | BW98: 0 | BX98: Ativo | BY98: Ativo
A99: 1 | B99: Marítimo importação | C99: Back to back | D99: IM2222-25 | E99: INTELCAV TECNOLOGIAS E CARTÕES S.A. | F99: INTELCAV TECNOLOGIAS E CARTÕES S.A. | G99: JIANG YIN ZHONGKA CARD-BASE NEWMATERIALCO., LTD. | H99: 45978 | I99: 46017.343 | J99: FOB | K99: EURFL25N02135ITJ | L99: 45965.717 | M99: 45965.717 | N99: Desembarcado | O99: MSL | P99: EURFL25N02135ITJ | Q99: SHANGHAI | S99: EVER FAME | T99: NAVEGANTES | V99: 03.935.003/0007-09 | X99: WINNING TRADING S.A. (SC) | Y99: MSL CORPORATE | Z99: PO 33 and PO 35 - ILOG: 5479/25 | AA99: Collect | AB99: 5479/25 | AE99: Pago | AF99: Recebido | AG99: Sem acerto com agente | AH99: Não aplicável | AJ99: 5.291 | AK99: 2370 | AL99: 5291 | AN99: LCL | AO99: 0 | AP99: 0 | AR99: 5.291 | AS99: 46030 | AT99: 46031 | AU99: =MONTH(AT99) -> 1 | AV99: LEADER LOGISTICS LTDA FILIAL ITJ | AY99: PF005905/25-01 | AZ99: TCKU6817787 | BA99: Matheus Bourscheid | BB99: Mariana Reis | BD99: 66.72 | BE99: 364.49 | BF99: 37.27 | BG99: 37.27 | BH99: 103.99 | BI99: 103.99 | BK99: 46030.675 | BL99: 219.14 | BM99: 219.14 | BN99: 583.63 | BO99: 583.63 | BP99: 46017.417 | BQ99: 46017.343 | BR99: 0 | BT99: Sincronizado | BU99: Falso | BV99: 11359 | BW99: 0 | BX99: Ativo | BY99: Ativo
A100: 1 | B100: Marítimo importação | C100: Back to back | D100: IM2063-25 | E100: NA WEB GROUP DE MARCAS LICENCIADAS LTDA | F100: NA WEB GROUP DE MARCAS LICENCIADAS LTDA | G100: UNIQUE PACK LIMITED | H100: 45970.01 | I100: 46018.251 | J100: FOB | K100: 261003921 | L100: 45950.76 | M100: 45950.76 | N100: Desembarcado | O100: MAERSK | P100: KDSY25100147 | Q100: XINGANG | S100: GOOD PROSPECT | T100: SANTOS | U100: CMA CGM ADVENTURE | V100: 39.269.114/0003-39 | X100: NA WEB GROUP DE MARCAS LICENCIADAS LTDA | Y100: REACH LOGISTICS CO., LTD | Z100: WEBUH413 - PRO25000581 - NAWEB127OUT25 | AA100: Prepaid | AB100: IM2063-25 | AE100: Parcialmente pago | AF100: Em aberto | AG100: Quitado | AH100: Não aplicável | AJ100: 70.19 | AK100: 11050 | AL100: 70190 | AN100: FCL | AO100: 0 | AP100: 1 | AQ100: 40 HIGH CUBE | AR100: 70.19 | AS100: 46029 | AT100: 46029 | AU100: =MONTH(AT100) -> 1 | AY100: PF005578/25-01 | AZ100: MRKU3246964 | BA100: Tiago Schneider | BB100: Mariana Reis | BD100: 96.01 | BE100: 976.61 | BF100: 2926.57 | BG100: 2760.44 | BH100: 3022.58 | BI100: 0 | BK100: 46043.576 | BL100: 15939.92 | BM100: 14628.3 | BN100: 16916.53 | BO100: 0 | BP100: 46018.292 | BQ100: 46018.251 | BR100: 2 | BT100: Sincronizado | BU100: Falso | BW100: 0 | BX100: Ativo | BY100: Ativo
...

Sheet Resumo 2025
A3: Processos em andamento | B3: Data: 02/02/2026
A4: Analista | B4: Senioridade/cargo | C4: Ag booking | D4: Ag embarque | E4: Embarcado | F4: Ag faturamento | G4: Total | H4: Meta
A5: Matheus Bourscheid | B5: Junior | C5: 9 | D5: 28 | E5: 37 | F5: 10 | G5: =SUM(C5:F5) -> 84 | H5: 70- 80
A6: Tiago S | B6: Senior | C6: 13 | D6: 62 | E6: 68 | F6: 28 | G6: =SUM(C6:F6) -> 171 | H6: 110-140
A7: Enila Kawely | B7: Senior | C7: 13 | D7: 27 | E7: 43 | F7: 24 | G7: =SUM(C7:F7) -> 107 | H7: 110-140 | M7: 750 | N7: 100
A8: Bruna Kelsch | B8: Senior | C8: 14 | D8: 27 | E8: 73 | F8: 68 | G8: =SUM(C8:F8) -> 182 | H8: 110-140 | M8: 734 | N8: =M8*N7/M7 -> 97.866667
A9: Annie Audrien | B9: Senior | C9: 1 | D9: 0 | E9: 9 | F9: 9 | G9: =SUM(C9:F9) -> 19 | H9: 110-140 | I9: só Ropelato conduzindo
A10: Matheus R | B10: Supervisor | C10: 23 | D10: 40 | E10: 53 | F10: 11 | G10: =SUM(C10:F10) -> 127 | H10: 80-110
G11: =SUM(G5:G10) -> 690
H12: minimo | I12: MÁXIMO
H13: =70+(110*4)+80 -> 590 | I13: =80+(140*4)+110 -> 750
A14: Chegadas confirmadas por mês: | C14: 1 | D14: 2 | E14: 3 | F14: 4 | G14: 5 | H14: 6 | I14: 7 | J14: 8 | K14: 9 | L14: 10 | M14: 11 | N14: 12
A15: Analista | B15: Assistente | C15: Janeiro | D15: Fevereiro | E15: Março | F15: Abril | G15: Maio | H15: Junho | I15: Julho | J15: Agosto | K15: Setembro | L15: Outubro | M15: Novembro | N15: Dezembro | O15: Total
A16: Matheus Bourscheid | B16: Graziele Meytre | C16: =SUMIFS('Faturados 2025 HS'!$A:$A,'Faturados 2025 HS'!$BB:$BB,'Resumo 2025'!$A16,'Faturados 2025 HS'!$AU:$AU,'Resumo 2025'!C$14) -> 6 | D16: =SUMIFS('Faturados 2025 HS'!$A:$A,'Faturados 2025 HS'!$BB:$BB,'Resumo 2025'!$A16,'Faturados 2025 HS'!$AU:$AU,'Resumo 2025'!D$14) -> 6 | E16: =SUMIFS('Faturados 2025 HS'!$A:$A,'Faturados 2025 HS'!$BB:$BB,'Resumo 2025'!$A16,'Faturados 2025 HS'!$AU:$AU,'Resumo 2025'!E$14) -> 10 | F16: =SUMIFS('Faturados 2025 HS'!$A:$A,'Faturados 2025 HS'!$BB:$BB,'Resumo 2025'!$A16,'Faturados 2025 HS'!$AU:$AU,'Resumo 2025'!F$14) -> 13 | G16: =SUMIFS('Faturados 2025 HS'!$A:$A,'Faturados 2025 HS'!$BB:$BB,'Resumo 2025'!$A16,'Faturados 2025 HS'!$AU:$AU,'Resumo 2025'!G$14) -> 22 | H16: =SUMIFS('Faturados 2025 HS'!$A:$A,'Faturados 2025 HS'!$BB:$BB,'Resumo 2025'!$A16,'Faturados 2025 HS'!$AU:$AU,'Resumo 2025'!H$14) -> 19 | I16: =SUMIFS('Faturados 2025 HS'!$A:$A,'Faturados 2025 HS'!$BB:$BB,'Resumo 2025'!$A16,'Faturados 2025 HS'!$AU:$AU,'Resumo 2025'!I$14) -> 29 | J16: =SUMIFS('Faturados 2025 HS'!$A:$A,'Faturados 2025 HS'!$BB:$BB,'Resumo 2025'!$A16,'Faturados 2025 HS'!$AU:$AU,'Resumo 2025'!J$14) -> 37 | ... N16: =SUMIFS('Faturados 2025 HS'!$A:$A,'Faturados 2025 HS'!$BB:$BB,'Resumo 2025'!$A16,'Faturados 2025 HS'!$AU:$AU,'Resumo 2025'!N$14) -> 32 | O16: =SUM(C16:N16) -> 295
A17: Tiago Schneider | B17: Kailane Claudino | C17: =SUMIFS('Faturados 2025 HS'!$A:$A,'Faturados 2025 HS'!$BB:$BB,'Resumo 2025'!$A17,'Faturados 2025 HS'!$AU:$AU,'Resumo 2025'!C$14) -> 65 | D17: =SUMIFS('Faturados 2025 HS'!$A:$A,'Faturados 2025 HS'!$BB:$BB,'Resumo 2025'!$A17,'Faturados 2025 HS'!$AU:$AU,'Resumo 2025'!D$14) -> 33 | E17: =SUMIFS('Faturados 2025 HS'!$A:$A,'Faturados 2025 HS'!$BB:$BB,'Resumo 2025'!$A17,'Faturados 2025 HS'!$AU:$AU,'Resumo 2025'!E$14) -> 29 | F17: =SUMIFS('Faturados 2025 HS'!$A:$A,'Faturados 2025 HS'!$BB:$BB,'Resumo 2025'!$A17,'Faturados 2025 HS'!$AU:$AU,'Resumo 2025'!F$14) -> 27 | G17: =SUMIFS('Faturados 2025 HS'!$A:$A,'Faturados 2025 HS'!$BB:$BB,'Resumo 2025'!$A17,'Faturados 2025 HS'!$AU:$AU,'Resumo 2025'!G$14) -> 23 | H17: =SUMIFS('Faturados 2025 HS'!$A:$A,'Faturados 2025 HS'!$BB:$BB,'Resumo 2025'!$A17,'Faturados 2025 HS'!$AU:$AU,'Resumo 2025'!H$14) -> 41 | I17: =SUMIFS('Faturados 2025 HS'!$A:$A,'Faturados 2025 HS'!$BB:$BB,'Resumo 2025'!$A17,'Faturados 2025 HS'!$AU:$AU,'Resumo 2025'!I$14) -> 39 | J17: =SUMIFS('Faturados 2025 HS'!$A:$A,'Faturados 2025 HS'!$BB:$BB,'Resumo 2025'!$A17,'Faturados 2025 HS'!$AU:$AU,'Resumo 2025'!J$14) -> 49 | ... N17: =SUMIFS('Faturados 2025 HS'!$A:$A,'Faturados 2025 HS'!$BB:$BB,'Resumo 2025'!$A17,'Faturados 2025 HS'!$AU:$AU,'Resumo 2025'!N$14) -> 53 | O17: =SUM(C17:N17) -> 539
A18: Enila Kawely | B18: Manuela Gonçalves | C18: =SUMIFS('Faturados 2025 HS'!$A:$A,'Faturados 2025 HS'!$BB:$BB,'Resumo 2025'!$A18,'Faturados 2025 HS'!$AU:$AU,'Resumo 2025'!C$14) -> 19 | D18: =SUMIFS('Faturados 2025 HS'!$A:$A,'Faturados 2025 HS'!$BB:$BB,'Resumo 2025'!$A18,'Faturados 2025 HS'!$AU:$AU,'Resumo 2025'!D$14) -> 24 | E18: =SUMIFS('Faturados 2025 HS'!$A:$A,'Faturados 2025 HS'!$BB:$BB,'Resumo 2025'!$A18,'Faturados 2025 HS'!$AU:$AU,'Resumo 2025'!E$14) -> 27 | F18: =SUMIFS('Faturados 2025 HS'!$A:$A,'Faturados 2025 HS'!$BB:$BB,'Resumo 2025'!$A18,'Faturados 2025 HS'!$AU:$AU,'Resumo 2025'!F$14) -> 27 | G18: =SUMIFS('Faturados 2025 HS'!$A:$A,'Faturados 2025 HS'!$BB:$BB,'Resumo 2025'!$A18,'Faturados 2025 HS'!$AU:$AU,'Resumo 2025'!G$14) -> 32 | H18: =SUMIFS('Faturados 2025 HS'!$A:$A,'Faturados 2025 HS'!$BB:$BB,'Resumo 2025'!$A18,'Faturados 2025 HS'!$AU:$AU,'Resumo 2025'!H$14) -> 35 | I18: =SUMIFS('Faturados 2025 HS'!$A:$A,'Faturados 2025 HS'!$BB:$BB,'Resumo 2025'!$A18,'Faturados 2025 HS'!$AU:$AU,'Resumo 2025'!I$14) -> 40 | J18: =SUMIFS('Faturados 2025 HS'!$A:$A,'Faturados 2025 HS'!$BB:$BB,'Resumo 2025'!$A18,'Faturados 2025 HS'!$AU:$AU,'Resumo 2025'!J$14) -> 29 | ... N18: =SUMIFS('Faturados 2025 HS'!$A:$A,'Faturados 2025 HS'!$BB:$BB,'Resumo 2025'!$A18,'Faturados 2025 HS'!$AU:$AU,'Resumo 2025'!N$14) -> 39 | O18: =SUM(C18:N18) -> 390
A19: Gabriel Hilgert | B19: N/A | C19: =SUMIFS('Faturados 2025 HS'!$A:$A,'Faturados 2025 HS'!$BB:$BB,'Resumo 2025'!$A19,'Faturados 2025 HS'!$AU:$AU,'Resumo 2025'!C$14) -> 2 | D19: =SUMIFS('Faturados 2025 HS'!$A:$A,'Faturados 2025 HS'!$BB:$BB,'Resumo 2025'!$A19,'Faturados 2025 HS'!$AU:$AU,'Resumo 2025'!D$14) -> 16 | E19: =SUMIFS('Faturados 2025 HS'!$A:$A,'Faturados 2025 HS'!$BB:$BB,'Resumo 2025'!$A19,'Faturados 2025 HS'!$AU:$AU,'Resumo 2025'!E$14) -> 7 | F19: =SUMIFS('Faturados 2025 HS'!$A:$A,'Faturados 2025 HS'!$BB:$BB,'Resumo 2025'!$A19,'Faturados 2025 HS'!$AU:$AU,'Resumo 2025'!F$14) -> 2 | G19: =SUMIFS('Faturados 2025 HS'!$A:$A,'Faturados 2025 HS'!$BB:$BB,'Resumo 2025'!$A19,'Faturados 2025 HS'!$AU:$AU,'Resumo 2025'!G$14) -> 3 | H19: =SUMIFS('Faturados 2025 HS'!$A:$A,'Faturados 2025 HS'!$BB:$BB,'Resumo 2025'!$A19,'Faturados 2025 HS'!$AU:$AU,'Resumo 2025'!H$14) -> 4 | I19: =SUMIFS('Faturados 2025 HS'!$A:$A,'Faturados 2025 HS'!$BB:$BB,'Resumo 2025'!$A19,'Faturados 2025 HS'!$AU:$AU,'Resumo 2025'!I$14) -> 0 | J19: =SUMIFS('Faturados 2025 HS'!$A:$A,'Faturados 2025 HS'!$BB:$BB,'Resumo 2025'!$A19,'Faturados 2025 HS'!$AU:$AU,'Resumo 2025'!J$14) -> 3 | ... N19: =SUMIFS('Faturados 2025 HS'!$A:$A,'Faturados 2025 HS'!$BB:$BB,'Resumo 2025'!$A19,'Faturados 2025 HS'!$AU:$AU,'Resumo 2025'!N$14) -> 0 | O19: =SUM(C19:N19) -> 37 | P19: rebates | Q19: =O19 -> 37
A20: Matheus Ropelato | B20: Graziele Meytre | C20: =SUMIFS('Faturados 2025 HS'!$A:$A,'Faturados 2025 HS'!$BB:$BB,'Resumo 2025'!$A20,'Faturados 2025 HS'!$AU:$AU,'Resumo 2025'!C$14) -> 66 | D20: =SUMIFS('Faturados 2025 HS'!$A:$A,'Faturados 2025 HS'!$BB:$BB,'Resumo 2025'!$A20,'Faturados 2025 HS'!$AU:$AU,'Resumo 2025'!D$14) -> 13 | E20: =SUMIFS('Faturados 2025 HS'!$A:$A,'Faturados 2025 HS'!$BB:$BB,'Resumo 2025'!$A20,'Faturados 2025 HS'!$AU:$AU,'Resumo 2025'!E$14) -> 21 | F20: =SUMIFS('Faturados 2025 HS'!$A:$A,'Faturados 2025 HS'!$BB:$BB,'Resumo 2025'!$A20,'Faturados 2025 HS'!$AU:$AU,'Resumo 2025'!F$14) -> 18 | G20: =SUMIFS('Faturados 2025 HS'!$A:$A,'Faturados 2025 HS'!$BB:$BB,'Resumo 2025'!$A20,'Faturados 2025 HS'!$AU:$AU,'Resumo 2025'!G$14) -> 38 | H20: =SUMIFS('Faturados 2025 HS'!$A:$A,'Faturados 2025 HS'!$BB:$BB,'Resumo 2025'!$A20,'Faturados 2025 HS'!$AU:$AU,'Resumo 2025'!H$14) -> 21 | I20: =SUMIFS('Faturados 2025 HS'!$A:$A,'Faturados 2025 HS'!$BB:$BB,'Resumo 2025'!$A20,'Faturados 2025 HS'!$AU:$AU,'Resumo 2025'!I$14) -> 27 | J20: =SUMIFS('Faturados 2025 HS'!$A:$A,'Faturados 2025 HS'!$BB:$BB,'Resumo 2025'!$A20,'Faturados 2025 HS'!$AU:$AU,'Resumo 2025'!J$14) -> 36 | ... N20: =SUMIFS('Faturados 2025 HS'!$A:$A,'Faturados 2025 HS'!$BB:$BB,'Resumo 2025'!$A20,'Faturados 2025 HS'!$AU:$AU,'Resumo 2025'!N$14) -> 122 | O20: =SUM(C20:N20) -> 533
A21: Annie Audrien | B21: Ágata Machado | C21: =SUMIFS('Faturados 2025 HS'!$A:$A,'Faturados 2025 HS'!$BB:$BB,'Resumo 2025'!$A21,'Faturados 2025 HS'!$AU:$AU,'Resumo 2025'!C$14) -> 51 | D21: =SUMIFS('Faturados 2025 HS'!$A:$A,'Faturados 2025 HS'!$BB:$BB,'Resumo 2025'!$A21,'Faturados 2025 HS'!$AU:$AU,'Resumo 2025'!D$14) -> 45 | E21: =SUMIFS('Faturados 2025 HS'!$A:$A,'Faturados 2025 HS'!$BB:$BB,'Resumo 2025'!$A21,'Faturados 2025 HS'!$AU:$AU,'Resumo 2025'!E$14) -> 36 | F21: =SUMIFS('Faturados 2025 HS'!$A:$A,'Faturados 2025 HS'!$BB:$BB,'Resumo 2025'!$A21,'Faturados 2025 HS'!$AU:$AU,'Resumo 2025'!F$14) -> 28 | G21: =SUMIFS('Faturados 2025 HS'!$A:$A,'Faturados 2025 HS'!$BB:$BB,'Resumo 2025'!$A21,'Faturados 2025 HS'!$AU:$AU,'Resumo 2025'!G$14) -> 23 | H21: =SUMIFS('Faturados 2025 HS'!$A:$A,'Faturados 2025 HS'!$BB:$BB,'Resumo 2025'!$A21,'Faturados 2025 HS'!$AU:$AU,'Resumo 2025'!H$14) -> 39 | I21: =SUMIFS('Faturados 2025 HS'!$A:$A,'Faturados 2025 HS'!$BB:$BB,'Resumo 2025'!$A21,'Faturados 2025 HS'!$AU:$AU,'Resumo 2025'!I$14) -> 32 | J21: =SUMIFS('Faturados 2025 HS'!$A:$A,'Faturados 2025 HS'!$BB:$BB,'Resumo 2025'!$A21,'Faturados 2025 HS'!$AU:$AU,'Resumo 2025'!J$14) -> 28 | ... N21: =SUMIFS('Faturados 2025 HS'!$A:$A,'Faturados 2025 HS'!$BB:$BB,'Resumo 2025'!$A21,'Faturados 2025 HS'!$AU:$AU,'Resumo 2025'!N$14) -> 0 | O21: =SUM(C21:N21) -> 366
A22: Bruna Kelsch | B22: Mackelly R | C22: =SUMIFS('Faturados 2025 HS'!$A:$A,'Faturados 2025 HS'!$BB:$BB,'Resumo 2025'!$A22,'Faturados 2025 HS'!$AU:$AU,'Resumo 2025'!C$14) -> 57 | D22: =SUMIFS('Faturados 2025 HS'!$A:$A,'Faturados 2025 HS'!$BB:$BB,'Resumo 2025'!$A22,'Faturados 2025 HS'!$AU:$AU,'Resumo 2025'!D$14) -> 40 | E22: =SUMIFS('Faturados 2025 HS'!$A:$A,'Faturados 2025 HS'!$BB:$BB,'Resumo 2025'!$A22,'Faturados 2025 HS'!$AU:$AU,'Resumo 2025'!E$14) -> 21 | F22: =SUMIFS('Faturados 2025 HS'!$A:$A,'Faturados 2025 HS'!$BB:$BB,'Resumo 2025'!$A22,'Faturados 2025 HS'!$AU:$AU,'Resumo 2025'!F$14) -> 27 | G22: =SUMIFS('Faturados 2025 HS'!$A:$A,'Faturados 2025 HS'!$BB:$BB,'Resumo 2025'!$A22,'Faturados 2025 HS'!$AU:$AU,'Resumo 2025'!G$14) -> 24 | H22: =SUMIFS('Faturados 2025 HS'!$A:$A,'Faturados 2025 HS'!$BB:$BB,'Resumo 2025'!$A22,'Faturados 2025 HS'!$AU:$AU,'Resumo 2025'!H$14) -> 26 | I22: =SUMIFS('Faturados 2025 HS'!$A:$A,'Faturados 2025 HS'!$BB:$BB,'Resumo 2025'!$A22,'Faturados 2025 HS'!$AU:$AU,'Resumo 2025'!I$14) -> 48 | J22: =SUMIFS('Faturados 2025 HS'!$A:$A,'Faturados 2025 HS'!$BB:$BB,'Resumo 2025'!$A22,'Faturados 2025 HS'!$AU:$AU,'Resumo 2025'!J$14) -> 30 | ... N22: =SUMIFS('Faturados 2025 HS'!$A:$A,'Faturados 2025 HS'!$BB:$BB,'Resumo 2025'!$A22,'Faturados 2025 HS'!$AU:$AU,'Resumo 2025'!N$14) -> 56 | O22: =SUM(C22:N22) -> 432
A23: Total Mês | C23: =SUM(C16:C22)-C24 -> 264 | D23: =SUM(D16:D22)-D24 -> 161 | E23: =SUM(E16:E22)-E24 -> 144 | F23: =SUM(F16:F22)-F24 -> 140 | G23: =SUM(G16:G22)-G24 -> 162 | H23: =SUM(H16:H22)-H24 -> 181 | I23: =SUM(I16:I22)-I24 -> 215 | J23: =SUM(J16:J22)-J24 -> 209 | ... L23: =SUM(L16:L22)-L24 -> 241 | M23: =SUM(N16:N22)-M24 -> 302 | N23: =SUM(O16:O22)-Q19 -> 2555
C24: =C19 -> 2 | D24: =D19 -> 16 | E24: =E19 -> 7 | F24: =F19 -> 2 | G24: =G19 -> 3 | H24: =H19 -> 4 | I24: =I19 -> 0 | J24: =J19 -> 3
A25: Analista Senior: 110 - 140 (Bruna Kelsch, Enila Kawely, Tiago Schneider, Annie Audrien)
A26: Analista Pleno : 80-110 (não temos ninguém no momento)
A27: Analista Junior: 70-80 (Matheus Bourscheid)
A28: Supervisor: 80-110 (Matheus Ropelato)

Sheet Faturados 2025 HS
D1: Cliente | E1: Notify | F1: Exportador | G1: ETD/ATD | H1: Nº processo house | I1: ETA/ATA | J1: Incoterm | K1: Nº conhecimento master | L1: Data processo | M1: Data abertura processo | N1: Situação embarque | O1: Companhia de transporte | P1: Conhecimentos | Q1: Origem | R1: Previsão início | S1: Navio | T1: Destino | U1: Navio transbordo | V1: Cliente - CNPJ | W1: Cliente Classificação | X1: Importador | Y1: Agente origem | Z1: Ref. cliente | AA1: Modalidade pgto. master | AB1: Ref. externa | AC1: Ref. interna | AD1: Tipo frete | AE1: Situação pagamento | AF1: Situação recebimento | AG1: Situação acerto agente | AH1: Situação CCT | AI1: Tipo do processo | AJ1: Metros cúbicos | AK1: Peso bruto | AL1: Peso cubado | AM1: Peso taxado | AN1: Tipo carga | AO1: Total container 20' | AP1: Total container 40' | AQ1: Equipamentos | AR1: Peso considerado | AS1: Data liberado faturamento | AT1: Data faturado | AU1: Mês | AV1: Desembaraço aduaneiro | AW1: Despachante | AX1: Data término | AY1: Números de embarque | AZ1: Número oferta | BA1: Containers | BB1: OPERACIONAL | BC1: FINANCEIRO OPERACIONAL | BD1: Número courrier | BE1: Lucro bruto momento processo | BF1: Lucro estimado corrente | BG1: Total pagamento processo | BH1: Total pago processo | BI1: Total recebimento processo | BJ1: Total recebido processo | BK1: Nível serviço | BL1: Data último acompanhamento | BM1: Tota pagamento corrente | BN1: Total pago corrente | BO1: Total recebimento corrente | BP1: Total recebido corrente | BQ1: Previsão último desembarque | BR1: Data último desembarque | BS1: Total TEUS | BT1: Tipo serviço aéreo | BU1: Situação tracking viagens | BV1: Seguro | BW1: Importância segurada | BX1: % seguro | BY1: Ativo
A2: 1 | B2: Aéreo importação | C2: Back to back | D2: THERMTRONIC GLOBAL LTDA | E2: THERMTRONIC GLOBAL LTDA | F2: Shenzhen Vertex Electronic Technology | G2: 45658.243 | H2: IA0552-24 | I2: 45294 | J2: EXW | K2: 020-32483566 | L2: 45643.632 | M2: 45643.632 | N2: Desembarcado | O2: LUFTHANSA CARGO | P2: BSZA2412046 | Q2: CHENGDU | T2: GUARULHOS | V2: 22.246.146/0001-54 | X2: WINNING TRADING S.A. (SC) | Y2: BVL - BON VOYAGE LOGISTICS INC. | Z2: ILOG 13882/24 - VTH241211BR | AA2: Prepaid | AB2: 13882/24 | AE2: Pago | AF2: Recebido | AG2: Quitado | AH2: Desconsolidado | AJ2: 0.1 | AK2: 20 | AL2: 16.667 | AM2: 20 | AN2: Aéreo | AR2: 20 | AS2: 45671 | AT2: 45671 | AU2: =MONTH(AT2) -> 1 | AV2: Falso | AW2: LEADER LOGISTICS LTDA FILIAL ITJ | AZ2: PF004866/24-02 | BB2: Annie Audrien | BE2: 240.94 | BF2: 1591.26 | BG2: 840.47 | BH2: 840.47 | BI2: 1081.41 | BJ2: 1081.41 | BL2: 45679.36 | BM2: 5399.09 | BN2: 5039 | BO2: 6990.35 | BP2: 6990.35 | BU2: Pendente atualização dados | BV2: Falso | BX2: 0 | BY2: Ativo
A3: 1 | B3: Marítimo importação | C3: Back to back | D3: FUSOPAR PARAFUSOS LTDA. | E3: FUSOPAR PARAFUSOS LTDA. | F3: SHANDONG TENGLONG IMPORT AND EXPORT CO., LTD. | G3: 45590.575 | H3: IM1820-24 | I3: 45308 | J3: FOB | K3: ONEYTA3DL4577600 | L3: 45580.663 | M3: 45580.663 | N3: Desembarcado | O3: ONE | P3: KDSY24100131 | Q3: QINGDAO | S3: ONE MANCHESTER | T3: RIO GRANDE | U3: MSC SHUBA B | V3: 89.135.073/0001-02 | X3: FUSOPAR PARAFUSOS LTDA. | Y3: STAR-TRANS LOGISTICS CO. LTD | Z3: FUSOPAR241014 | AA3: Collect | AB3: IM1820-24 | AE3: Pago | AF3: Recebido | AG3: Quitado | AH3: Não aplicável | AJ3: 30 | AK3: 26900 | AL3: 30000 | AN3: FCL | AO3: 0 | AP3: 1 | AQ3: 40 NOR | AR3: 30 | AS3: 45685 | AT3: 45686 | AU3: =MONTH(AT3) -> 1 | AV3: Falso | AZ3: PF003994/24-02 | BA3: TTNU8537843 | BB3: Annie Audrien | BE3: 121.89 | BF3: 1886.79 | BG3: 4566.46 | BH3: 4566.46 | BI3: 4688.35 | BJ3: 4688.35 | BL3: 45685.715 | BM3: 27016.35 | BN3: 27016.35 | BO3: 28903.14 | BP3: 28903.14 | BQ3: 45674.75 | BR3: 45308 | BS3: 2 | BU3: Sincronizado | BV3: Falso | BX3: 0 | BY3: Ativo
B4: Demurrage | C4: Back to back | D4: LANGE TERMOPLASTICOS LTDA. | E4: LANGE TERMOPLASTICOS LTDA. | G4: 45228.333 | H4: DEMU0064-24 | I4: 45292 | J4: FOB | K4: ONEYTA3RA6821300 | L4: 45485.368 | M4: 45485.368 | N4: Desembarcado | O4: ONE | P4: KDSY23100066 | Q4: QINGDAO | S4: SEASPAN BEYOND | T4: NAVEGANTES | U4: SEASPAN OSPREY | V4: 93.244.861/0001-04 | X4: WINNING TRADING S.A. (RO) | Y4: NÃO UTILIZAR (STAR TRANS CARGO S.L.) | Z4: OE1026/23 + ILOG 3597/23 + PF004164/23 + IM1750-23 | AA4: Collect | AB4: DEMU0064-24 | AE4: Sem pagamento | AF4: Sem recebimento | AG4: Sem acerto com agente | AH4: Não aplicável | AL4: 0 | AN4: FCL | AO4: 0 | AP4: 1 | AQ4: 40 HIGH CUBE | AR4: 0 | AT4: 45770 | AU4: =MONTH(AT4) -> 4 | AV4: Falso | AW4: LEADER LOGISTICS LTDA FILIAL ITJ | AZ4: PF005190/23-02 | BA4: TRHU8243140 | BB4: Matheus Bourscheid | BE4: 525 | BF4: 3249.61 | BG4: 675 | BH4: 675 | BI4: 1200 | BJ4: 1200 | BL4: 45758.67 | BM4: 4151.25 | BN4: 4151.25 | BO4: 7400.86 | BP4: 7400.86 | BQ4: 45289.333 | BS4: 2 | BV4: Falso | BX4: 0 | BY4: Ativo
A5: 1 | B5: Marítimo importação | C5: Back to back | D5: VOLCOM DISTRIBUIDORA DE PECAS LTDA | E5: VOLCOM DISTRIBUIDORA DE PECAS LTDA | F5: Sampa International | G5: 45556 | H5: IM1507-24 | I5: 45624 | J5: FOB | K5: IST/ANR/00453 | L5: 45538.356 | M5: 45538.356 | N5: Desembarcado | O5: ECU WORLDWIDE LOGISTICS DO BRAZIL LTDA | P5: 24EX-004488 | Q5: ISTANBUL | S5: W KAMPALA | T5: ITAPOA | U5: MAERSK GANGES | V5: 03.981.614/0002-70 | X5: WINNING TRADING S.A. (SC) | Y5: SOLIBRA LOJISTIK HIZMETLERI A.S. | Z5: ILOG 13088/24 | AA5: Collect | AB5: 13088/24 | AE5: Pago | AF5: Recebido | AG5: Quitado | AH5: Não aplicável | AJ5: 7.12 | AK5: 1151 | AL5: 7120 | AN5: LCL | AO5: 0 | AP5: 1 | AQ5: 40 HIGH CUBE | AR5: 7.12 | AS5: 45663 | AT5: 45663 | AU5: =MONTH(AT5) -> 1 | AV5: Falso | AW5: LEADER LOGISTICS LTDA FILIAL ITJ | AZ5: PF004377/24-01 | BB5: Annie Audrien | BE5: 323.37 | BF5: 2277.74 | BG5: 1052.29 | BH5: 1052.29 | BI5: 1375.66 | BJ5: 1375.66 | BL5: 45663.631 | BM5: 6347.32 | BN5: 6347.32 | BO5: 8625.06 | BP5: 8509.65 | BQ5: 45624 | BR5: 45624 | BS5: 2 | BU5: Tracking inválido | BV5: Falso | BX5: 0 | BY5: Ativo
A6: 1 | B6: Marítimo importação | C6: Back to back | D6: FERTILIZANTES OMEGA LTDA | E6: FERTILIZANTES OMEGA LTDA | F6: JIANGXI TIANSHENG NEW MATERIALS CO.,LTD | G6: 45607 | H6: IM1837-24 | I6: 45639 | J6: FOB | K6: YSGSN241009144 | L6: 45581.671 | M6: 45581.671 | N6: Desembarcado | O6: CRAFT | P6: SWS2410054 | Q6: SHANGHAI | S6: COSCO SHIPPING ARGENTINA | T6: SANTOS | V6: 03.041.024/0001-87 | X6: FERTILIZANTES OMEGA LTDA | Y6: (LCL) SHENZHEN SMOOTHWIN INTERNATIONAL | Z6: ILOG 12476/24 | AA6: Collect | AB6: 12476/24 | AE6: Pago | AF6: Recebido | AG6: Quitado | AH6: Não aplicável | AJ6: 5.672 | AK6: 4224 | AL6: 5672 | AN6: LCL | AO6: 0 | AP6: 0 | AR6: 5.672 | AS6: 45681 | AT6: 45684 | AU6: =MONTH(AT6) -> 1 | AV6: Falso | AW6: LEADER LOGISTICS LTDA FILIAL ITJ | AZ6: PF003604/24-02 | BB6: Annie Audrien | BE6: 254.97 | BF6: 2016.54 | BG6: 1081.58 | BH6: 1081.58 | BI6: 1336.55 | BJ6: 1336.55 | BL6: 45681.411 | BM6: 6555.13 | BN6: 6555.13 | BO6: 8571.67 | BP6: 8571.67 | BS6: 0 | BU6: Tracking inativo | BV6: Falso | BX6: 0 | BY6: Ativo
A7: 1 | B7: Marítimo importação | C7: Back to back | D7: ELV FABRICACAO E COMERCIO DE MOVEIS LTDA | E7: ELV FABRICACAO E COMERCIO DE MOVEIS LTDA | F7: Shandong Hongniu Laser Equipment Co., LTD. | G7: 45567.201 | H7: IM1533-24 | I7: 45640 | J7: FOB | K7: OOLU2747356340 | L7: 45539.622 | M7: 45539.622 | N7: Desembarcado | O7: OOCL | P7: KDSY24090131 | Q7: QINGDAO | S7: CSCL URANUS | T7: PARANAGUA | U7: CMA CGM PARATY | V7: 29.766.379/0001-27 | X7: ELV FABRICACAO E COMERCIO DE MOVEIS LTDA | Y7: STAR-TRANS LOGISTICS CO. LTD | Z7: ILOG 11873/24 - PI HN-20240705DL | AA7: Collect | AB7: 11873/24 | AE7: Pago | AF7: Recebido | AG7: Quitado | AH7: Não aplicável | AJ7: 43.96 | AK7: 19860 | AL7: 43960 | AN7: FCL | AO7: 0 | AP7: 1 | AQ7: 40 HIGH CUBE | AR7: 43.96 | AS7: 45666 | AT7: 45667 | AU7: =MONTH(AT7) -> 1 | AV7: Falso | AW7: LEADER LOGISTICS LTDA FILIAL ITJ | AZ7: PF002031/24-01 | BA7: UETU5220890 | BB7: Annie Audrien | BE7: 972.82 | BF7: 6706.82 | BG7: 6551.75 | BH7: 6551.75 | BI7: 7524.57 | BJ7: 7524.57 | BL7: 45666.667 | BM7: 41100.1 | BN7: 41100.1 | BO7: 47806.92 | BP7: 47806.92 | BQ7: 45641 | BR7: 45640 | BS7: 2 | BU7: Sincronizado | BV7: Falso | BX7: 0 | BY7: Ativo
A8: 1 | B8: Marítimo importação | C8: Back to back | D8: PORTO VERDE NAUTICA LTDA | E8: PORTO VERDE NAUTICA LTDA | F8: XUZHOU SPECIAL-PURPOSE AUTOMOBILE CO., LTD. | G8: 45604 | H8: IM1767-24 | I8: 45641 | J8: FOB | K8: OOLU2749142160 | L8: 45574.456 | M8: 45574.456 | N8: Desembarcado | O8: OOCL | P8: KDSY24100144 | Q8: QINGDAO | S8: COSCO SHIPPING ARGENTINA | T8: RIO DE JANEIRO | V8: 43.003.463/0001-10 | X8: PORTO VERDE NAUTICA LTDA | Y8: STAR-TRANS LOGISTICS CO. LTD | Z8: ILOG 12556/24 - JYHJ240614 | AA8: Collect | AB8: 12556/24 | AE8: Pago | AF8: Recebido | AG8: Quitado | AH8: Não aplicável | AJ8: 42 | AK8: 5191 | AL8: 42000 | AN8: FCL | AO8: 0 | AP8: 1 | AQ8: 40 NOR | AR8: 42 | AS8: 45665 | AT8: 45665 | AU8: =MONTH(AT8) -> 1 | AV8: Falso | AW8: LEADER LOGISTICS LTDA FILIAL ITJ | AZ8: PF003542/24-02 | BA8: TGHU6993062 | BB8: Annie Audrien | BE8: 1083.54 | BF8: 6834.24 | BG8: 5601.86 | BH8: 5601.86 | BI8: 6685.4 | BJ8: 6685.4 | BL8: 45666.753 | BM8: 36069.25 | BN8: 35975.14 | BO8: 42903.49 | BP8: 42903.49 | BQ8: 45640 | BR8: 45641 | BS8: 2 | BU8: Tracking inativo | BV8: Falso | BX8: 0 | BY8: Ativo
B9: Demurrage | C9: Back to back | D9: CARGO SHIPPING SAO PAULO LTDA | E9: CARGO SHIPPING SAO PAULO LTDA | F9: LONGSAIL SUPPLY CHAIN CO.,LTD. | G9: 45257 | H9: DEMU0111-24 | I9: 45326 | J9: CFR | K9: 233061675 | L9: 45534.751 | M9: 45534.751 | N9: Desembarcado | O9: MAERSK | P9: SZES2311091 | Q9: SHANGHAI | S9: ATACAMA | T9: VITORIA | U9: LOG-IN PANTANAL | V9: 20.974.901/0001-91 | X9: CARGO SHIPPING SAO PAULO LTDA | Y9: SHENZHEN EVERSEAS INTERNATIONAL LOGISTICS CO | Z9: SPOIMP62151-23 - IM2096-23 | AA9: Prepaid | AB9: DEMU0111-24 | AE9: Sem pagamento | AF9: Sem recebimento | AG9: Sem acerto com agente | AH9: Não aplicável | AL9: 0 | AN9: FCL | AO9: 0 | AP9: 18 | AQ9: 40 FLAT RACK, 40 HIGH CUBE | AR9: 0 | AT9: 45770 | AU9: =MONTH(AT9) -> 4 | AV9: Falso | BA9: CAXU5788970, CAXU5790107, CAXU5790128, CAXU5790431, CAXU5790452, CAXU5791654, CAXU5792650, CAXU5793071, CAXU5793549, CAXU5795270, CAXU5796342, CAXU5796363, MRKU2557956, MRKU4557810, MRSU3834600, MSKU8784115, TCLU6012162, TRIU0831115 | BB9: Matheus Bourscheid | BE9: -457.57 | BF9: 100 | BG9: 2720 | BH9: 2720 | BI9: 2262.43 | BJ9: 2262.43 | BL9: 45534.748 | BM9: 13811 | BN9: 13811 | BO9: 13911 | BP9: 13911 | BQ9: 45326 | BS9: 36 | BV9: Falso | BX9: 0 | BY9: Ativo
B10: Demurrage | C10: Back to back | D10: CARGO SHIPPING SAO PAULO LTDA | E10: CARGO SHIPPING SAO PAULO LTDA | F10: LONGSAIL SUPPLY CHAIN CO.,LTD. | G10: 45294 | H10: DEMU0112-24 | I10: 45382 | J10: CFR | K10: MAEU234031716 | L10: 45534.767 | M10: 45534.767 | N10: Desembarcado | O10: MAERSK | P10: SZES2312077 | Q10: SHANGHAI | S10: MAERSK LA PAZ | T10: VITORIA | U10: LOG-IN PANTANAL | V10: 20.974.901/0001-91 | X10: CARGO SHIPPING SAO PAULO LTDA | Y10: SHENZHEN EVERSEAS INTERNATIONAL LOGISTICS CO | Z10: SPOIMP62515-23 - IM0055-24 | AA10: Prepaid | AB10: DEMU0112-24 | AE10: Sem pagamento | AF10: Sem recebimento | AG10: Sem acerto com agente | AH10: Não aplicável | AL10: 0 | AN10: FCL | AO10: 0 | AP10: 8 | AQ10: 40 FLAT RACK, 40 HIGH CUBE | AR10: 0 | AT10: 45770 | AU10: =MONTH(AT10) -> 4 | AV10: Falso | BA10: MAEU3421870, MAEU3438908, MAEU3485540, MAEU3495087, MRSU4032424, MRSU4785747, SUDU9700555, TCKU6703927 | BB10: Matheus Bourscheid | BE10: 784.37 | BF10: 6808.79 | BG10: 2340 | BH10: 2340 | BI10: 3124.37 | BJ10: 3124.37 | BM10: 12402 | BN10: 12402 | BO10: 19210.79 | BP10: 19210.79 | BQ10: 45382 | BS10: 16 | BV10: Falso | BX10: 0 | BY10: Ativo
B11: Demurrage | C11: Back to back | D11: BOLD S.A | E11: BOLD S.A | G11: 45358.875 | H11: DEMU0078-24 | I11: 45400 | J11: FOB | K11: HDMUSHAZ27244500 | L11: 45503.707 | M11: 45503.707 | N11: Desembarcado | O11: HYUNDAI | P11: KDSY24010132 | Q11: SHANGHAI | S11: HYUNDAI UNITY | T11: NAVEGANTES | V11: 04.626.152/0001-55 | X11: WINNING TRADING S.A. (SC) | Y11: REACH LOGISTICS CO., LTD | Z11: PO 85517 + OC2204/23 + IM0170-24 | AA11: Collect | AB11: DEMU0078-24 | AE11: Sem pagamento | AF11: Sem recebimento | AG11: Sem acerto com agente | AH11: Não aplicável | AJ11: 32740 | AK11: 27251.5 | AL11: 32740000 | AN11: FCL | AO11: 0 | AP11: 1 | AQ11: 40 HIGH CUBE | AR11: 27251.5 | AT11: 45758 | AU11: =MONTH(AT11) -> 4 | AV11: Falso | AW11: LEADER LOGISTICS LTDA FILIAL ITJ | AZ11: PF000906/24-01 | BA11: TCKU6103521 | BB11: Matheus Bourscheid | BE11: 1050 | BF11: 6396.18 | BG11: 2150 | BH11: 2150 | BI11: 3200 | BJ11: 3200 | BL11: 45506.607 | BM11: 12104.5 | BN11: 12104.5 | BO11: 18500.68 | BP11: 18500.68 | BQ11: 45403 | BS11: 2 | BV11: Falso | BX11: 0 | BY11: Ativo
B12: Demurrage | C12: Back to back | D12: VIDA EM GRAOS COMERCIO E INDUSTRIA DE PRODUTOS ALIMENTICIOS, IMPORTACAO E E | E12: VOX COMERCIAL IMPORTADORA E EXPORTADORA LTDA | F12: OCEAN SPRAY CRANBERRIES INC AGENCIA EN CHILE | G12: 45491 | H12: DEMU0129-24 | I12: 45535 | J12: FOB | K12: MEDUEJ930464 | L12: 45572.388 | M12: 45572.388 | N12: Desembarcado | O12: MSC MEDITERRANEAN SHIPPING DO BRASIL LTDA. | P12: BR24070031948 | Q12: CORONEL | S12: ANTHEA Y | T12: ITAPOA | U12: MSC LOS ANGELES | V12: 18.285.535/0001-11 | X12: VOX COMERCIAL IMPORTADORA E EXPORTADORA LTDA | Y12: WORLD TRANSPORT INTERNATIONAL LTDA. | Z12: VEG3612/24 - IM1030-24 | AA12: Prepaid | AB12: DEMU0129-24 | AE12: Sem pagamento | AF12: Sem recebimento | AG12: Sem acerto com agente | AH12: Não aplicável | AJ12: 43.43 | AK12: 23384 | AL12: 43430 | AN12: FCL | AO12: 0 | AP12: 1 | AQ12: 40 HIGH CUBE | AR12: 43.43 | AT12: 45694 | AU12: =MONTH(AT12) -> 2 | AV12: Falso | AZ12: PF002296/24-01 | BA12: TLLU8635663 | BB12: Matheus Bourscheid | BE12: 28 | BF12: 1104.56 | BG12: 2860 | BH12: 2860 | BI12: 2888 | BJ12: 2888 | BL12: 45677.555 | BM12: 16463.02 | BN12: 16463.02 | BO12: 17567.58 | BP12: 17567.58 | BQ12: 45536 | BS12: 2 | BU12: Tracking inativo | BV12: Falso | BX12: 0 | BY12: Ativo
B13: Demurrage | C13: Back to back | D13: ALL FOR GYM COMERCIO DE ARTIGOS ESPORTIVOS LTDA | E13: ALL FOR GYM COMERCIO DE ARTIGOS ESPORTIVOS LTDA | F13: NANTONG IRONMAN SPORTING INDUSTRIAL CO., LTD. | G13: 45536 | H13: DEMU0157-24 | I13: 45593 | J13: FOB | K13: HDMUNKGM85565100 | L13: 45622.745 | M13: 45622.745 | N13: Desembarcado | O13: HYUNDAI | P13: TCSH2408475 | Q13: NANTONG | S13: FEEDER VESSEL | T13: SANTOS | U13: HYUNDAI FORCE | V13: 53.001.146/0001-18 | X13: WINNING TRADING S.A. (RO) | Y13: XIAMEN TRANS-CHINA LOGISTICS CO. | Z13: OE0763/24 - ILOG 7891-24 - IM1345-24 | AA13: Collect | AB13: DEMU0157-24 | AE13: Sem pagamento | AF13: Sem recebimento | AG13: Sem acerto com agente | AH13: Não aplicável | AJ13: 60.57 | AK13: 12198.7 | AL13: 60570 | AN13: FCL | AO13: 0 | AP13: 1 | AQ13: 40 HIGH CUBE | AR13: 60.57 | AT13: 45664 | AU13: =MONTH(AT13) -> 1 | AV13: Falso | AW13: LEADER LOGISTICS LTDA FILIAL ITJ | AZ13: PF003029/24-01 | BA13: TIIU5010449 | BB13: Matheus Bourscheid | BE13: 1095 | BF13: 6152.5 | BG13: 705 | BH13: 705 | BI13: 1800 | BJ13: 1800 | BL13: 45639.676 | BM13: 4864.5 | BN13: 4864.5 | BO13: 11017 | BP13: 11017 | BQ13: 45594 | BS13: 2 | BU13: Tracking inativo | BV13: Falso | BX13: 0 | BY13: Ativo
B14: Demurrage | C14: Back to back | D14: BOLD S.A | E14: BOLD S.A | F14: SHANGHAI ALUMETAL DECORATIVE MATERIAL CO., LTD. | G14: 45565 | H14: DEMU0155-24 | I14: 45600 | J14: FOB | K14: NGNB40361600 | L14: 45622.621 | M14: 45622.621 | N14: Desembarcado | O14: PIL | P14: KDSY24080111 | Q14: NINGBO | S14: KOTA PURI | T14: ITAJAI | V14: 04.626.152/0001-55 | X14: BOLD S.A | Y14: REACH LOGISTICS CO., LTD | Z14: PO 91261 + ILOG 11459/24 + IM1380-24 | AA14: Collect | AB14: DEMU0155-24 | AE14: Sem pagamento | AF14: Sem recebimento | AG14: Sem acerto com agente | AH14: Não aplicável | AJ14: 35.87 | AK14: 52602 | AL14: 35870 | AN14: FCL | AO14: 0 | AP14: 2 | AQ14: 40 NOR | AR14: 52.602 | AT14: 45840 | AU14: =MONTH(AT14) -> 7 | AV14: Falso | AW14: LEADER LOGISTICS LTDA FILIAL ITJ | AZ14: PF003705/24-01 | BA14: PCIU6126819, PCIU6141602 | BB14: Matheus Bourscheid | BE14: 777.5 | BF14: 4588.09 | BG14: 330 | BH14: 330 | BI14: 1107.5 | BJ14: 1107.5 | BL14: 45758.478 | BM14: 2028.61 | BN14: 2028.61 | BO14: 6616.7 | BP14: 6616.7 | BQ14: 45598 | BS14: 4 | BU14: Tracking inativo | BV14: Falso | BX14: 0 | BY14: Ativo
B15: Demurrage | C15: Back to back | D15: AMERICAN DISTRIBUICAO LTDA | E15: AMERICAN DISTRIBUICAO LTDA | F15: ZHEJIANG ZHUOLI METAL PRODUCTS CO.,LTD | G15: 45565.804 | H15: DEMU0175-24 | I15: 45612 | J15: FOB | K15: NGP1676258 | L15: 45639.691 | M15: 45639.691 | N15: Desembarcado | O15: COMPAGNIE GENERALE MARITIME - CMA CGM | P15: ZJQRSE242109Y | Q15: NINGBO | S15: KOTA PURI | T15: SUAPE | U15: MERCOSUL SUAPE | V15: 15.150.798/0009-82 | X15: AMERICAN DISTRIBUICAO LTDA | Y15: NINGBO QR INTERNATIONAL LOGISTIC CO.,LTD | Z15: PI: ZL-LCY20240507 - IM1587-24 | AA15: Collect | AB15: DEMU0175-24 | AE15: Sem pagamento | AF15: Sem recebimento | AG15: Sem acerto com agente | AH15: Não aplicável | AJ15: 340 | AK15: 7643.3 | AL15: 340000 | AN15: FCL | AO15: 0 | AP15: 5 | AQ15: 40 HIGH CUBE | AR15: 340 | AT15: 45660 | AU15: =MONTH(AT15) -> 1 | AV15: Falso | AZ15: PF003463/24-01 | BA15: CMAU3553025, CMAU4304937, SEGU6333461, TCLU9626122, TCNU4881930 | BB15: Matheus Bourscheid | BE15: 500 | BF15: 3234.63 | BG15: 0 | BH15: 0 | BI15: 500 | BJ15: 500 | BL15: 45649.688 | BM15: 0 | BN15: 0 | BO15: 3234.63 | BP15: 3234.63 | BQ15: 45612.181 | BS15: 10 | BU15: Tracking inativo | BV15: Falso | BX15: 0 | BY15: Ativo
B16: Demurrage | C16: Back to back | D16: SANTO VINO IMPORTADORA LTDA | E16: SANTO VINO IMPORTADORA LTDA | F16: ANGELO ROCCA & FIGLI | G16: 45583 | H16: DEMU0178-24 | I16: 45619 | J16: EXW | K16: HLCUGOA241018942 | L16: 45646.658 | M16: 45646.658 | N16: Desembarcado | O16: HAPAG LLOYD | P16: 55909 - 65360 | Q16: GENOA | S16: CORCOVADO | T16: NAVEGANTES | U16: LOG-IN EVOLUTION | V16: 29.029.124/0002-62 | X16: WIN TRADING LTDA | Y16: VECTOR SPA | Z16: PART LOT IM1706-24 - IM1927-24 | AA16: Prepaid | AB16: DEMU0178-24 | AE16: Sem pagamento | AF16: Sem recebimento | AG16: Sem acerto com agente | AH16: Não aplicável | AJ16: 2 | AK16: 1782.8 | AL16: 2000 | AN16: FCL | AO16: 1 | AP16: 0 | AQ16: 20 DRY BOX | AR16: 2 | AT16: 45660 | AU16: =MONTH(AT16) -> 1 | AV16: Falso | AZ16: PF003725/24-01 | BA16: HLXU1328402 | BB16: Matheus Bourscheid | BE16: 60.65 | BF16: 453.3 | BG16: 402.31 | BH16: 402.31 | BI16: 462.96 | BJ16: 462.96 | BL16: 45646.676 | BM16: 2618.85 | BN16: 2618.85 | BO16: 3072.15 | BP16: 3072.15 | BQ16: 45619 | BS16: 1 | BU16: Tracking inativo | BV16: Falso | BX16: 0 | BY16: Ativo
A17: 1 | B17: Marítimo importação | C17: Back to back | D17: PHS EMBALAGENS LTDA | E17: PHS EMBALAGENS LTDA | F17: Jiangyin Asion WPC New Materials Co., Ltd | G17: 45606 | H17: IM1872-24 | I17: 45643 | J17: FOB | K17: SHSTS24197546 | L17: 45588.446 | M17: 45588.446 | N17: Desembarcado | O17: CHARTER LINK | P17: SWS2410073 | Q17: SHANGHAI | S17: EVER LOTUS | T17: SANTOS | V17: 40.466.606/0001-31 | X17: WINNING TRADING S.A. (RO) | Y17: (LCL) SHENZHEN SMOOTHWIN INTERNATIONAL | Z17: ILOG 12224/24 | AA17: Collect | AB17: 12224/24 | AE17: Pago | AF17: Recebido | AG17: Quitado | AH17: Não aplicável | AJ17: 8.017 | AK17: 2732 | AL17: 8017 | AN17: LCL | AO17: 0 | AP17: 0 | AR17: 8.017 | AS17: 45663 | AT17: 45663 | AU17: =MONTH(AT17) -> 1 | AV17: Falso | AW17: LEADER LOGISTICS LTDA FILIAL ITJ | AZ17: PF003947/24-01 | BA17: DFOU6152674 | BB17: Annie Audrien | BE17: 502.9 | BF17: 3351.07 | BG17: 559.08 | BH17: 559.08 | BI17: 1061.98 | BJ17: 1061.98 | BL17: 45663.683 | BM17: 3527.31 | BN17: 3527.31 | BO17: 6878.38 | BP17: 6878.38 | BQ17: 45643 | BR17: 45643 | BS17: 0 | BU17: Tracking inativo | BV17: Falso | BX17: 0 | BY17: Ativo
B18: Demurrage | C18: Back to back | D18: ENVASES SUL INDUSTRIA, COMERCIO DE EMBALAGENS LTDA | E18: ENVASES SUL INDUSTRIA, COMERCIO DE EMBALAGENS LTDA | F18: IMRO MASCHINENBAU GMBH | G18: 45582 | H18: DEMU0179-24 | I18: 45624 | J18: EXW | K18: 243910257 | L18: 45653.661 | M18: 45653.661 | N18: Desembarcado | O18: MAERSK | P18: EXP-2024/09-0027 | Q18: HAMBURG | S18: MAERSK EL PALOMAR | T18: ITAPOA | U18: MAERSK GANGES | V18: 19.328.827/0001-57 | X18: WINNING TRADING S.A. (SC) | Y18: FR8 (GERMANY) GMBH | Z18: ORBCON - ILOG 11182/24 - IM1423-24 | AA18: Collect | AB18: DEMU0179-24 | AE18: Sem pagamento | AF18: Sem recebimento | AG18: Sem acerto com agente | AH18: Não aplicável | AL18: 0 | AN18: FCL | AO18: 0 | AP18: 3 | AQ18: 40 FLAT RACK, 40 HIGH CUBE | AR18: 0 | AT18: 45663 | AU18: =MONTH(AT18) -> 1 | AV18: Falso | AW18: LEADER LOGISTICS LTDA FILIAL ITJ | AZ18: PF003139/24-01 | BA18: MAEU3423045, MAEU343 8739, TCLU5875662 | BB18: Matheus Bourscheid | BE18: 1399.47 | BF18: 9539.68 | BG18: 2001.06 | BH18: 2001.06 | BI18: 3400.53 | BJ18: 3400.53 | BL18: 45653.667 | BM18: 13025.91 | BN18: 13025.91 | BO18: 22565.59 | BP18: 22565.59 | BQ18: 45624 | BS18: 6 | BU18: Tracking inativo | BV18: Falso | BX18: 0 | BY18: Ativo
A19: 1 | B19: Marítimo importação | C19: Back to back | D19: LEADER MARKET IMPORTADORA E EXPORTADORA LTDA | E19: LEADER MARKET IMPORTADORA E EXPORTADORA LTDA | F19: GUANGDONG FARET AUTO RADIATOR CO., LTD. | G19: 45589.856 | H19: IM1770-24 | I19: 45643 | J19: FOB | K19: OOLU2748866970 | L19: 45574.633 | M19: 45574.633 | N19: Desembarcado | O19: OOCL | P19: KDSY24100056 | Q19: XINGANG | S19: COSCO EUROPE | T19: NAVEGANTES | U19: COSCO SHIPPING CHILE | V19: 14.009.305/0001-79 | X19: LEADER MARKET IMPORTADORA E EXPORTADORA LTDA | Y19: STAR-TRANS LOGISTICS CO. LTD | Z19: LD0024.24 | AA19: Collect | AB19: IM1770-24 | AE19: Pago | AF19: Recebido | AG19: Quitado | AH19: Não aplicável | AJ19: 204 | AK19: 18110 | AL19: 204000 | AN19: FCL | AO19: 0 | AP19: 3 | AQ19: 40 HIGH CUBE | AR19: 204 | AS19: 45664 | AT19: 45664 | AU19: =MONTH(AT19) -> 1 | AV19: Falso | AW19: LEADER LOGISTICS LTDA FILIAL ITJ | AZ19: PF003878/24-01 | BA19: OOCU8647015, TIIU5621453, TIIU5621469 | BB19: Annie Audrien | BE19: 2068.32 | BF19: 8031.9 | BG19: 18326.62 | BH19: 18326.62 | BI19: 20394.94 | BJ19: 20394.94 | BL19: 45664.612 | BM19: 119535.09 | BN19: 119489.78 | BO19: 127566.99 | BP19: 127566.99 | BQ19: 45643.333 | BR19: 45643 | BS19: 6 | BU19: Sincronizado | BV19: Falso | BX19: 0 | BY19: Ativo
B20: Demurrage | C20: Back to back | D20: BLK DO BRASIL COMERCIAL IMPORTADORA E EXPORTADORA LTDA | E20: BLK DO BRASIL COMERCIAL IMPORTADORA E EXPORTADORA LTDA | F20: QINGDAO HAPPY DIVISION EICOMEX IMPORT AND EXPORT LTD. | G20: 45568.082 | H20: DEMU0004-25 | I20: 45628 | J20: FOB | K20: QGD1267662 | L20: 45666.665 | M20: 45666.665 | N20: Desembarcado | O20: COMPAGNIE GENERALE MARITIME - CMA CGM | P20: KDSY24090082 | Q20: QINGDAO | S20: CMA CGM BAHIA | T20: IMBITUBA | U20: CMA CGM HONG KONG | V20: 05.275.075/0002-80 | X20: WINNING TRADING S.A. (SC) | Y20: STAR-TRANS LOGISTICS CO. LTD | Z20: QHDE240801 - ILOG 13106/24 - IM1431-24 | AA20: Collect | AB20: DEMU0004-25 | AE20: Sem pagamento | AF20: Recebido | AG20: Sem acerto com agente | AH20: Não aplicável | AJ20: 17.6 | AK20: 19267.4 | AL20: 17600 | AN20: FCL | AO20: 0 | AP20: 1 | AQ20: 40 NOR | AR20: 19.267 | AT20: 45693 | AU20: =MONTH(AT20) -> 2 | AV20: Falso | AW20: LEADER LOGISTICS LTDA FILIAL ITJ | AZ20: PF003085/24-01 | BA20: CXRU1047380 | BB20: Matheus Bourscheid | BE20: 1016 | BF20: 6410.54 | BG20: 850 | BH20: 850 | BI20: 1866 | BJ20: 1866 | BL20: 45687.386 | BM20: 5414.5 | BN20: 5414.5 | BO20: 11825.04 | BP20: 11825.04 | BQ20: 45628.542 | BS20: 2 | BU20: Tracking inativo | BV20: Falso | BX20: 0 | BY20: Ativo
B21: Demurrage | C21: Back to back | D21: BOLD S.A | E21: BOLD S.A | F21: TAIZHOU CITY YONGNING ACRYLIC PRODUCTS CO.,LTD. | G21: 45489 | H21: DEMU0005-25 | I21: 45632 | J21: FOB | K21: MEDUF6625299 | L21: 45666.684 | M21: 45666.685 | N21: Desembarcado | O21: MSC MEDITERRANEAN SHIPPING DO BRASIL LTDA. | P21: KDSY24060044 | Q21: SHANGHAI | S21: MSC EMMA | T21: NAVEGANTES | U21: LOG-IN EVOLUTION | V21: 04.626.152/0001-55 | X21: WINNING TRADING S.A. (SC) | Y21: REACH LOGISTICS CO., LTD | Z21: PO 88791 + ILOG 9732/24 + IM0902-24 | AA21: Collect | AB21: DEMU0005-25 | AE21: Sem pagamento | AF21: Sem recebimento | AG21: Sem acerto com agente | AH21: Não aplicável | AJ21: 61.43 | AK21: 52151.78 | AL21: 61430 | AN21: FCL | AO21: 0 | AP21: 2 | AQ21: 40 HIGH CUBE | AR21: 61.43 | AT21: 45727 | AU21: =MONTH(AT21) -> 3 | AV21: Falso | AW21: LEADER LOGISTICS LTDA FILIAL ITJ | AZ21: PF002602/24-01 | BA21: MSMU4064144, MSMU5437237 | BB21: Matheus Bourscheid | BE21: 1010 | BF21: 5844.64 | BG21: 990 | BH21: 990 | BI21: 2000 | BJ21: 2000 | BL21: 45667.691 | BM21: 6592.22 | BN21: 6592.22 | BO21: 12436.86 | BP21: 12436.86 | BQ21: 45632 | BS21: 4 | BU21: Tracking inativo | BV21: Falso | BX21: 0 | BY21: Ativo
B22: Demurrage | C22: Back to back | D22: ENVASES SUL INDUSTRIA, COMERCIO DE EMBALAGENS LTDA | E22: ENVASES SUL INDUSTRIA, COMERCIO DE EMBALAGENS LTDA | F22: IMRO MASCHINENBAU GMBH | G22: 45616.712 | H22: DEMU0008-25 | I22: 45637 | J22: EXW | K22: 244931046 | L22: 45672.643 | M22: 45672.643 | N22: Desembarcado | O22: MAERSK | P22: HBL026948 | Q22: HOUSTON | S22: MSC VANCOUVER | T22: ITAPOA | V22: 19.328.827/0001-57 | X22: WINNING TRADING S.A. (SC) | Y22: GLOBAL CARGO - USA | Z22: ORBCON - INV. 107266v - ILOG 11480/24 - IM1629-24 | AB22: DEMU0008-25 | AE22: Sem pagamento | AF22: Sem recebimento | AG22: Sem acerto com agente | AH22: Não aplicável | AJ22: 1.95 | AK22: 980 | AL22: 1950 | AN22: FCL | AO22: 1 | AP22: 0 | AQ22: 20 DRY BOX | AR22: 1.95 | AT22: 45679 | AU22: =MONTH(AT22) -> 1 | AV22: Falso | AW22: LEADER LOGISTICS LTDA FILIAL ITJ | AZ22: PF003443/24-02 | BA22: TIIU2154801 | BB22: Matheus Bourscheid | BE22: 1239 | BF22: 7890.98 | BG22: 300 | BH22: 300 | BI22: 1539 | BJ22: 1539 | BL22: 45672.645 | BM22: 1865.64 | BN22: 1865.64 | BO22: 9756.62 | BP22: 9756.62 | BQ22: 45637 | BS22: 1 | BU22: Tracking inativo | BV22: Falso | BX22: 0 | BY22: Ativo
A23: 1 | B23: Aéreo importação | C23: Back to back | D23: CALCADOS BEIRA RIO S/A | E23: CALCADOS BEIRA RIO S/A | F23: ATOM SPA | G23: 45634 | H23: IA0482-24 | I23: 45643 | J23: EXW | K23: 047-31889012 | L23: 45590.583 | M23: 45590.583 | N23: Desembarcado | O23: TAP | P23: 0124103655 | Q23: MALPENSA (MILAN) | T23: VIRACOPOS (CAMPINAS) | V23: 88.379.771/0030-17 | X23: CALCADOS BEIRA RIO S/A | Y23: TEC CARGO ITALIA SRL | Z23: 842/24 - ATOM - 20060489 | AA23: Prepaid | AB23: IA0482-24 | AE23: Pago | AF23: Recebido | AG23: Quitado | AH23: Desconsol. externa | AJ23: 0.912 | AK23: 118 | AL23: 152 | AM23: 152 | AN23: Aéreo | AR23: 152 | AS23: 45666 | AT23: 45667 | AU23: =MONTH(AT23) -> 1 | AV23: Falso | AW23: TWIN | BB23: Matheus Ropelato | BE23: 402.93 | BF23: 2680.21 | BG23: 964.52 | BH23: 964.52 | BI23: 1367.45 | BJ23: 1367.45 | BL23: 45666.677 | BM23: 6007.99 | BN23: 5632.91 | BO23: 8688.2 | BP23: 8688.2 | BQ23: 45657 | BR23: 45655.594 | BU23: Tracking inativo | BV23: Falso | BX23: 0 | BY23: Ativo
A24: 1 | B24: Marítimo importação | C24: Back to back | D24: FRAMA PRODUTOS DE PAPELARIA LTDA. | E24: FRAMA PRODUTOS DE PAPELARIA LTDA. | G24: 45597.717 | H24: IM1805-24 | I24: 45645 | J24: FOB | K24: GLSL24101064 | L24: 45580.331 | M24: 45580.331 | N24: Desembarcado | O24: CRAFT | P24: SWS2410047 | Q24: HONG KONG | S24: EVER FASHION | T24: RIO GRANDE | U24: LOG-IN ENDURANCE | V24: 93.762.201/0001-07 | X24: FRAMA PRODUTOS DE PAPELARIA LTDA. | Y24: SHENZHEN SMOOTHWIN INTERNATIONAL | Z24: ILOG 10608/24 | AA24: Collect | AB24: 10608/24 | AE24: Pago | AF24: Recebido | AG24: Quitado | AH24: Não aplicável | AJ24: 4.675 | AK24: 1953.6 | AL24: 4675 | AN24: LCL | AO24: 0 | AP24: 0 | AR24: 4.675 | AS24: 45660 | AT24: 45663 | AU24: =MONTH(AT24) -> 1 | AV24: Falso | AW24: LEADER LOGISTICS LTDA FILIAL ITJ | AZ24: PF003933/24-02 | BA24: AMCU9416162 | BB24: Bruna Kelsch | BE24: 236.99 | BF24: 1655.67 | BG24: 518.27 | BH24: 518.27 | BI24: 755.26 | BJ24: 755.26 | BL24: 45660.589 | BM24: 3248.47 | BN24: 3248.47 | BO24: 4904.14 | BP24: 4904.14 | BQ24: 45645.667 | BR24: 45645 | BS24: 0 | BU24: Sincronizado | BV24: Falso | BX24: 0 | BY24: Ativo
B25: Demurrage | C25: Back to back | D25: PORTO VERDE NAUTICA LTDA | E25: PORTO VERDE NAUTICA LTDA | F25: XUZHOU SPECIAL-PURPOSE AUTOMOBILE CO., LTD. | G25: 45604 | H25: DEMU0007-25 | I25: 45640 | J25: FOB | K25: OOLU2749142160 | L25: 45670.764 | M25: 45670.764 | N25: Desembarcado | O25: OOCL | P25: KDSY24100144 | Q25: QINGDAO | S25: COSCO SHIPPING ARGENTINA | T25: RIO DE JANEIRO | V25: 43.003.463/0001-10 | X25: PORTO VERDE NAUTICA LTDA | Y25: STAR-TRANS LOGISTICS CO. LTD | Z25: ILOG 12556/24 - JYHJ240614 - IM1767-24 | AA25: Collect | AB25: DEMU0007-25 | AE25: Sem pagamento | AF25: Sem recebimento | AG25: Sem acerto com agente | AH25: Não aplicável | AJ25: 42 | AK25: 5191 | AL25: 42000 | AN25: FCL | AO25: 0 | AP25: 1 | AQ25: 40 NOR | AR25: 42 | AT25: 45699 | AU25: =MONTH(AT25) -> 2 | AV25: Falso | AW25: LEADER LOGISTICS LTDA FILIAL ITJ | AZ25: PF003542/24-02 | BA25: TGHU6993062 | BB25: Matheus Bourscheid | BE25: 2650 | BF25: 16881.71 | BG25: 0 | BH25: 0 | BI25: 2650 | BJ25: 2650 | BL25: 45671.568 | BM25: 0 | BN25: 0 | BO25: 16881.71 | BP25: 16881.71 | BQ25: 45640 | BR25: 45640 | BS25: 2 | BU25: Tracking inativo | BV25: Falso | BX25: 0 | BY25: Ativo
A26: 1 | B26: Marítimo importação | C26: Back to back | D26: FUSOPAR PARAFUSOS LTDA. | E26: FUSOPAR PARAFUSOS LTDA | F26: Linkfast Technical Co., Ltd | G26: 45596.501 | H26: IM1836-24 | I26: 45645 | J26: FOB | K26: COSU6399096530 | L26: 45581.664 | M26: 45581.664 | N26: Desembarcado | O26: COSCO BRASIL | P26: KDSY24100129 | Q26: SHANGHAI | S26: CMA CGM PARATY | T26: NAVEGANTES | V26: 89.135.073/0001-02 | X26: FUSOPAR PARAFUSOS LTDA | Y26: STAR-TRANS LOGISTICS CO. LTD | Z26: INVOICE 2413047LF - 23216/24 | AA26: Prepaid | AB26: IM1836-24 | AD26: SPOT | AE26: Pago | AF26: Recebido | AG26: Quitado | AH26: Não aplicável | AJ26: 15 | AK26: 25149.04 | AL26: 15000 | AN26: FCL | AO26: 0 | AP26: 1 | AQ26: 40 NOR | AR26: 25.149 | AS26: 45673 | AT26: 45673 | AU26: =MONTH(AT26) -> 1 | AV26: Falso | AZ26: PF004014/24-02 | BA26: OERU4133593 | BB26: Annie Audrien | BE26: 191.25 | BF26: 1536.72 | BG26: 4201.03 | BH26: 4201.03 | BI26: 4392.28 | BJ26: 4392.28 | BL26: 45673.406 | BM26: 25693.47 | BN26: 25693.47 | BO26: 27230.19 | BP26: 27230.19 | BQ26: 45645 | BR26: 45645 | BS26: 2 | BU26: Sincronizado | BV26: Falso | BX26: 0 | BY26: Ativo
A27: 1 | B27: Marítimo importação | C27: Back to back | D27: N.R. BENNESBY COMERCIO DE UTENSILIOS DOMESTICOS LTDA | E27: N.R. BENNESBY COMERCIO DE UTENSILIOS DOMESTICOS LTDA | F27: PT. STONE MALL INDONESIA | G27: 45583.108 | H27: IM1761-24 | I27: 45645 | J27: FOB | K27: 245059209 | L27: 45573.742 | M27: 45573.742 | N27: Desembarcado | O27: MAERSK | P27: JKT/ITP-161024 | Q27: JAKARTA | S27: PORTO GERMENO | T27: ITAPOA | U27: MAERSK LAGUNA | V27: 37.882.316/0004-07 | X27: N.R. BENNESBY COMERCIO DE UTENSILIOS DOMESTICOS LTDA | Y27: NINGBO QR INTERNATIONAL LOGISTIC CO.,LTD | Z27: BID-005766 | AA27: Collect | AB27: IM1761-24 | AE27: Pago | AF27: Recebido | AG27: Quitado | AH27: Não aplicável | AJ27: 20 | AK27: 27900 | AL27: 20000 | AN27: FCL | AO27: 1 | AP27: 0 | AQ27: 20 DRY BOX | AR27: 27.9 | AS27: 45666 | AT27: 45667 | AU27: =MONTH(AT27) -> 1 | AV27: Falso | AZ27: PF003859/24-02 | BA27: MRKU9333599 | BB27: Annie Audrien | BE27: 91.2 | BF27: 1469.23 | BG27: 5599.62 | BH27: 5599.62 | BI27: 5690.82 | BJ27: 5690.82 | BL27: 45666.69 | BM27: 35346.15 | BN27: 35227.6 | BO27: 36815.38 | BP27: 36815.38 | BQ27: 45645.75 | BR27: 45645 | BS27: 1 | BU27: Sincronizado | BV27: Falso | BX27: 0 | BY27: Ativo
B28: Demurrage | C28: Back to back | D28: FIOLUX INDUSTRIA E COMERCIO LTDA | E28: FIOLUX INDUSTRIA E COMERCIO LTDA | F28: JIANGYIN HUAXIN PRECISION TECHNOLOGY CORPORATION | G28: 45609 | H28: DEMU0001-25 | I28: 45642 | J28: FOB | K28: 246200148 | L28: 45663.741 | M28: 45663.741 | N28: Desembarcado | O28: MAERSK | P28: KDSY24100199 | Q28: SHANGHAI | S28: ZIM THAILAND | T28: SANTOS | V28: 96.420.914/0001-80 | X28: WINNING TRADING S.A. (RO) | Y28: STAR-TRANS LOGISTICS CO. LTD | Z28: 24078W - Ilog 12672/24 - IM1922-24 | AA28: Collect | AB28: DEMU0001-25 | AE28: Sem pagamento | AF28: Sem recebimento | AG28: Sem acerto com agente | AH28: Não aplicável | AJ28: 8.59 | AK28: 25889.3 | AL28: 8590 | AN28: FCL | AO28: 0 | AP28: 1 | AQ28: 40 NOR | AR28: 25.889 | AT28: 45694 | AU28: =MONTH(AT28) -> 2 | AV28: Falso | AZ28: PF004153/24-01 | BA28: MMAU1167553 | BB28: Matheus Bourscheid | BE28: 572.5 | BF28: 3577.53 | BG28: 535 | BH28: 535 | BI28: 1107.5 | BJ28: 1107.5 | BL28: 45694.487 | BM28: 3323.63 | BN28: 3323.63 | BO28: 6901.16 | BP28: 6901.16 | BQ28: 45641 | BS28: 2 | BU28: Tracking inativo | BV28: Falso | BX28: 0 | BY28: Ativo
B29: Demurrage | C29: Back to back | D29: MAVE COMERCIO DE ACESSORIOS LTDA | E29: MAVE COMERCIO DE ACESSORIOS LTDA | F29: VALENACERE S.A . | G29: 45587.062 | H29: DEMU0014-25 | I29: 45642.937 | J29: FOB | K29: COSU6398947740 | L29: 45674.752 | M29: 45674.752 | N29: Desembarcado | O29: COSCO BRASIL | P29: KDSY24100036 | Q29: XIAMEN | S29: COSCO WELLINGTON | T29: NAVEGANTES | U29: EVER LISSOME | V29: 11.044.498/0001-00 | X29: WINNING TRADING S.A. (SC) | Y29: REACH LOGISTICS CO., LTD | Z29: ILOG 10951/24 - IM1754-24 | AA29: Collect | AB29: DEMU0014-25 | AE29: Sem pagamento | AF29: Sem recebimento | AG29: Sem acerto com agente | AH29: Não aplicável | AJ29: 159 | AK29: 75609 | AL29: 159000 | AN29: FCL | AO29: 0 | AP29: 3 | AQ29: 40 NOR | AR29: 159 | AT29: 45693 | AU29: =MONTH(AT29) -> 2 | AV29: Falso | AW29: LEADER LOGISTICS LTDA FILIAL ITJ | AZ29: PF003858/24-01 | BA29: SEGU9477631, TEMU9329369, TTNU8075642 | BB29: Matheus Bourscheid | BE29: 7220 | BF29: 44802.09 | BG29: 3380 | BH29: 3380 | BI29: 10600 | BJ29: 10600 | BL29: 45692.65 | BM29: 20787 | BN29: 20787 | BO29: 65589.09 | BP29: 65589.09 | BQ29: 45642.708 | BS29: 6 | BU29: Tracking inativo | BV29: Falso | BX29: 0 | BY29: Ativo
A30: 1 | B30: Marítimo importação | C30: Back to back | D30: GL IMPORTADORA LTDA | E30: GL IMPORTADORA LTDA | F30: YIWU JIN-JACK IMPORT AND EXPORT CO., LTD. | G30: 45599.737 | H30: IM1772-24 | I30: 45645 | J30: FOB | K30: OOLU2153179940 | L30: 45575.636 | M30: 45575.636 | N30: Desembarcado | O30: OOCL | P30: KDSY24100161 | Q30: NINGBO | S30: CMA CGM PARATY | T30: NAVEGANTES | V30: 51.816.157/0002-01 | X30: WINNING TRADING S.A. (SC) | Y30: STAR-TRANS LOGISTICS CO. LTD | Z30: ILOG 12483/24 | AA30: Collect | AB30: 12483/24 | AE30: Pago | AF30: Recebido | AG30: Quitado | AH30: Não aplicável | AJ30: 66.98 | AK30: 17454.05 | AL30: 66980 | AN30: FCL | AO30: 0 | AP30: 1 | AQ30: 40 HIGH CUBE | AR30: 66.98 | AS30: 45672 | AT30: 45672 | AU30: =MONTH(AT30) -> 1 | AV30: Falso | AW30: LEADER LOGISTICS LTDA FILIAL ITJ | AZ30: PF003811/24-01 | BA30: OOLU6833589 | BB30: Annie Audrien | BE30: 811.94 | BF30: 6517.44 | BG30: 6235.71 | BH30: 6235.71 | BI30: 7047.65 | BJ30: 7047.65 | BL30: 45678.63 | BM30: 39245.08 | BN30: 39245.08 | BO30: 45762.52 | BP30: 45762.52 | BQ30: 45645 | BR30: 45645 | BS30: 2 | BU30: Sincronizado | BV30: Falso | BX30: 0 | BY30: Ativo
B31: Demurrage | C31: Back to back | D31: MAVE COMERCIO DE ACESSORIOS LTDA | E31: MAVE COMERCIO DE ACESSORIOS LTDA | F31: VALENACERE S.A . | G31: 45594.248 | H31: DEMU0013-25 | I31: 45643 | J31: FOB | K31: COSU6399757640 | L31: 45674.734 | M31: 45674.734 | N31: Desembarcado | O31: COSCO BRASIL | P31: KDSY24100130 | Q31: XIAMEN | S31: CSCL EAST CHINA SEA | T31: NAVEGANTES | U31: COSCO SHIPPING CHILE | V31: 11.044.498/0001-00 | X31: WINNING TRADING S.A. (SC) | Y31: STAR-TRANS LOGISTICS CO. LTD | Z31: ILOG 11741/24 - PO E240903011 - IM1883-24 | AA31: Collect | AB31: DEMU0013-25 | AE31: Sem pagamento | AF31: Sem recebimento | AG31: Sem acerto com agente | AH31: Não aplicável | AJ31: 159 | AK31: 75521.6 | AL31: 159000 | AN31: FCL | AO31: 0 | AP31: 3 | AQ31: 40 HIGH CUBE | AR31: 159 | AT31: 45693 | AU31: =MONTH(AT31) -> 2 | AV31: Falso | AW31: LEADER LOGISTICS LTDA FILIAL ITJ | AZ31: PF004010/24-01 | BA31: DFSU7167483, FSCU9344916, OOCU6528125 | BB31: Matheus Bourscheid | BE31: 1750 | BF31: 10891.23 | BG31: 0 | BH31: 0 | BI31: 1750 | BJ31: 1750 | BL31: 45691.373 | BM31: 0 | BN31: 0 | BO31: 10891.23 | BP31: 10891.23 | BQ31: 45643.333 | BS31: 6 | BU31: Tracking inativo | BV31: Falso | BX31: 0 | BY31: Ativo
A32: 1 | B32: Marítimo importação | C32: Back to back | D32: PHG MATERIAIS PARA CONSTRUCAO LTDA | E32: PHG MATERIAIS PARA CONSTRUCAO LTDA | F32: Huzhou Mizudahope Bioscience CO., LTD | G32: 45599.737 | H32: IM1464-24 | I32: 45645.778 | J32: FOB | K32: OOLU2153401980 | L32: 45531.44 | M32: 45531.44 | N32: Desembarcado | O32: OOCL | P32: KDSY24090122D | Q32: NINGBO | S32: CMA CGM PARATY | T32: NAVEGANTES | V32: 26.021.460/0001-90 | X32: WINNING TRADING S.A. (SC) | Y32: STAR-TRANS LOGISTICS CO. LTD | Z32: ILOG 11540/24 - PI NO.: 10/2024-E | AA32: Collect | AB32: 11540/24 | AE32: Pago | AF32: Recebido | AG32: Sem acerto com agente | AH32: Não aplicável | AJ32: 11.11 | AK32: 5044.2 | AL32: 11110 | AN32: FCL | AO32: 0 | AP32: 1 | AQ32: 40 HIGH CUBE | AR32: 11.11 | AS32: 45667 | AT32: 45673 | AU32: =MONTH(AT32) -> 1 | AV32: Falso | AW32: LEADER LOGISTICS LTDA FILIAL ITJ | AZ32: PF003258/24-01 | BA32: FCIU9625180 | BB32: Matheus Ropelato | BE32: 349.59 | BF32: 2406.59 | BG32: 1107.71 | BH32: 1107.71 | BI32: 1457.3 | BJ32: 1457.3 | BL32: 45670.464 | BM32: 7056.11 | BN32: 7056.11 | BO32: 9462.7 | BP32: 9462.7 | BQ32: 45645.778 | BR32: 45645.778 | BS32: 2 | BU32: Sincronizado | BV32: Falso | BX32: 0 | BY32: Ativo
A33: 1 | B33: Marítimo importação | C33: Back to back | D33: JMC INDUSTRIA DE MATERIAIS DE CONSTRUCAO LTDA | E33: JMC INDUSTRIA DE MATERIAIS DE CONSTRUCAO LTDA | F33: Huzhou Mizudahope Bioscience CO., LTD | G33: 45599.737 | H33: IM1463-24 | I33: 45645.778 | J33: FOB | K33: OOLU2153401980 | L33: 45531.439 | M33: 45531.439 | N33: Desembarcado | O33: OOCL | P33: KDSY24090122C | Q33: NINGBO | S33: CMA CGM PARATY | T33: NAVEGANTES | V33: 25.355.203/0001-21 | X33: WINNING TRADING S.A. (SC) | Y33: STAR-TRANS LOGISTICS CO. LTD | Z33: ILOG 11539/24 - PI NO.: 10/2024-C | AA33: Collect | AB33: 11539/24 | AE33: Pago | AF33: Recebido | AG33: Sem acerto com agente | AH33: Não aplicável | AJ33: 8.93 | AK33: 4021.2 | AL33: 8930 | AN33: FCL | AO33: 0 | AP33: 1 | AQ33: 40 HIGH CUBE | AR33: 8.93 | AS33: 45674 | AT33: 45674 | AU33: =MONTH(AT33) -> 1 | AV33: Falso | AW33: LEADER LOGISTICS LTDA FILIAL ITJ | AZ33: PF003258/24-01 | BA33: FCIU9625180 | BB33: Matheus Ropelato | BE33: 311.17 | BF33: 2130.34 | BG33: 890.37 | BH33: 890.37 | BI33: 1201.54 | BJ33: 1201.54 | BL33: 45670.463 | BM33: 5671.63 | BN33: 5671.63 | BO33: 7801.97 | BP33: 7801.97 | BQ33: 45645.778 | BR33: 45645.778 | BS33: 2 | BU33: Sincronizado | BV33: Falso | BX33: 0 | BY33: Ativo
A34: 1 | B34: Marítimo importação | C34: Back to back | D34: ARGA 10 INDUSTRIA E COMERCIO DE MATERIAIS DE CONSTRUCAO LTDA | E34: ARGA 10 INDUSTRIA E COMERCIO DE MATERIAIS DE CONSTRUCAO LTDA | F34: Huzhou Mizudahope Bioscience CO., LTD | G34: 45599.737 | H34: IM1454-24 | I34: 45645.778 | J34: FOB | K34: OOLU2153401980 | L34: 45530.761 | M34: 45530.761 | N34: Desembarcado | O34: OOCL | P34: KDSY24090122A | Q34: NINGBO | S34: CMA CGM PARATY | T34: NAVEGANTES | V34: 27.046.830/0001-06 | X34: WINNING TRADING S.A. (SC) | Y34: STAR-TRANS LOGISTICS CO. LTD | Z34: ILOG 11538/24 - PI NO.: 10/2024-A | AA34: Collect | AB34: 11538/24 | AE34: Pago | AF34: Recebido | AG34: Sem acerto com agente | AH34: Não aplicável | AJ34: 17.66 | AK34: 8027.4 | AL34: 17660 | AN34: FCL | AO34: 0 | AP34: 1 | AQ34: 40 HIGH CUBE | AR34: 17.66 | AS34: 45667 | AT34: 45673 | AU34: =MONTH(AT34) -> 1 | AV34: Falso | AW34: LEADER LOGISTICS LTDA FILIAL ITJ | AZ34: PF003258/24-01 | BA34: FCIU9625180 | BB34: Matheus Ropelato | BE34: 464.94 | BF34: 3236.12 | BG34: 1760.79 | BH34: 1760.79 | BI34: 2225.73 | BJ34: 2225.73 | BL34: 45670.458 | BM34: 11216.22 | BN34: 11216.23 | BO34: 14452.34 | BP34: 14452.34 | BQ34: 45645.778 | BR34: 45645.778 | BS34: 2 | BU34: Sincronizado | BV34: Falso | BX34: 0 | BY34: Ativo
B35: Demurrage | C35: Back to back | D35: GL IMPORTADORA LTDA | E35: GL IMPORTADORA LTDA | F35: YIWU JIN-JACK IMPORT AND EXPORT CO., LTD. | G35: 45599.737 | H35: DEMU0016-25 | I35: 45645 | J35: FOB | K35: OOLU2153179940 | L35: 45678.623 | M35: 45678.623 | N35: Desembarcado | O35: OOCL | P35: KDSY24100161 | Q35: NINGBO | S35: CMA CGM PARATY | T35: NAVEGANTES | V35: 51.816.157/0002-01 | X35: WINNING TRADING S.A. (SC) | Y35: STAR-TRANS LOGISTICS CO. LTD | Z35: ILOG 12483/24 - IM1772-24 | AA35: Collect | AB35: DEMU0016-25 | AE35: Sem pagamento | AF35: Sem recebimento | AG35: Sem acerto com agente | AH35: Não aplicável | AJ35: 66.98 | AK35: 17454.05 | AL35: 66980 | AN35: FCL | AO35: 0 | AP35: 1 | AQ35: 40 HIGH CUBE | AR35: 66.98 | AT35: 45680 | AU35: =MONTH(AT35) -> 1 | AV35: Falso | AW35: LEADER LOGISTICS LTDA FILIAL ITJ | AZ35: PF003811/24-01 | BA35: OOLU6833589 | BB35: Matheus Bourscheid | BE35: 1580 | BF35: 10201.94 | BG35: 1120 | BH35: 1120 | BI35: 2700 | BJ35: 2700 | BL35: 45678.64 | BM35: 6932.8 | BN35: 6932.8 | BO35: 17134.74 | BP35: 17134.74 | BQ35: 45645 | BS35: 2 | BU35: Tracking inativo | BV35: Falso | BX35: 0 | BY35: Ativo
A36: 1 | B36: Marítimo importação | C36: Back to back | D36: ARGABRUS INDUSTRIA E COMERCIO LTDA | E36: ARGABRUS INDUSTRIA E COMERCIO LTDA | F36: Huzhou Mizudahope Bioscience CO., LTD | G36: 45599.737 | H36: IM1462-24 | I36: 45645.778 | J36: FOB | K36: OOLU2153401980 | L36: 45531.437 | M36: 45531.437 | N36: Desembarcado | O36: OOCL | P36: KDSY24090122B | Q36: NINGBO | S36: CMA CGM PARATY | T36: NAVEGANTES | V36: 26.696.696/0001-26 | X36: WINNING TRADING S.A. (SC) | Y36: STAR-TRANS LOGISTICS CO. LTD | Z36: ILOG 11537/24 - PI NO.: 10/2024-B | AA36: Collect | AB36: 11537/24 | AE36: Pago | AF36: Recebido | AG36: Quitado | AH36: Não aplicável | AJ36: 22.81 | AK36: 10305 | AL36: 22810 | AN36: FCL | AO36: 0 | AP36: 1 | AQ36: 40 HIGH CUBE | AR36: 22.81 | AS36: 45667 | AT36: 45671 | AU36: =MONTH(AT36) -> 1 | AV36: Falso | AW36: LEADER LOGISTICS LTDA FILIAL ITJ | AZ36: PF003258/24-01 | BA36: FCIU9625180 | BB36: Matheus Ropelato | BE36: 455.63 | BF36: 3278.25 | BG36: 2374.26 | BH36: 2374.26 | BI36: 2829.89 | BJ36: 2829.89 | BL36: 45670.463 | BM36: 15097.07 | BN36: 15097.07 | BO36: 18375.32 | BP36: 18375.32 | BQ36: 45645.778 | BR36: 45645.778 | BS36: 2 | BU36: Sincronizado | BV36: Falso | BX36: 0 | BY36: Ativo
A37: 1 | B37: Marítimo importação | C37: Back to back | D37: DENNIS FAUSTO DE SOUZA | E37: DENNIS FAUSTO DE SOUZA | F37: VALENACERE S.A . | G37: 45617 | H37: IM1831-24 | I37: 45646 | J37: FOB | K37: GLSL24100959 | L37: 45581.592 | M37: 45581.592 | N37: Desembarcado | O37: CRAFT | P37: SWS2410059 | Q37: SHENZHEN | S37: MSC AINO | T37: SANTOS | V37: 09.496.414/0001-28 | X37: DENNIS FAUSTO DE SOUZA | Y37: (LCL) SHENZHEN SMOOTHWIN INTERNATIONAL | Z37: ILOG 11630/24 | AA37: Collect | AB37: 11630/24 | AE37: Pago | AF37: Recebido | AG37: Quitado | AH37: Não aplicável | AJ37: 18.478 | AK37: 2013 | AL37: 18478 | AN37: LCL | AO37: 0 | AP37: 0 | AR37: 18.478 | AS37: 45666 | AT37: 45672 | AU37: =MONTH(AT37) -> 1 | AV37: Falso | AW37: LEADER LOGISTICS LTDA FILIAL ITJ | AZ37: PF003974/24-01 | BB37: Annie Audrien | BE37: 635.07 | BF37: 4727.26 | BG37: 3063.54 | BH37: 3063.54 | BI37: 3705.43 | BJ37: 3698.61 | BL37: 45666.729 | BM37: 19219.47 | BN37: 19219.47 | BO37: 23946.73 | BP37: 23903.23 | BQ37: 45648 | BR37: 45646 | BS37: 0 | BU37: Tracking inativo | BV37: Falso | BX37: 0 | BY37: Ativo
A38: 1 | B38: Marítimo importação | C38: Back to back | D38: BKZA COMERCIO DE UTILIDADES LTDA | E38: BKZA COMERCIO DE UTILIDADES LTDA | F38: ANJI NAISI FURNITURE CO.,LTD | G38: 45590.007 | H38: IM1760-24 | I38: 45646 | J38: FOB | K38: COSU6398192630 | L38: 45573.686 | M38: 45573.686 | N38: Desembarcado | O38: COSCO BRASIL | P38: KDSY24100063 | Q38: SHANGHAI | S38: KOTA PELANGI | T38: PARANAGUA | V38: 39.634.307/0001-80 | X38: BKZA COMERCIO DE UTILIDADES LTDA | Y38: STAR-TRANS LOGISTICS CO. LTD | Z38: ILOG 12349/24 | AA38: Collect | AB38: 12349/24 | AD38: SPOT | AE38: Pago | AF38: Recebido | AG38: Quitado | AH38: Não aplicável | AJ38: 57 | AK38: 8550 | AL38: 57000 | AN38: FCL | AO38: 0 | AP38: 1 | AQ38: 40 NOR | AR38: 57 | AS38: 45659 | AT38: 45659 | AU38: =MONTH(AT38) -> 1 | AV38: Falso | AW38: LEADER LOGISTICS LTDA FILIAL ITJ | AZ38: PF003875/24-01 | BA38: TEMU9291005 | BB38: Annie Audrien | BE38: 606.62 | BF38: 4270.93 | BG38: 4409.09 | BH38: 4409.09 | BI38: 5015.71 | BJ38: 5015.71 | BL38: 45659.669 | BM38: 27738.83 | BN38: 27738.83 | BO38: 32009.76 | BP38: 32009.76 | BQ38: 45647 | BR38: 45646 | BS38: 2 | BU38: Sincronizado | BV38: Falso | BX38: 0 | BY38: Ativo
A39: 1 | B39: Marítimo importação | C39: Back to back | D39: IMMAC DO BRASIL COMERCIO DE MAQUINAS LTDA | E39: IMMAC DO BRASIL COMERCIO DE MAQUINAS LTDA | F39: FOSHAN SAMFACC ROBOT CO., LTD | G39: 45606.217 | H39: IM1834-24 | I39: 45646 | J39: FOB | K39: CANM64512600 | L39: 45581.64 | M39: 45581.64 | N39: Desembarcado | O39: HYUNDAI | P39: KDSY24100150 | Q39: SHEKOU | S39: HYUNDAI TOKYO | T39: RIO GRANDE | V39: 15.711.899/0001-28 | X39: IMMAC DO BRASIL COMERCIO DE MAQUINAS LTDA | Y39: STAR-TRANS LOGISTICS CO. LTD | Z39: ILOG 12537/24 - BORUNTE + SAMFACC | AA39: Collect | AB39: 12537/24 | AE39: Pago | AF39: Recebido | AG39: Quitado | AH39: Não aplicável | AJ39: 49.244 | AK39: 11780 | AL39: 49244 | AN39: FCL | AO39: 0 | AP39: 2 | AQ39: 40 HIGH CUBE | AR39: 49.244 | AS39: 45673 | AT39: 45673 | AU39: =MONTH(AT39) -> 1 | AV39: Falso | AW39: LEADER LOGISTICS LTDA FILIAL ITJ | AZ39: PF004023/24-01 | BA39: CAAU5142080 | BB39: Annie Audrien | BE39: 445.96 | BF39: 2203.8 | BG39: 11890.28 | BH39: 11890.28 | BI39: 12336.24 | BJ39: 12336.24 | BL39: 45673.403 | BM39: 76082.42 | BN39: 75951.31 | BO39: 78286.22 | BP39: 78286.22 | BQ39: 45646 | BR39: 45646 | BS39: 4 | BU39: Sincronizado | BV39: Falso | BX39: 0 | BY39: Ativo
A40: 1 | B40: Marítimo importação | C40: Back to back | D40: FUSOPAR PARAFUSOS LTDA. | E40: FUSOPAR PARAFUSOS LTDA. | F40: T AND C FASTENER INDUSTRY CO., LTD. | G40: 45599.5 | H40: IM1806-24 | I40: 45646 | J40: FOB | K40: HDMUSHAM64012500 | L40: 45580.366 | M40: 45580.366 | N40: Desembarcado | O40: HYUNDAI | P40: SHYY24102457 | Q40: SHANGHAI | S40: HYUNDAI TOKYO | T40: RIO GRANDE | V40: 89.135.073/0001-02 | X40: FUSOPAR PARAFUSOS LTDA. | Y40: AURORA INTERNATIONAL LOGISTICS CO.,LTD. | Z40: CI-202410030 | AA40: Collect | AB40: IM1806-24 | AE40: Pago | AF40: Recebido | AG40: Quitado | AH40: Não aplicável | AJ40: 21.153 | AK40: 24897.62 | AL40: 21153 | AN40: FCL | AO40: 0 | AP40: 1 | AQ40: 40 NOR | AR40: 24.898 | AS40: 45666 | AT40: 45672 | AU40: =MONTH(AT40) -> 1 | AV40: Falso | AZ40: PF003961/24-01 | BA40: TCLU1279310 | BB40: Annie Audrien | BE40: 153.29 | BF40: 339.91 | BG40: 4280.43 | BH40: 4280.43 | BI40: 4433.72 | BJ40: 4433.72 | BL40: 45666.704 | BM40: 27543.34 | BN40: 27468.11 | BO40: 27883.25 | BP40: 27883.25 | BQ40: 45646 | BR40: 45646 | BS40: 2 | BU40: Sincronizado | BV40: Falso | BX40: 0 | BY40: Ativo
A41: 1 | B41: Marítimo importação | C41: Back to back | D41: FUSOPAR PARAFUSOS LTDA. | E41: FUSOPAR PARAFUSOS LTDA. | F41: T AND C FASTENER INDUSTRY CO., LTD. | G41: 45599.5 | H41: IM1804-24 | I41: 45646 | J41: FOB | K41: HDMUSHAM34454200 | L41: 45579.771 | M41: 45579.771 | N41: Desembarcado | O41: HYUNDAI | P41: SHYY24102461 | Q41: SHANGHAI | S41: HYUNDAI TOKYO | T41: RIO GRANDE | V41: 89.135.073/0001-02 | X41: FUSOPAR PARAFUSOS LTDA. | Y41: AURORA INTERNATIONAL LOGISTICS CO.,LTD. | Z41: CI-202410029 + IN-202409028 | AA41: Collect | AB41: IM1804-24 | AE41: Pago | AF41: Recebido | AG41: Quitado | AH41: Não aplicável | AJ41: 24.678 | AK41: 25507.1 | AL41: 24678 | AN41: FCL | AO41: 0 | AP41: 1 | AQ41: 40 NOR | AR41: 25.507 | AS41: 45666 | AT41: 45672 | AU41: =MONTH(AT41) -> 1 | AV41: Falso | AZ41: PF003962/24-01 | BA41: HDMU5560139 | BB41: Annie Audrien | BE41: 163.29 | BF41: 402.8 | BG41: 4270.43 | BH41: 4270.43 | BI41: 4433.72 | BJ41: 4433.72 | BL41: 45666.703 | BM41: 27480.45 | BN41: 27410.24 | BO41: 27883.25 | BP41: 27883.25 | BQ41: 45646 | BR41: 45646 | BS41: 2 | BU41: Sincronizado | BV41: Falso | BX41: 0 | BY41: Ativo
A42: 1 | B42: Marítimo importação | C42: Back to back | D42: FRAMA PRODUTOS DE PAPELARIA LTDA. | E42: FRAMA PRODUTOS DE PAPELARIA LTDA. | F42: SHANTOU CITY CHAOYANG AREA MEICHANG PLASTICS CO., LTD. | G42: 45612.83 | H42: IM1660-24 | I42: 45646.532 | J42: FOB | K42: GSINRIG241002744 | L42: 45559.646 | M42: 45559.646 | N42: Desembarcado | O42: CRAFT | P42: SWS2409116 | Q42: SINGAPORE | S42: PARANAGUA EXPRESS | T42: RIO GRANDE | U42: PARANAGUA EXPRESS | V42: 93.762.201/0001-07 | X42: FRAMA PRODUTOS DE PAPELARIA LTDA. | Y42: (LCL) SHENZHEN SMOOTHWIN INTERNATIONAL | Z42: ILOG 10607/24 | AA42: Collect | AB42: 10607/24 | AE42: Pago | AF42: Recebido | AG42: Quitado | AH42: Não aplicável | AJ42: 13.301 | AK42: 2081.84 | AL42: 13301 | AN42: LCL | AO42: 0 | AP42: 0 | AR42: 13.301 | AS42: 45660 | AT42: 45663 | AU42: =MONTH(AT42) -> 1 | AV42: Falso | AW42: LEADER LOGISTICS LTDA FILIAL ITJ | AZ42: PF003638/24-01 | BA42: MORU1103850 | BB42: Bruna Kelsch | BE42: 256.37 | BF42: 1883.97 | BG42: 2460.78 | BH42: 2460.78 | BI42: 2717.15 | BJ42: 2717.15 | BL42: 45660.588 | BM42: 15456.58 | BN42: 15456.58 | BO42: 17340.55 | BP42: 17340.55 | BQ42: 45646.532 | BR42: 45646.532 | BS42: 0 | BU42: Sincronizado | BV42: Falso | BX42: 0 | BY42: Ativo
B43: Demurrage | C43: Back to back | D43: PHG MATERIAIS PARA CONSTRUCAO LTDA | E43: PHG MATERIAIS PARA CONSTRUCAO LTDA | F43: Huzhou Mizudahope Bioscience CO., LTD | G43: 45599.737 | H43: DEMU0011-25 | I43: 45645.778 | J43: FOB | K43: OOLU2153401980 | L43: 45673.464 | M43: 45673.464 | N43: Desembarcado | O43: OOCL | P43: KDSY24090122D | Q43: NINGBO | S43: CMA CGM PARATY | T43: NAVEGANTES | V43: 26.021.460/0001-90 | X43: WINNING TRADING S.A. (SC) | Y43: STAR-TRANS LOGISTICS CO. LTD | Z43: IM1454-24 (ILOG:11538/24) - IM1462-24 (ILOG: 11537/24) - IM1463-24 (ILOG: 11539/24) - IM1464-24 (ILOG: 11540/24) | AA43: Collect | AB43: DEMU0011-25 | AE43: Sem pagamento | AF43: Sem recebimento | AG43: Sem acerto com agente | AH43: Não aplicável | AJ43: 11.11 | AK43: 5044.2 | AL43: 11110 | AN43: FCL | AO43: 0 | AP43: 1 | AQ43: 40 HIGH CUBE | AR43: 11.11 | AT43: 45673 | AU43: =MONTH(AT43) -> 1 | AV43: Falso | AW43: LEADER LOGISTICS LTDA FILIAL ITJ | AZ43: PF003258/24-01 | BA43: FCIU9625180 | BB43: Matheus Bourscheid | BE43: 1250 | BF43: 7924.48 | BG43: 0 | BH43: 0 | BI43: 1250 | BJ43: 1250 | BL43: 45673.559 | BM43: 0 | BN43: 0 | BO43: 7924.48 | BP43: 7924.48 | BQ43: 45645.778 | BS43: 2 | BU43: Tracking inativo | BV43: Falso | BX43: 0 | BY43: Ativo
A44: 1 | B44: Marítimo importação | C44: Back to back | D44: ROL MAR METALURGICA LTDA | E44: ROL MAR METALURGICA LTDA | F44: WUHAN KEJIA MACHINERY AND ELECTRICAL IMP. AND EXP.CO..LTD | G44: 45603.256 | H44: IM1794-24 | I44: 45646.532 | J44: FOB | K44: ONEYSH4UZA449800 | L44: 45579.697 | M44: 45579.697 | N44: Desembarcado | O44: ONE | P44: KDSY24100111 | Q44: SHANGHAI | S44: PARANAGUA EXPRESS | T44: RIO GRANDE | U44: PARANAGUA EXPRESS | V44: 87.076.519/0001-31 | X44: ROL MAR METALURGICA LTDA | Y44: STAR-TRANS LOGISTICS CO. LTD | Z44: ILOG 12645/24 | AA44: Collect | AB44: 12645/24 | AE44: Pago | AF44: Recebido | AG44: Quitado | AH44: Não aplicável | AJ44: 15 | AK44: 16761 | AL44: 15000 | AN44: FCL | AO44: 0 | AP44: 1 | AQ44: 40 NOR | AR44: 16.761 | AS44: 45665 | AT44: 45665 | AU44: =MONTH(AT44) -> 1 | AV44: Falso | AW44: LEADER LOGISTICS LTDA FILIAL ITJ | AZ44: PF003698/24-01 | BA44: ONEU9272541 | BB44: Annie Audrien | BE44: 172.31 | BF44: 881.61 | BG44: 4574.09 | BH44: 4574.09 | BI44: 4746.4 | BJ44: 4746.4 | BL44: 45665.378 | BM44: 29409.46 | BN44: 29389.62 | BO44: 30291.07 | BP44: 30291.07 | BQ44: 45646.532 | BR44: 45646.532 | BS44: 2 | BU44: Sincronizado | BV44: Falso | BX44: 0 | BY44: Ativo
A45: 1 | B45: Aéreo importação | C45: Back to back | D45: SEIREN DO BRASIL INDUSTRIA TEXTIL LTDA | E45: SEIREN DO BRASIL INDUSTRIA TEXTIL LTDA | F45: LAWER S.P.A. | G45: 45646 | H45: IA0537-24 | I45: 45647 | J45: EXW | K45: 020-54680452 | L45: 45630.723 | M45: 45630.723 | N45: Desembarcado | O45: LUFTHANSA CARGO | P45: 0124103799 | Q45: MALPENSA (MILAN) | T45: VIRACOPOS (CAMPINAS) | V45: 43.651.066/0001-54 | X45: SEIREN DO BRASIL INDUSTRIA TEXTIL LTDA | Y45: TEC CARGO ITALIA SRL | Z45: ILOG 13263/24 | AA45: Prepaid | AB45: 13263/24 | AE45: Pago | AF45: Recebido | AG45: Quitado | AH45: Desconsolidado | AJ45: 0.034 | AK45: 5.6 | AL45: 5.688 | AM45: 6 | AN45: Aéreo | AR45: 5.688 | AS45: 45659 | AT45: 45659 | AU45: =MONTH(AT45) -> 1 | AV45: Falso | AW45: LEADER LOGISTICS LTDA FILIAL ITJ | AZ45: PF004621/24-01 | BB45: Annie Audrien | BE45: 140.24 | BF45: 959.43 | BG45: 480.8 | BH45: 480.8 | BI45: 621.04 | BJ45: 621.04 | BL45: 45665.484 | BM45: 3215.71 | BN45: 2818.89 | BO45: 4175.14 | BP45: 4175.14 | BQ45: 45647 | BR45: 45647 | BT45: (Não informado) | BU45: Tracking inativo | BV45: Falso | BX45: 0 | BY45: Ativo
A46: 1 | B46: Aéreo importação | C46: Back to back | D46: CALCADOS BEIRA RIO S/A | E46: CALCADOS BEIRA RIO S/A | F46: VALCOMELTON, S.L.U | G46: 45642 | H46: IA0524-24 | I46: 45648 | J46: EXW | K46: 118-12535386 | L46: 45623.645 | M46: 45623.645 | N46: Desembarcado | O46: TAAG - ANGOLA AIRLINES | P46: SMAD2418357 | Q46: BILBAO | T46: GUARULHOS | V46: 88.379.771/0030-17 | X46: CALCADOS BEIRA RIO S/A | Y46: JOIN THE MOMENT (ESPANHA) | Z46: 855/24 - VALCO MELTON - 517 | AA46: Prepaid | AB46: IA0524-24 | AE46: Pago | AF46: Recebido | AG46: Quitado | AH46: Desconsolidado | AJ46: 0.748 | AK46: 114 | AL46: 124.639 | AM46: 114 | AN46: Aéreo | AR46: 124.639 | AS46: 45667 | AT46: 45671 | AU46: =MONTH(AT46) -> 1 | AV46: Falso | AW46: TWIN | BB46: Matheus Ropelato | BE46: 295.21 | BF46: 2385.57 | BG46: 839.22 | BH46: 839.22 | BI46: 1134.43 | BJ46: 1134.43 | BL46: 45786.67 | BM46: 4813.55 | BN46: 4865.17 | BO46: 7199.12 | BP46: 7199.12 | BQ46: 45653.447 | BR46: 45652.441 | BU46: Tracking inativo | BV46: Falso | BX46: 0 | BY46: Ativo
A47: 1 | B47: Marítimo importação | C47: Back to back | D47: BHIO SUPPLY INDUSTRIA E COMERCIO DE EQUIPAMENTOS MEDICOS S/A | E47: BHIO SUPPLY INDUSTRIA E COMERCIO DE EQUIPAMENTOS MEDICOS S/A | F47: UNIMICRO MEDICAL SYSTEMS (SHENZHEN) CO., LTD. | G47: 45620.476 | H47: IM1972-24 | I47: 45648.713 | J47: EXW | K47: PSLSZXSTS01199 | L47: 45604.722 | M47: 45604.722 | N47: Desembarcado | O47: MAERSK | P47: SWS2411049 | Q47: YANTIAN | S47: MAERSK LANCO | T47: SANTOS | V47: 73.297.509/0001-11 | X47: WINNING TRADING S.A. (RO) | Y47: (LCL) SHENZHEN SMOOTHWIN INTERNATIONAL | Z47: UNIMICRO - 12155/24 | AA47: Collect | AB47: 12155/24 | AE47: Pago | AF47: Recebido | AG47: Quitado | AH47: Não aplicável | AJ47: 10.265 | AK47: 905.5 | AL47: 10265 | AN47: LCL | AO47: 0 | AP47: 0 | AR47: 10.265 | AS47: 45667 | AT47: 45670 | AU47: =MONTH(AT47) -> 1 | AV47: Falso | AW47: LEADER LOGISTICS LTDA FILIAL ITJ | AZ47: PF004344/24-01 | BA47: MNBU0326449 | BB47: Enila Kawely | BE47: 1014.07 | BF47: 6864.97 | BG47: 1878.53 | BH47: 1878.53 | BI47: 2892.6 | BJ47: 2892.6 | BL47: 45667.573 | BM47: 11847.98 | BN47: 11861.67 | BO47: 18712.95 | BP47: 18712.95 | BS47: 0 | BU47: Sincronizado | BV47: Falso | BX47: 0 | BY47: Ativo
A48: 1 | B48: Marítimo importação | C48: Back to back | D48: RADIMPORT IMPORTACAO E EXPORTACAO LTDA | E48: RADIMPORT IMPORTACAO E EXPORTACAO LTDA | F48: ZHEJIANG ROPAS RADIATOR CO.,LTD | G48: 45608.519 | H48: IM1945-24 | I48: 45649 | J48: FOB | K48: OOLU2153983180 | L48: 45600.634 | M48: 45600.634 | N48: Desembarcado | O48: OOCL | P48: KDSY24110014 | Q48: NINGBO | S48: COSCO SHIPPING ARGENTINA | T48: ITAPOA | V48: 33.920.493/0001-37 | X48: SAFE IMPORTADORA LTDA | Y48: STAR-TRANS LOGISTICS CO. LTD | Z48: 2x40'HC - INVOICE.: LBS2411-531 + LBS2411-532 - RIMPORT 025.24 | AA48: Collect | AB48: IM1945-24 | AE48: Pago | AF48: Recebido | AG48: Quitado | AH48: Não aplicável | AJ48: 131.33 | AK48: 9700 | AL48: 131330 | AN48: FCL | AO48: 0 | AP48: 2 | AQ48: 40 HIGH CUBE | AR48: 131.33 | AS48: 45659 | AT48: 45659 | AU48: =MONTH(AT48) -> 1 | AV48: Falso | AZ48: PF003422/24-01 | BA48: BEAU5779550, TCNU1068187 | BB48: Matheus Ropelato | BE48: 2191.48 | BF48: 15117.55 | BG48: 10878.88 | BH48: 10878.88 | BI48: 13070.36 | BJ48: 13070.36 | BL48: 45664.449 | BM48: 69958.12 | BN48: 69958.12 | BO48: 85075.67 | BP48: 85075.67 | BQ48: 45648 | BR48: 45649 | BS48: 4 | BU48: Sincronizado | BV48: Falso | BX48: 0 | BY48: Ativo
A49: 1 | B49: Marítimo importação | C49: Back to back | D49: RADIMPORT IMPORTACAO E EXPORTACAO LTDA | E49: RADIMPORT IMPORTACAO E EXPORTACAO LTDA | F49: RUIAN STYLE INTERNATIONAL TRADING CO.,LTD. | G49: 45608.519 | H49: IM1946-24 | I49: 45649 | J49: FOB | K49: OOLU2153909030 | L49: 45600.643 | M49: 45600.643 | N49: Desembarcado | O49: OOCL | P49: KDSY24110015 | Q49: NINGBO | S49: COSCO SHIPPING ARGENTINA | T49: ITAPOA | V49: 33.920.493/0001-37 | X49: SAFE IMPORTADORA LTDA | Y49: STAR-TRANS LOGISTICS CO. LTD | Z49: 2x40'HC - INVOICE NO.: HL20240601-8/9 - RIMPORT 024.24 | AA49: Collect | AB49: IM1946-24 | AE49: Pago | AF49: Recebido | AG49: Quitado | AH49: Não aplicável | AJ49: 137.26 | AK49: 12189 | AL49: 137260 | AN49: FCL | AO49: 0 | AP49: 2 | AQ49: 40 HIGH CUBE | AR49: 137.26 | AS49: 45659 | AT49: 45659 | AU49: =MONTH(AT49) -> 1 | AV49: Falso | AZ49: PF002429/24-01 | BA49: CSLU6289948, OOCU6718125 | BB49: Matheus Ropelato | BE49: 2170.76 | BF49: 14996.92 | BG49: 10878.88 | BH49: 10878.88 | BI49: 13049.64 | BJ49: 13049.64 | BL49: 45664.446 | BM49: 69943.93 | BN49: 69943.93 | BO49: 84940.85 | BP49: 84940.85 | BQ49: 45648 | BR49: 45649 | BS49: 4 | BU49: Sincronizado | BV49: Falso | BX49: 0 | BY49: Ativo
A50: 1 | B50: Aéreo importação | C50: Back to back | D50: HALO ORIGEM INDUSTRIA DE COUROS ARTESANAIS LTDA. | E50: HALO ORIGEM INDUSTRIA DE COUROS ARTESANAIS LTDA. | F50: GE.MA.TA S.P.A. | G50: 45644.5 | H50: IA0535-24 | I50: 45649 | J50: EXW | K50: 04731893024 | L50: 45630.573 | M50: 45630.573 | N50: Desembarcado | O50: TAP | P50: 240900912222 | Q50: LINATE (MILAN) | T50: GUARULHOS | V50: 08.412.083/0001-38 | X50: HALO ORIGEM INDUSTRIA DE COUROS ARTESANAIS LTDA. | Y50: ALISPED S.P.A. | Z50: AIR - IMP040/2024 - ILOG- 13399/24 | AA50: Prepaid | AB50: 13399/24 | AE50: Pago | AF50: Recebido | AG50: Quitado | AH50: Desconsolidado | AJ50: 2.152 | AK50: 281 | AL50: 360 | AM50: 360 | AN50: Aéreo | AR50: 360 | AS50: 45671 | AT50: 45672 | AU50: =MONTH(AT50) -> 1 | AV50: Falso | AW50: LEADER LOGISTICS LTDA FILIAL ITJ | AZ50: PF004641/24-01 | BB50: Tiago Schneider | BE50: 768.13 | BF50: 5899.81 | BG50: 1719.06 | BH50: 1719.06 | BI50: 2487.19 | BJ50: 2487.19 | BL50: 45671.652 | BM50: 10821.15 | BN50: 10821.15 | BO50: 16720.96 | BP50: 16720.96 | BU50: Pendente atualização dados | BV50: Falso | BX50: 0 | BY50: Ativo
A51: 1 | B51: Marítimo importação | C51: Back to back | D51: DAILY WORK INDUSTRIA COMERCIO IMPORTACAO E EXPORTACAO DE VESTUARIO E TECIDO | E51: DAILY WORK INDUSTRIA COMERCIO IMPORTACAO E EXPORTACAO DE VESTUARIO E TECIDO | F51: BOYANG PROTECTION PTE. LTD. | G51: 45603.256 | H51: IM1593-24 | I51: 45650 | J51: FOB | K51: SHAYTYO90018 | L51: 45547.712 | M51: 45547.712 | N51: Desembarcado | O51: WORLD FREIGHT 03-03 | P51: SWS2409075 | Q51: SHANGHAI | S51: PARANAGUA EXPRESS | T51: NAVEGANTES | V51: 08.239.818/0001-73 | X51: DAILY WORK INDUSTRIA COMERCIO IMPORTACAO E EXPORTACAO DE VESTUARIO E TECIDO | Y51: (LCL) SHENZHEN SMOOTHWIN INTERNATIONAL | Z51: ILOG 9888/24 + BY24F0419 | AA51: Collect | AB51: 9888/24 | AE51: Pago | AF51: Recebido | AG51: Quitado | AH51: Não aplicável | AJ51: 3.844 | AK51: 1698.5 | AL51: 3844 | AN51: LCL | AO51: 0 | AP51: 0 | AR51: 3.844 | AS51: 45660 | AT51: 45660 | AU51: =MONTH(AT51) -> 1 | AV51: Falso | AW51: LEADER LOGISTICS LTDA FILIAL ITJ | AZ51: PF003518/24-01 | BA51: ONEU1675406 | BB51: Bruna Kelsch | BE51: 197.4 | BF51: 1641.39 | BG51: 1259.29 | BH51: 1259.29 | BI51: 1458.81 | BJ51: 1456.69 | BL51: 45660.585 | BM51: 7781.4 | BN51: 7471.16 | BO51: 9422.79 | BP51: 9409.29 | BQ51: 45650 | BR51: 45650 | BS51: 0 | BU51: Sincronizado | BV51: Falso | BX51: 0 | BY51: Ativo
A52: 1 | B52: Marítimo importação | C52: Back to back | D52: MAVE COMERCIO DE ACESSORIOS LTDA | E52: MAVE COMERCIO DE ACESSORIOS LTDA | F52: VALENACERE S.A . | G52: 45585.427 | H52: IM1740-24 | I52: 45650 | J52: FOB | K52: ONEYNB4BECJ49800 | L52: 45567.69 | M52: 45567.69 | N52: Desembarcado | O52: ONE | P52: KDSY24100010 | Q52: NINGBO | S52: ONE PARANA | T52: NAVEGANTES | U52: PARANAGUA EXPRESS | V52: 11.044.498/0001-00 | X52: WINNING TRADING S.A. (SC) | Y52: STAR-TRANS LOGISTICS CO. LTD | Z52: ILOG 11136/24 - PI-NV24L011 | AA52: Collect | AB52: 11136/24 | AE52: Pago | AF52: Recebido | AG52: Quitado | AH52: Não aplicável | AJ52: 36 | AK52: 25552 | AL52: 36000 | AN52: FCL | AO52: 0 | AP52: 1 | AQ52: 40 NOR | AR52: 36 | AS52: 45660 | AT52: 45660 | AU52: =MONTH(AT52) -> 1 | AV52: Falso | AW52: LEADER LOGISTICS LTDA FILIAL ITJ | AZ52: PF003818/24-01 | BA52: ONEU9012117 | BB52: Matheus Ropelato | BE52: 568.82 | BF52: 3990.45 | BG52: 4609.75 | BH52: 4609.75 | BI52: 5178.57 | BJ52: 5178.57 | BL52: 45670.456 | BM52: 29472.44 | BN52: 29472.44 | BO52: 33462.89 | BP52: 33462.89 | BQ52: 45651 | BR52: 45650 | BS52: 2 | BU52: Sincronizado | BV52: Falso | BX52: 0 | BY52: Ativo
A53: 1 | B53: Marítimo importação | C53: Back to back | D53: N.R. BENNESBY COMERCIO DE UTENSILIOS DOMESTICOS LTDA | E53: N.R. BENNESBY COMERCIO DE UTENSILIOS DOMESTICOS LTDA | F53: PT. ANUGRAH WATU GEDE STONE TILE INDUSTRY AND QUARRY | G53: 45592.951 | H53: IM1762-24 | I53: 45650.587 | J53: FOB | K53: 245709584 | L53: 45573.753 | M53: 45573.753 | N53: Desembarcado | O53: MAERSK | P53: SMG/ITP-2711024 | Q53: SEMARANG | S53: MAERSK PORT KLANG | T53: ITAPOA | U53: MAERSK LANCO | V53: 37.882.316/0004-07 | X53: N.R. BENNESBY COMERCIO DE UTENSILIOS DOMESTICOS LTDA | Y53: NINGBO QR INTERNATIONAL LOGISTIC CO.,LTD | Z53: BID-005734 | AA53: Collect | AB53: IM1762-24 | AE53: Pago | AF53: Recebido | AG53: Quitado | AH53: Não aplicável | AK53: 27000 | AL53: 0 | AN53: FCL | AO53: 1 | AP53: 0 | AQ53: 20 DRY BOX | AR53: 27 | AS53: 45666 | AT53: 45667 | AU53: =MONTH(AT53) -> 1 | AV53: Falso | AZ53: PF003837/24-02 | BA53: MRKU7113656 | BB53: Annie Audrien | BE53: 523.33 | BF53: 4437.66 | BG53: 5743.04 | BH53: 5743.04 | BI53: 6266.37 | BJ53: 6266.37 | BL53: 45666.692 | BM53: 36327.46 | BN53: 36127.61 | BO53: 40765.12 | BP53: 40765.12 | BQ53: 45650.587 | BR53: 45650.587 | BS53: 1 | BU53: Sincronizado | BV53: Falso | BX53: 0 | BY53: Ativo
B54: Demurrage | C54: Back to back | D54: CAIMAN INDUSTRIA E COMERCIO DE MALHAS LTDA | E54: CAIMAN INDUSTRIA E COMERCIO DE MALHAS LTDA | F54: ESCARRÉ, AUTOMATIZACIÓN Y SERVICIOS, S.L. | G54: 45603.999 | H54: DEMU0009-25 | I54: 45648.9 | J54: EXW | K54: HLCUBC1241011730 | L54: 45672.667 | M54: 45672.667 | N54: Desembarcado | O54: HAPAG LLOYD | P54: SMAD2414155 | Q54: BARCELONA | S54: MSC ARICA | T54: NAVEGANTES | U54: LOG-IN EVOLUTION | V54: 75.370.437/0001-16 | X54: CAIMAN INDUSTRIA E COMERCIO DE MALHAS LTDA | Y54: JOIN THE MOMENT (ESPANHA) | Z54: ILOG 9901/24 - IM1728-24 | AB54: DEMU0009-25 | AE54: Sem pagamento | AF54: Sem recebimento | AG54: Sem acerto com agente | AH54: Não aplicável | AJ54: 29.616 | AK54: 2040 | AL54: 29616 | AN54: FCL | AO54: 1 | AP54: 0 | AQ54: 20 DRY BOX | AR54: 29.616 | AT54: 45673 | AU54: =MONTH(AT54) -> 1 | AV54: Falso | AW54: LEADER LOGISTICS LTDA FILIAL ITJ | AZ54: PF002160/24-01 | BA54: UACU3978336 | BB54: Matheus Bourscheid | BE54: 604.18 | BF54: 4041.63 | BG54: 255.63 | BH54: 255.63 | BI54: 859.81 | BJ54: 859.81 | BL54: 45672.68 | BM54: 1664 | BN54: 1664 | BO54: 5705.63 | BP54: 5705.63 | BQ54: 45648.9 | BS54: 1 | BU54: Tracking inativo | BV54: Falso | BX54: 0 | BY54: Ativo
A55: 1 | B55: Marítimo importação | C55: Back to back | D55: CALCADOS BEIRA RIO S/A | E55: CALCADOS BEIRA RIO S/A | F55: L'STRIVER TECH.(H.K.)CO.,LIMITED | G55: 45608.495 | H55: IM1895-24 | I55: 45652 | J55: FOB | K55: HDMUNBOZ49040700 | L55: 45590.806 | M55: 45590.806 | N55: Desembarcado | O55: HYUNDAI | P55: SHYY24110746 | Q55: NINGBO | S55: HYUNDAI FAITH | T55: RIO GRANDE | V55: 88.379.771/0035-21 | X55: CALCADOS BEIRA RIO S/A | Y55: AURORA INTERNATIONAL LOGISTICS CO.,LTD. | Z55: 849/24 - L'STRIVER - 2410008 | AA55: Collect | AB55: IM1895-24 | AE55: Pago | AF55: Recebido | AG55: Quitado | AH55: Não aplicável | AJ55: 65 | AK55: 25890 | AL55: 65000 | AN55: FCL | AO55: 0 | AP55: 1 | AQ55: 40 HIGH CUBE | AR55: 65 | AS55: 45659 | AT55: 45660 | AU55: =MONTH(AT55) -> 1 | AV55: Falso | AW55: Commander Logistica Ltda | BA55: TIIU6007413 | BB55: Matheus Ropelato | BE55: 280.32 | BF55: 1388.12 | BG55: 5945.9 | BH55: 5945.9 | BI55: 6226.22 | BJ55: 6226.22 | BL55: 45679.603 | BM55: 38151.93 | BN55: 38015.64 | BO55: 39540.05 | BP55: 39540.05 | BQ55: 45650 | BR55: 45652 | BS55: 2 | BU55: Sincronizado | BV55: Falso | BX55: 0 | BY55: Ativo
A56: 1 | B56: Marítimo importação | C56: Back to back | D56: CALCADOS BEIRA RIO S/A | E56: CALCADOS BEIRA RIO S/A | F56: L'STRIVER TECH.(H.K.)CO.,LIMITED | G56: 45608.495 | H56: IM1892-24 | I56: 45652 | J56: FOB | K56: HDMUNBOZ55833800 | L56: 45590.798 | M56: 45590.798 | N56: Desembarcado | O56: HYUNDAI | P56: SHYY24110742 | Q56: NINGBO | S56: HYUNDAI FAITH | T56: RIO GRANDE | V56: 88.379.771/0035-21 | X56: CALCADOS BEIRA RIO S/A | Y56: AURORA INTERNATIONAL LOGISTICS CO.,LTD. | Z56: 846/24 - L'STRIVER - 2410005 | AA56: Collect | AB56: IM1892-24 | AE56: Pago | AF56: Recebido | AG56: Quitado | AH56: Não aplicável | AJ56: 65 | AK56: 26400 | AL56: 65000 | AN56: FCL | AO56: 0 | AP56: 1 | AQ56: 40 HIGH CUBE | AR56: 65 | AS56: 45659 | AT56: 45660 | AU56: =MONTH(AT56) -> 1 | AV56: Falso | AW56: Commander Logistica Ltda | BA56: TXGU8528970 | BB56: Matheus Ropelato | BE56: 280.32 | BF56: 1388.12 | BG56: 5945.9 | BH56: 5945.9 | BI56: 6226.22 | BJ56: 6226.22 | BL56: 45674.338 | BM56: 38151.93 | BN56: 38015.64 | BO56: 39540.05 | BP56: 39540.05 | BQ56: 45650 | BR56: 45652 | BS56: 2 | BU56: Sincronizado | BV56: Falso | BX56: 0 | BY56: Ativo
